Workbook

Sheet Quote Info
B1: DELIGHT INTERNATIONAL – PRICING: QUOTE INFORMATION
B2: Fill in this sheet first. Yellow = input (blue text) · green = calculated. Markups, contingency, discount and VAT apply to every service in this workbook.
B4: QUOTATION DETAILS
B5: Quotation No.
B6: Revision
B7: Date
B8: Client
B9: Attention (client contact)
B10: Project / Plant
B11: Location / site
B12: Client enquiry / RFQ reference
B13: Prepared by
B15: CURRENCY (rates are entered in AED; the client quote is converted)
B16: Quote currency | C16: AED
B17: Currency | C17: AED per 1 unit | F17: Source
B18: AED | C18: 1 | F18: Base currency
B19: USD | C19: 3.6725 | F19: UAE central bank peg (AED 3.6725 = USD 1)
B20: SAR | C20: =3.6725/3.75 -> 0.97933333 | F20: Via USD pegs (SAR 3.75 = USD 1)
B21: OMR | C21: =3.6725/0.3845 -> 9.5513654 | F21: Via USD pegs (OMR 0.3845 = USD 1)
B22: GBP | C22: 4.92 | F22: DUQM Rev 1.0 market rate 17-Jun-2026 – update
B23: Exchange rate used (AED per 1 quote-currency unit) | C23: =INDEX(CurrRate,MATCH(QCurr,CurrU,0)) -> 1
B25: WORKING PATTERN
B26: Shift length (hours) | C26: 12 | G26: Manpower rates are per person per shift (12-hour day)
B27: Shifts per day (1 = day only, 2 = 24-hour) | C27: 2
B29: MARKUP CONTROLS (selling = cost × (1 + markup))
B30: Markup mode | C30: Simple | E30: Simple | F30: Detailed | G30: Simple = 2 markups (in-house / rented). Detailed = 5 markups.
B31: SIMPLE – In-house crew & equipment | C31: 0.3 | G31: 30% = highest of ASAB R2 (30%) and DUQM Rev 1.0 (10–30%) – edit per job
B32: SIMPLE – Rented crew & equipment, bought-in items | C32: 0.3
B33: DETAILED – In-house manpower | C33: 0.3
B34: DETAILED – Rented manpower | C34: 0.3
B35: DETAILED – In-house equipment | C35: 0.3
B36: DETAILED – Rented equipment | C36: 0.3
B37: DETAILED – Chemicals, consumables & third-party services | C37: 0.3
B39: Effective markup applied (calculated) | C39: In-house | D39: Rented | E39: Third-party
B40: Manpower | C40: =IF(QMkMode="Detailed",N(MkInMP),N(MkIn)) -> 0.3 | D40: =IF(QMkMode="Detailed",N(MkRentMP),N(MkRent)) -> 0.3 | E40: =IF(QMkMode="Detailed",N(MkCons),N(MkRent)) -> 0.3
B41: Equipment | C41: =IF(QMkMode="Detailed",N(MkInEq),N(MkIn)) -> 0.3 | D41: =IF(QMkMode="Detailed",N(MkRentEq),N(MkRent)) -> 0.3 | E41: =IF(QMkMode="Detailed",N(MkCons),N(MkRent)) -> 0.3
B42: Chemicals, consumables & services | C42: =IF(QMkMode="Detailed",N(MkCons),N(MkIn)) -> 0.3 | D42: =IF(QMkMode="Detailed",N(MkCons),N(MkRent)) -> 0.3 | E42: =IF(QMkMode="Detailed",N(MkCons),N(MkRent)) -> 0.3
B44: CONTINGENCY, DISCOUNT & VAT
B45: Contingency (% of total cost, internal risk allowance) | G45: Added to the price, not marked up
B46: Commercial discount (% of price) | G46: Applied to the price before VAT
B47: VAT (%) | C47: 0.05 | G47: UAE 5% · KSA 15% · Oman 5% · Qatar 0% – set per quotation
B49: COMMERCIAL TERMS (printed on the client quotation)
B50: Validity
B51: Payment terms
B52: Delivery / mobilisation time
B53: Exclusions
B54: Client scope / supplied by client
B55: Other notes
B57: COMPANY DETAILS (letterhead on the client quotation)
B58: Company name | C58: Delight Equipment International L.L.C.
B59: Address | C59: P.O. Box 2932, Abu Dhabi, United Arab Emirates
B60: Telephone / fax | C60: Tel: +971 2 5515641 | Fax: +971 2 5515643
B61: E-mail / website | C61: info@delightintl.ae | www.delightintl.ae
B62: Tagline | C62: MAINTENANCE SIMPLIFIED
B63: Certifications | C63: ISO 9001 · ISO 14001 · ISO 45001

Sheet Rates
B1: RATES (COST, AED, excl. markup)
B2: Values taken from ASAB CC Pricing R2 and DUQM Pricing Rev 1.0 – the higher one where both list the same item. Rented column blank = same as cost. Add items in the blank yellow rows.
B4: MANPOWER – cost per person per shift / day
B5: Grade | D5: Cost | E5: Rented cost (if different) | H5: Source / remarks
B6: Project Manager | D6: 1000 | H6: ASAB 1,000 · DUQM 1,000
B7: Project Engineer | D7: 700 | H7: ASAB 500 · DUQM 700 → highest
B8: Supervisor | D8: 500 | H8: ASAB 400 · DUQM 500 → highest
B9: Job Performer / Permit Receiver | H9: not in either sheet
B10: Safety Officer | D10: 300 | H10: DUQM
B11: Technician / Operator | D11: 400 | H11: ASAB 300 · DUQM 400 → highest
B12: Pipe Fitter | H12: not in either sheet
B13: Helper | D13: 300 | H13: ASAB 200 · DUQM 300 → highest
B14: Others | D14: 400 | H14: DUQM
B15: Decontamination Specialist | D15: 5400 | H15: DUQM (per day)
B16: Specialised Services | D16: 2400 | H16: DUQM (per day)
B17: Remote Technical Support | D17: 2250 | H17: DUQM (per day)
B25: EQUIPMENT – cost per unit per day (LS = lump sum, counted once)
B26: Equipment | C26: Unit | D26: Cost | E26: Rented cost (if different) | H26: Source / remarks
B27: Chemical circulation pump skid (SS316, VFD) | C27: day | D27: 800 | H27: ASAB
B28: Vessel circulation pump (gamma jet feed) | C28: day | D28: 800 | H28: ASAB
B29: Centrifugal pump | C29: day | D29: 1000 | H29: DUQM
B30: Drum pump | C30: day | D30: 500 | H30: DUQM
B31: Diaphragm pump & manifolds (transfer set) | C31: day | D31: 300 | H31: ASAB
B32: Diaphragm pump | C32: day | D32: 100 | H32: DUQM
B33: Manifold | C33: day | D33: 250 | H33: DUQM
B34: Chemical mixing / dosing tank 10 m³ | C34: day | D34: 150 | H34: ASAB
B35: DM water buffer tank | C35: day | D35: 150 | H35: ASAB
B36: Waste holding tank 500 bbl (~80 m³) | C36: day | D36: 400 | H36: ASAB rental
B37: Effluent tank 60 m³ | C37: day | D37: 500 | H37: DUQM
B38: Diesel boiler 2 TPH | C38: day | D38: 3000 | H38: ASAB rental
... B53: 10-point VP injection module (CORE) | C53: day | D53: 890 | H53: DUQM
B65: CHEMICALS – price per kg (or per IBC)
B66: Chemical | C66: Purity | D66: Price per kg | E66: Price per IBC | F66: IBC net content (kg) | G66: Price per kg used | H66: Source / remarks
B67: SODIUM HYDROXIDE (CAUSTIC SODA) | C67: 0.49 | D67: 3 | G67: =IF(ISNUMBER(D67),D67,IF(AND(ISNUMBER(E67),N(F67)>0),E67/F67,"")) -> 3 | H67: ASAB R2
B68: CITRIC ACID | C68: 1 | D68: 4 | G68: =IF(ISNUMBER(D68),D68,IF(AND(ISNUMBER(E68),N(F68)>0),E68/F68,"")) -> 4 | H68: ASAB R2
B69: AMMONIUM BIFLUORIDE | C69: 1 | D69: 16 | G69: =IF(ISNUMBER(D69),D69,IF(AND(ISNUMBER(E69),N(F69)>0),E69/F69,"")) -> 16 | H69: ASAB R2
B70: SODIUM META SILICATE | C70: 1 | D70: 9 | G70: =IF(ISNUMBER(D70),D70,IF(AND(ISNUMBER(E70),N(F70)>0),E70/F70,"")) -> 9 | H70: ASAB R2
B71: TRI SODIUM PHOSPHATE | C71: 1 | D71: 6 | G71: =IF(ISNUMBER(D71),D71,IF(AND(ISNUMBER(E71),N(F71)>0),E71/F71,"")) -> 6 | H71: ASAB R2
B72: INHIBITORS - RODINE & ARMOHIB | C72: 1 | D72: 12 | G72: =IF(ISNUMBER(D72),D72,IF(AND(ISNUMBER(E72),N(F72)>0),E72/F72,"")) -> 12 | H72: ASAB R2
B73: SURFACTANTS - NP-9 / MULTI CLEAN | C73: 1 | D73: 12 | G73: =IF(ISNUMBER(D73),D73,IF(AND(ISNUMBER(E73),N(F73)>0),E73/F73,"")) -> 12 | H73: ASAB R2
B74: HYDROGEN PEROXIDE (35%) | C74: 0.35 | D74: 4 | G74: =IF(ISNUMBER(D74),D74,IF(AND(ISNUMBER(E74),N(F74)>0),E74/F74,"")) -> 4 | H74: ASAB R2
B75: AMMONIA (25%) | C75: 0.25 | D75: 6 | G75: =IF(ISNUMBER(D75),D75,IF(AND(ISNUMBER(E75),N(F75)>0),E75/F75,"")) -> 6 | H75: ASAB R2
B76: SODA ASH (SODIUM CARBONATE) | C76: 1 | D76: 10 | G76: =IF(ISNUMBER(D76),D76,IF(AND(ISNUMBER(E76),N(F76)>0),E76/F76,"")) -> 10 | H76: ASAB R2
B77: HYDROCHLORIC ACID (HCl) | C77: 0.33 | D77: 2 | G77: =IF(ISNUMBER(D77),D77,IF(AND(ISNUMBER(E77),N(F77)>0),E77/F77,"")) -> 2 | H77: ASAB R2
B78: SULPHURIC ACID | C78: 0.98 | D78: 8 | G78: =IF(ISNUMBER(D78),D78,IF(AND(ISNUMBER(E78),N(F78)>0),E78/F78,"")) -> 8 | H78: ASAB R2
... B81: ANTIFOAM | C81: 1 | D81: 9 | G81: =IF(ISNUMBER(D81),D81,IF(AND(ISNUMBER(E81),N(F81)>0),E81/F81,"")) -> 9 | H81: ASAB R2
B82: CORE CLEAN VP1 | C82: 1 | E82: 17463.24 | G82: =IF(ISNUMBER(D82),D82,IF(AND(ISNUMBER(E82),N(F82)>0),E82/F82,"")) | H82: DUQM – vapour phase – enter IBC net kg
B83: CORE CLEAN 2600 | C83: 1 | E83: 35625 | G83: =IF(ISNUMBER(D83),D83,IF(AND(ISNUMBER(E83),N(F83)>0),E83/F83,"")) | H83: DUQM – steam-out / boil-out – enter IBC net kg
B84: CORE CLEAN 3010 | C84: 1 | E84: 29411.76 | G84: =IF(ISNUMBER(D84),D84,IF(AND(ISNUMBER(E84),N(F84)>0),E84/F84,"")) | H84: DUQM (ref) – enter IBC net kg
B85: CORE CLEAN 5421 | C85: 1 | E85: 33823.53 | G85: =IF(ISNUMBER(D85),D85,IF(AND(ISNUMBER(E85),N(F85)>0),E85/F85,"")) | H85: DUQM (ref) – enter IBC net kg
G86: =IF(ISNUMBER(D86),D86,IF(AND(ISNUMBER(E86),N(F86)>0),E86/F86,""))
G87: =IF(ISNUMBER(D87),D87,IF(AND(ISNUMBER(E87),N(F87)>0),E87/F87,""))
G88: =IF(ISNUMBER(D88),D88,IF(AND(ISNUMBER(E88),N(F88)>0),E88/F88,""))
G89: =IF(ISNUMBER(D89),D89,IF(AND(ISNUMBER(E89),N(F89)>0),E89/F89,""))
G90: =IF(ISNUMBER(D90),D90,IF(AND(ISNUMBER(E90),N(F90)>0),E90/F90,""))
G91: =IF(ISNUMBER(D91),D91,IF(AND(ISNUMBER(E91),N(F91)>0),E91/F91,""))
B93: CONSUMABLES & THIRD-PARTY SERVICES – cost per unit
B94: Item | C94: Unit | D94: Cost | H94: Source / remarks
B95: Waste disposal | C95: m³ | D95: 290 | H95: ASAB GMET/SQ/03002 290 · DUQM 50 (TBC) → highest
B96: Disposables / PPE | C96: person-day | D96: 150 | H96: ASAB 100 · DUQM 150 → highest
B97: Pre-engineering works | C97: person-day | D97: 1500 | H97: ASAB 500–1,500 → highest
B98: Kurita litmus paper | C98: roll | D98: 150 | H98: DUQM
B99: Chemical shipping | C99: trip | D99: 18350 | H99: ASAB (USD 5,000 × 3.67)
B100: Sea freight 40' HC (CFR Sohar, incl. VGM) | C100: container | D100: 40453.37 | H100: DUQM (£8,166.67 + £55.56) × 4.92
B101: Local co-operative fee (Al Dhafra) | C101: month | D101: 3000 | H101: ASAB (GMET quote, billed as actual)
B111: LOGISTICS – mobilisation / demobilisation (cost per trip)
B112: Vehicle | D112: Cost per trip | H112: Source / remarks
B113: 40 ft trailer | D113: 15000 | H113: ASAB 2,500 · DUQM 15,000 → highest
B114: Low-bed trailer
B115: Truck with crane (HIAB)
B116: Crew bus
B121: PERSONNEL EXTRAS
B122: Item | D122: Cost | H122: Source / remarks
B123: FAT – food, accommodation & transport (per person per day) | D123: 250 | H123: ASAB 150 · DUQM 250 → highest
B124: Accommodation – specialists (per person per day) | D124: 700 | H124: DUQM
B125: Visa (per person) | D125: 2300 | H125: DUQM
B126: Flight – return (per person) | D126: 3300 | H126: DUQM
B127: Crew visas & tickets – India (per person) | D127: 4500 | H127: DUQM
B128: Crew transport – pickup (per vehicle per day) | D128: 500 | H128: DUQM pickup

Sheet CC Settings
B1: VOLUME SETTINGS
B2: Yellow = input. Unit names, loop names and regime names feed the drop-down lists on the volume sheet.
B4: PROJECT
B5: Client | C5: =QClient -> 0
B6: Plant / Project | C6: =QProject -> 0
B7: Proposal No. | C7: =QNo -> 0
B9: Job type | C9: Chemical Cleaning | D9: Fixed for this service
B11: GENERAL
B12: Water density (water weight → volume) | C12: 1000 | D12: kg/m³
B13: Tube pitch ratio (pitch ÷ OD) | C13: 1.25 | D13: –
B14: Default circulation / solution allowance | C14: 1.15 | D14: × fill volume | F14: Solution = equipment volume × fill % × circulation (ASAB: 115%)
B15: Default no. of fills (for waste volume) | C15: 5 | D15: fills
B16: Default waste allowance | C16: 0.25 | D16: on top of fills | F16: Waste = solution × fills × (1 + allowance) (ASAB: 5 fills + 25%)
B18: DEFAULT FILL % BY EQUIPMENT TYPE (used when the Fill % cell on a row is blank)
B19: Equipment type | C19: Chemical cleaning | D19: Decontamination | F19: Method note
B20: Exchanger | C20: 1 | D20: 1 | F20: CC full volume · Decon vapour phase
B21: Piping | C21: 1 | D21: 1 | F21: CC full volume · Decon vapour phase
B22: Column | C22: 0.2 | D22: 1 | F22: CC 20% + gamma jet · Decon vapour phase (complete volume)
B23: Vessel – Vertical | C23: 0.2 | D23: 0.3 | F23: CC 20% + gamma jet · Decon boil-out 30%
B24: Vessel – Horizontal | C24: 0.2 | D24: 0.3 | F24: CC 20% + gamma jet · Decon boil-out 30%
B25: Tank | C25: 0.2 | D25: 0.3 | F25: CC 20% + gamma jet · Decon gamma-jet circulation (TO CONFIRM)
B26: Filter / Other | C26: 0.2 | D26: 0.3 | F26: CC 20% + gamma jet · Decon boil-out 30%
B27: ASAB R2 used 15% fill for vessels with gamma jetting – set per project.
B29: UNITS / TRAINS (up to 12)
B30: Unit 1 name | C30: Unit 1
B31: Unit 2 name | C31: Unit 2
B32: Unit 3 name | C32: Unit 3
B33: Unit 4 name | C33: Unit 4
B34: Unit 5 name | C34: Unit 5
B35: Unit 6 name | C35: Unit 6
B36: Unit 7 name | C36: Unit 7
B37: Unit 8 name | C37: Unit 8
B38: Unit 9 name | C38: Unit 9
B39: Unit 10 name | C39: Unit 10
B40: Unit 11 name | C40: Unit 11
B41: Unit 12 name | C41: Unit 12
B43: CHEMICAL REGIMES (up to 4; concentrations on the chemicals sheet)
B44: Regime 1 name | C44: SS
B45: Regime 2 name | C45: CS
B46: Regime 3 name | C46: Regime 3
B47: Regime 4 name | C47: Regime 4
B49: LOOPS (up to 40 – rename freely, e.g. ML-1, MV-1)
B50: Loop name (drop-down) | C50: Loop description
B51: Loop 1
B52: Loop 2
B53: Loop 3
B54: Loop 4
B55: Loop 5
B56: Loop 6
B57: Loop 7
B58: Loop 8
B59: Loop 9
B60: Loop 10
B61: Loop 11
B62: Loop 12
... B90: Loop 40

Sheet CC Volume
A1: VOLUME CALCULATION – one row per equipment, units stacked
A2: ="Job type: "&CC_JobType&" · Client: "&CC_Client&" · Plant: "&CC_Plant&" · Proposal: "&CC_ProjNo -> Job type: Chemical Cleaning · Client: 0 · Plant: 0 · Proposal: 0
A3: Yellow = input (only the columns that apply to the equipment type). Units of each dimension column are chosen in row 7. Factors left blank use the defaults on the settings sheet. Volumes in m³.
A5: ITEM | J5: PIPING | N5: SHELL / VESSEL | S5: TUBES (exchangers) | Y5: CHANNELS / BONNETS | AD5: CALCULATED (m³) | AI5: FACTORS (blank = default) | AM5: RESULT (m³)
A6: # | B6: Loop | C6: Tag No. | D6: Description / service | E6: Equipment type | F6: Chemical regime | G6: Volume basis | H6: Given volume | I6: Water weight | J6: NPS | K6: Schedule | L6: Pipe ID (if given) | M6: Pipe length | N6: Shell / vessel ID | O6: Length T/T | P6: Head 1 / shell cover | Q6: Head 2 | R6: Cone height | S6: No. of tubes | T6: Tube OD | U6: Tube ID | V6: Tube length | W6: Tube pitch | X6: Tube layout | Y6: Channel / bonnet ID | Z6: Front channel length | AA6: Front head | AB6: Rear channel length | AC6: Rear head | AD6: Tube side vol. | AE6: Shell side / vessel vol. | AF6: Piping vol. | AG6: Volume from dimensions | AH6: Volume from water weight | AI6: Fill % | AJ6: Circulation % | AK6: No. of fills | AL6: Waste allowance % | AM6: WASTE VOLUME | AN6: EQUIPMENT VOLUME | AO6: SOLUTION VOLUME | AP6: OD used (m) | AQ6: Shell area (m²) | AR6: Shell length (m) | AS6: Pipe ID used (mm) | AT6: Fill used | AU6: Unit no.
H7: m³ | I7: kg | L7: mm | M7: m | N7: mm | O7: mm | R7: mm | S7: nos | T7: mm | U7: mm | V7: mm | W7: mm | Y7: mm | Z7: mm | AB7: mm | AD7: m³ | AE7: m³ | AF7: m³ | AG7: m³ | AH7: m³ | AI7: % | AJ7: % | AK7: nos | AL7: % | AM7: m³ | AN7: m³ | AO7: m³
A9: ="UNIT 1: "&INDEX(CC_UnitNames,1) -> UNIT 1: Unit 1
A10: 1 | B10: Loop 1 | C10: EXAMPLE ML-1 | D10: Piping loop – volume given (ASAB ML-1) | E10: Piping | F10: SS | G10: Given volume | H10: 27.115 | AD10: =IF(E10="Exchanger",IF(AND(ISNUMBER(S10),ISNUMBER(U10),ISNUMBER(V10)),S10*PI()/4*(U10*INDEX(LenF,MATCH($U$7,LenU,0)))^2*V10*INDEX(LenF,MATCH($V$7,LenU,0)),0)+IF(ISNUMBER(Y10),PI()/4*(Y10*INDEX(LenF,MATCH($Y$7,LenU,0)))^2*N(Z10)*INDEX(LenF,MATCH($Z$7,LenU,0))+IF(AA10="",0,IF(AA10="Conical",PI()/12*(Y10*INDEX(LenF,MATCH($Y$7,LenU,0)))^2*(0),INDEX(HeadK,MATCH(AA10,HeadU,0))*(Y10*INDEX(LenF,MATCH($Y$7,LenU,0)))^3)),0)+IF(ISNUMBER(Y10),PI()/4*(Y10*INDEX(LenF,MATCH($Y$7,LenU,0)))^2*N(AB10)*INDEX(LenF,MATCH($AB$7,LenU,0))+IF(AC10="",0,IF(AC10="Conical",PI()/12*(Y10*INDEX(LenF,MATCH($Y$7,LenU,0)))^2*(0),INDEX(HeadK,MATCH(AC10,HeadU,0))*(Y10*INDEX(LenF,MATCH($Y$7,LenU,0)))^3)),0),"") | AE10: =IF(OR(E10="",E10="Piping"),"",IF(E10="Exchanger",AQ10*AR10+IF(P10="",0,IF(P10="Conical",PI()/12*(SQRT(4*AQ10/PI()))^2*(0),INDEX(HeadK,MATCH(P10,HeadU,0))*(SQRT(4*AQ10/PI()))^3))-IF(AND(ISNUMBER(S10),ISNUMBER(V10)),S10*PI()/4*AP10^2*V10*INDEX(LenF,MATCH($V$7,LenU,0)),0),IF(ISNUMBER(N10),PI()/4*(N10*INDEX(LenF,MATCH($N$7,LenU,0)))^2*N(O10)*INDEX(LenF,MATCH($O$7,LenU,0))+IF(P10="",0,IF(P10="Conical",PI()/12*(N10*INDEX(LenF,MATCH($N$7,LenU,0)))^2*(N(R10)*INDEX(LenF,MATCH($R$7,LenU,0))),INDEX(HeadK,MATCH(P10,HeadU,0))*(N10*INDEX(LenF,MATCH($N$7,LenU,0)))^3))+IF(Q10="",0,IF(Q10="Conical",PI()/12*(N10*INDEX(LenF,MATCH($N$7,LenU,0)))^2*(N(R10)*INDEX(LenF,MATCH($R$7,LenU,0))),INDEX(HeadK,MATCH(Q10,HeadU,0))*(N10*INDEX(LenF,MATCH($N$7,LenU,0)))^3)),0))) | AF10: =IF(E10<>"Piping","",IF(AND(ISNUMBER(AS10),ISNUMBER(M10)),PI()/4*(AS10/1000)^2*M10*INDEX(LenF,MATCH($M$7,LenU,0)),0)) -> 0 | AG10: =IF(E10="","",N(AD10)+N(AE10)+N(AF10)) -> 0 | AH10: =IF(ISNUMBER(I10),I10*INDEX(WtF,MATCH($I$7,WtU,0))/CC_WaterRho,"") | AM10: =IF(AO10="","",AO10*IF(ISNUMBER(AK10),AK10,CC_DefFills)*(1+IF(ISNUMBER(AL10),AL10,CC_DefAllow))) -> 194.88906 | AN10: =IF(G10="Given volume",IF(ISNUMBER(H10),H10*INDEX(VolF,MATCH($H$7,VolU,0)),""),IF(G10="Water weight",AH10,IF(N(AG10)=0,"",AG10))) -> 27.115 | AO10: =IF(N(AN10)=0,"",AN10*AT10*IF(ISNUMBER(AJ10),AJ10,CC_DefCirc)) -> 31.18225 | AP10: =IF(ISNUMBER(T10),T10*INDEX(LenF,MATCH($T$7,LenU,0)),IF(ISNUMBER(W10),W10*INDEX(LenF,MATCH($W$7,LenU,0))/CC_PitchRatio,0)) -> 0 | AQ10: =IF(ISNUMBER(N10),PI()/4*(N10*INDEX(LenF,MATCH($N$7,LenU,0)))^2,IF(AND(ISNUMBER(S10),ISNUMBER(W10),X10<>""),S10*(W10*INDEX(LenF,MATCH($W$7,LenU,0)))^2*INDEX(LayoutF,MATCH(X10,LayoutU,0)),0)) -> 0 | AR10: =IF(ISNUMBER(O10),O10*INDEX(LenF,MATCH($O$7,LenU,0)),IF(ISNUMBER(V10),V10*INDEX(LenF,MATCH($V$7,LenU,0)),0)) -> 0 | AS10: =IF(ISNUMBER(L10),L10*INDEX(LenF,MATCH($L$7,LenU,0))*1000,IF(OR(J10="",K10=""),"",IFERROR(IF(INDEX(PipeWT,MATCH(J10,NPSU,0),MATCH(K10,SchU,0))="","Sch n/a",INDEX(PipeOD,MATCH(J10,NPSU,0))-2*INDEX(PipeWT,MATCH(J10,NPSU,0),MATCH(K10,SchU,0))),""))) | AT10: =IF(ISNUMBER(AI10),AI10,IFERROR(INDEX(IF(CC_JobType="Decontamination",CC_TypeFillDC,CC_TypeFillCC),MATCH(E10,CC_TypeL,0)),1)) -> 1 | AU10: 1
A11: 2 | B11: Loop 2 | C11: EXAMPLE V-101 | D11: Vertical vessel (dimensions) | E11: Vessel – Vertical | F11: SS | N11: 2000 | O11: 6000 | P11: 2:1 Ellipsoidal | Q11: 2:1 Ellipsoidal | AD11: =IF(E11="Exchanger",IF(AND(ISNUMBER(S11),ISNUMBER(U11),ISNUMBER(V11)),S11*PI()/4*(U11*INDEX(LenF,MATCH($U$7,LenU,0)))^2*V11*INDEX(LenF,MATCH($V$7,LenU,0)),0)+IF(ISNUMBER(Y11),PI()/4*(Y11*INDEX(LenF,MATCH($Y$7,LenU,0)))^2*N(Z11)*INDEX(LenF,MATCH($Z$7,LenU,0))+IF(AA11="",0,IF(AA11="Conical",PI()/12*(Y11*INDEX(LenF,MATCH($Y$7,LenU,0)))^2*(0),INDEX(HeadK,MATCH(AA11,HeadU,0))*(Y11*INDEX(LenF,MATCH($Y$7,LenU,0)))^3)),0)+IF(ISNUMBER(Y11),PI()/4*(Y11*INDEX(LenF,MATCH($Y$7,LenU,0)))^2*N(AB11)*INDEX(LenF,MATCH($AB$7,LenU,0))+IF(AC11="",0,IF(AC11="Conical",PI()/12*(Y11*INDEX(LenF,MATCH($Y$7,LenU,0)))^2*(0),INDEX(HeadK,MATCH(AC11,HeadU,0))*(Y11*INDEX(LenF,MATCH($Y$7,LenU,0)))^3)),0),"") | AE11: =IF(OR(E11="",E11="Piping"),"",IF(E11="Exchanger",AQ11*AR11+IF(P11="",0,IF(P11="Conical",PI()/12*(SQRT(4*AQ11/PI()))^2*(0),INDEX(HeadK,MATCH(P11,HeadU,0))*(SQRT(4*AQ11/PI()))^3))-IF(AND(ISNUMBER(S11),ISNUMBER(V11)),S11*PI()/4*AP11^2*V11*INDEX(LenF,MATCH($V$7,LenU,0)),0),IF(ISNUMBER(N11),PI()/4*(N11*INDEX(LenF,MATCH($N$7,LenU,0)))^2*N(O11)*INDEX(LenF,MATCH($O$7,LenU,0))+IF(P11="",0,IF(P11="Conical",PI()/12*(N11*INDEX(LenF,MATCH($N$7,LenU,0)))^2*(N(R11)*INDEX(LenF,MATCH($R$7,LenU,0))),INDEX(HeadK,MATCH(P11,HeadU,0))*(N11*INDEX(LenF,MATCH($N$7,LenU,0)))^3))+IF(Q11="",0,IF(Q11="Conical",PI()/12*(N11*INDEX(LenF,MATCH($N$7,LenU,0)))^2*(N(R11)*INDEX(LenF,MATCH($R$7,LenU,0))),INDEX(HeadK,MATCH(Q11,HeadU,0))*(N11*INDEX(LenF,MATCH($N$7,LenU,0)))^3)),0))) -> 20.943951 | AF11: =IF(E11<>"Piping","",IF(AND(ISNUMBER(AS11),ISNUMBER(M11)),PI()/4*(AS11/1000)^2*M11*INDEX(LenF,MATCH($M$7,LenU,0)),0)) | AG11: =IF(E11="","",N(AD11)+N(AE11)+N(AF11)) -> 20.943951 | AH11: =IF(ISNUMBER(I11),I11*INDEX(WtF,MATCH($I$7,WtU,0))/CC_WaterRho,"") | AI11: 0.15 | AM11: =IF(AO11="","",AO11*IF(ISNUMBER(AK11),AK11,CC_DefFills)*(1+IF(ISNUMBER(AL11),AL11,CC_DefAllow))) -> 22.580197 | AN11: =IF(G11="Given volume",IF(ISNUMBER(H11),H11*INDEX(VolF,MATCH($H$7,VolU,0)),""),IF(G11="Water weight",AH11,IF(N(AG11)=0,"",AG11))) -> 20.943951 | AO11: =IF(N(AN11)=0,"",AN11*AT11*IF(ISNUMBER(AJ11),AJ11,CC_DefCirc)) -> 3.6128316 | AP11: =IF(ISNUMBER(T11),T11*INDEX(LenF,MATCH($T$7,LenU,0)),IF(ISNUMBER(W11),W11*INDEX(LenF,MATCH($W$7,LenU,0))/CC_PitchRatio,0)) -> 0 | AQ11: =IF(ISNUMBER(N11),PI()/4*(N11*INDEX(LenF,MATCH($N$7,LenU,0)))^2,IF(AND(ISNUMBER(S11),ISNUMBER(W11),X11<>""),S11*(W11*INDEX(LenF,MATCH($W$7,LenU,0)))^2*INDEX(LayoutF,MATCH(X11,LayoutU,0)),0)) -> 3.1415927 | AR11: =IF(ISNUMBER(O11),O11*INDEX(LenF,MATCH($O$7,LenU,0)),IF(ISNUMBER(V11),V11*INDEX(LenF,MATCH($V$7,LenU,0)),0)) -> 6 | AS11: =IF(ISNUMBER(L11),L11*INDEX(LenF,MATCH($L$7,LenU,0))*1000,IF(OR(J11="",K11=""),"",IFERROR(IF(INDEX(PipeWT,MATCH(J11,NPSU,0),MATCH(K11,SchU,0))="","Sch n/a",INDEX(PipeOD,MATCH(J11,NPSU,0))-2*INDEX(PipeWT,MATCH(J11,NPSU,0),MATCH(K11,SchU,0))),""))) | AT11: =IF(ISNUMBER(AI11),AI11,IFERROR(INDEX(IF(CC_JobType="Decontamination",CC_TypeFillDC,CC_TypeFillCC),MATCH(E11,CC_TypeL,0)),1)) -> 0.15 | AU11: 1
A12: 3 | B12: Loop 2 | C12: EXAMPLE E-101 | D12: Shell & tube exchanger | E12: Exchanger | F12: SS | N12: 800 | O12: 6000 | S12: 500 | T12: 19.05 | U12: 15.75 | V12: 6096 | W12: 23.81 | X12: Triangular (30°) | Y12: 800 | Z12: 600 | AA12: Flat | AB12: 300 | AC12: 2:1 Ellipsoidal | AD12: =IF(E12="Exchanger",IF(AND(ISNUMBER(S12),ISNUMBER(U12),ISNUMBER(V12)),S12*PI()/4*(U12*INDEX(LenF,MATCH($U$7,LenU,0)))^2*V12*INDEX(LenF,MATCH($V$7,LenU,0)),0)+IF(ISNUMBER(Y12),PI()/4*(Y12*INDEX(LenF,MATCH($Y$7,LenU,0)))^2*N(Z12)*INDEX(LenF,MATCH($Z$7,LenU,0))+IF(AA12="",0,IF(AA12="Conical",PI()/12*(Y12*INDEX(LenF,MATCH($Y$7,LenU,0)))^2*(0),INDEX(HeadK,MATCH(AA12,HeadU,0))*(Y12*INDEX(LenF,MATCH($Y$7,LenU,0)))^3)),0)+IF(ISNUMBER(Y12),PI()/4*(Y12*INDEX(LenF,MATCH($Y$7,LenU,0)))^2*N(AB12)*INDEX(LenF,MATCH($AB$7,LenU,0))+IF(AC12="",0,IF(AC12="Conical",PI()/12*(Y12*INDEX(LenF,MATCH($Y$7,LenU,0)))^2*(0),INDEX(HeadK,MATCH(AC12,HeadU,0))*(Y12*INDEX(LenF,MATCH($Y$7,LenU,0)))^3)),0),"") -> 1.1132452 | AE12: =IF(OR(E12="",E12="Piping"),"",IF(E12="Exchanger",AQ12*AR12+IF(P12="",0,IF(P12="Conical",PI()/12*(SQRT(4*AQ12/PI()))^2*(0),INDEX(HeadK,MATCH(P12,HeadU,0))*(SQRT(4*AQ12/PI()))^3))-IF(AND(ISNUMBER(S12),ISNUMBER(V12)),S12*PI()/4*AP12^2*V12*INDEX(LenF,MATCH($V$7,LenU,0)),0),IF(ISNUMBER(N12),PI()/4*(N12*INDEX(LenF,MATCH($N$7,LenU,0)))^2*N(O12)*INDEX(LenF,MATCH($O$7,LenU,0))+IF(P12="",0,IF(P12="Conical",PI()/12*(N12*INDEX(LenF,MATCH($N$7,LenU,0)))^2*(N(R12)*INDEX(LenF,MATCH($R$7,LenU,0))),INDEX(HeadK,MATCH(P12,HeadU,0))*(N12*INDEX(LenF,MATCH($N$7,LenU,0)))^3))+IF(Q12="",0,IF(Q12="Conical",PI()/12*(N12*INDEX(LenF,MATCH($N$7,LenU,0)))^2*(N(R12)*INDEX(LenF,MATCH($R$7,LenU,0))),INDEX(HeadK,MATCH(Q12,HeadU,0))*(N12*INDEX(LenF,MATCH($N$7,LenU,0)))^3)),0))) -> 2.147179 | AF12: =IF(E12<>"Piping","",IF(AND(ISNUMBER(AS12),ISNUMBER(M12)),PI()/4*(AS12/1000)^2*M12*INDEX(LenF,MATCH($M$7,LenU,0)),0)) | AG12: =IF(E12="","",N(AD12)+N(AE12)+N(AF12)) -> 3.2604242 | AH12: =IF(ISNUMBER(I12),I12*INDEX(WtF,MATCH($I$7,WtU,0))/CC_WaterRho,"") | AM12: =IF(AO12="","",AO12*IF(ISNUMBER(AK12),AK12,CC_DefFills)*(1+IF(ISNUMBER(AL12),AL12,CC_DefAllow))) -> 23.434299 | AN12: =IF(G12="Given volume",IF(ISNUMBER(H12),H12*INDEX(VolF,MATCH($H$7,VolU,0)),""),IF(G12="Water weight",AH12,IF(N(AG12)=0,"",AG12))) -> 3.2604242 | AO12: =IF(N(AN12)=0,"",AN12*AT12*IF(ISNUMBER(AJ12),AJ12,CC_DefCirc)) -> 3.7494878 | AP12: =IF(ISNUMBER(T12),T12*INDEX(LenF,MATCH($T$7,LenU,0)),IF(ISNUMBER(W12),W12*INDEX(LenF,MATCH($W$7,LenU,0))/CC_PitchRatio,0)) -> 0.01905 | AQ12: =IF(ISNUMBER(N12),PI()/4*(N12*INDEX(LenF,MATCH($N$7,LenU,0)))^2,IF(AND(ISNUMBER(S12),ISNUMBER(W12),X12<>""),S12*(W12*INDEX(LenF,MATCH($W$7,LenU,0)))^2*INDEX(LayoutF,MATCH(X12,LayoutU,0)),0)) -> 0.50265482 | AR12: =IF(ISNUMBER(O12),O12*INDEX(LenF,MATCH($O$7,LenU,0)),IF(ISNUMBER(V12),V12*INDEX(LenF,MATCH($V$7,LenU,0)),0)) -> 6 | AS12: =IF(ISNUMBER(L12),L12*INDEX(LenF,MATCH($L$7,LenU,0))*1000,IF(OR(J12="",K12=""),"",IFERROR(IF(INDEX(PipeWT,MATCH(J12,NPSU,0),MATCH(K12,SchU,0))="","Sch n/a",INDEX(PipeOD,MATCH(J12,NPSU,0))-2*INDEX(PipeWT,MATCH(J12,NPSU,0),MATCH(K12,SchU,0))),""))) | AT12: =IF(ISNUMBER(AI12),AI12,IFERROR(INDEX(IF(CC_JobType="Decontamination",CC_TypeFillDC,CC_TypeFillCC),MATCH(E12,CC_TypeL,0)),1)) -> 1 | AU12: 1
A13: 4 | C13: EXAMPLE 6"-P-1001 | D13: Line from isometric | E13: Piping | F13: CS | J13: 6" (DN 150) | K13: Sch 40 | M13: 120 | AD13: =IF(E13="Exchanger",IF(AND(ISNUMBER(S13),ISNUMBER(U13),ISNUMBER(V13)),S13*PI()/4*(U13*INDEX(LenF,MATCH($U$7,LenU,0)))^2*V13*INDEX(LenF,MATCH($V$7,LenU,0)),0)+IF(ISNUMBER(Y13),PI()/4*(Y13*INDEX(LenF,MATCH($Y$7,LenU,0)))^2*N(Z13)*INDEX(LenF,MATCH($Z$7,LenU,0))+IF(AA13="",0,IF(AA13="Conical",PI()/12*(Y13*INDEX(LenF,MATCH($Y$7,LenU,0)))^2*(0),INDEX(HeadK,MATCH(AA13,HeadU,0))*(Y13*INDEX(LenF,MATCH($Y$7,LenU,0)))^3)),0)+IF(ISNUMBER(Y13),PI()/4*(Y13*INDEX(LenF,MATCH($Y$7,LenU,0)))^2*N(AB13)*INDEX(LenF,MATCH($AB$7,LenU,0))+IF(AC13="",0,IF(AC13="Conical",PI()/12*(Y13*INDEX(LenF,MATCH($Y$7,LenU,0)))^2*(0),INDEX(HeadK,MATCH(AC13,HeadU,0))*(Y13*INDEX(LenF,MATCH($Y$7,LenU,0)))^3)),0),"") | AE13: =IF(OR(E13="",E13="Piping"),"",IF(E13="Exchanger",AQ13*AR13+IF(P13="",0,IF(P13="Conical",PI()/12*(SQRT(4*AQ13/PI()))^2*(0),INDEX(HeadK,MATCH(P13,HeadU,0))*(SQRT(4*AQ13/PI()))^3))-IF(AND(ISNUMBER(S13),ISNUMBER(V13)),S13*PI()/4*AP13^2*V13*INDEX(LenF,MATCH($V$7,LenU,0)),0),IF(ISNUMBER(N13),PI()/4*(N13*INDEX(LenF,MATCH($N$7,LenU,0)))^2*N(O13)*INDEX(LenF,MATCH($O$7,LenU,0))+IF(P13="",0,IF(P13="Conical",PI()/12*(N13*INDEX(LenF,MATCH($N$7,LenU,0)))^2*(N(R13)*INDEX(LenF,MATCH($R$7,LenU,0))),INDEX(HeadK,MATCH(P13,HeadU,0))*(N13*INDEX(LenF,MATCH($N$7,LenU,0)))^3))+IF(Q13="",0,IF(Q13="Conical",PI()/12*(N13*INDEX(LenF,MATCH($N$7,LenU,0)))^2*(N(R13)*INDEX(LenF,MATCH($R$7,LenU,0))),INDEX(HeadK,MATCH(Q13,HeadU,0))*(N13*INDEX(LenF,MATCH($N$7,LenU,0)))^3)),0))) | AF13: =IF(E13<>"Piping","",IF(AND(ISNUMBER(AS13),ISNUMBER(M13)),PI()/4*(AS13/1000)^2*M13*INDEX(LenF,MATCH($M$7,LenU,0)),0)) -> 2.2375032 | AG13: =IF(E13="","",N(AD13)+N(AE13)+N(AF13)) -> 2.2375032 | AH13: =IF(ISNUMBER(I13),I13*INDEX(WtF,MATCH($I$7,WtU,0))/CC_WaterRho,"") | AM13: =IF(AO13="","",AO13*IF(ISNUMBER(AK13),AK13,CC_DefFills)*(1+IF(ISNUMBER(AL13),AL13,CC_DefAllow))) -> 16.082054 | AN13: =IF(G13="Given volume",IF(ISNUMBER(H13),H13*INDEX(VolF,MATCH($H$7,VolU,0)),""),IF(G13="Water weight",AH13,IF(N(AG13)=0,"",AG13))) -> 2.2375032 | AO13: =IF(N(AN13)=0,"",AN13*AT13*IF(ISNUMBER(AJ13),AJ13,CC_DefCirc)) -> 2.5731287 | AP13: =IF(ISNUMBER(T13),T13*INDEX(LenF,MATCH($T$7,LenU,0)),IF(ISNUMBER(W13),W13*INDEX(LenF,MATCH($W$7,LenU,0))/CC_PitchRatio,0)) -> 0 | AQ13: =IF(ISNUMBER(N13),PI()/4*(N13*INDEX(LenF,MATCH($N$7,LenU,0)))^2,IF(AND(ISNUMBER(S13),ISNUMBER(W13),X13<>""),S13*(W13*INDEX(LenF,MATCH($W$7,LenU,0)))^2*INDEX(LayoutF,MATCH(X13,LayoutU,0)),0)) -> 0 | AR13: =IF(ISNUMBER(O13),O13*INDEX(LenF,MATCH($O$7,LenU,0)),IF(ISNUMBER(V13),V13*INDEX(LenF,MATCH($V$7,LenU,0)),0)) -> 0 | AS13: =IF(ISNUMBER(L13),L13*INDEX(LenF,MATCH($L$7,LenU,0))*1000,IF(OR(J13="",K13=""),"",IFERROR(IF(INDEX(PipeWT,MATCH(J13,NPSU,0),MATCH(K13,SchU,0))="","Sch n/a",INDEX(PipeOD,MATCH(J13,NPSU,0))-2*INDEX(PipeWT,MATCH(J13,NPSU,0),MATCH(K13,SchU,0))),""))) -> 154.08 | AT13: =IF(ISNUMBER(AI13),AI13,IFERROR(INDEX(IF(CC_JobType="Decontamination",CC_TypeFillDC,CC_TypeFillCC),MATCH(E13,CC_TypeL,0)),1)) -> 1 | AU13: 1
A14: 5 | AD14: =IF(E14="Exchanger",IF(AND(ISNUMBER(S14),ISNUMBER(U14),ISNUMBER(V14)),S14*PI()/4*(U14*INDEX(LenF,MATCH($U$7,LenU,0)))^2*V14*INDEX(LenF,MATCH($V$7,LenU,0)),0)+IF(ISNUMBER(Y14),PI()/4*(Y14*INDEX(LenF,MATCH($Y$7,LenU,0)))^2*N(Z14)*INDEX(LenF,MATCH($Z$7,LenU,0))+IF(AA14="",0,IF(AA14="Conical",PI()/12*(Y14*INDEX(LenF,MATCH($Y$7,LenU,0)))^2*(0),INDEX(HeadK,MATCH(AA14,HeadU,0))*(Y14*INDEX(LenF,MATCH($Y$7,LenU,0)))^3)),0)+IF(ISNUMBER(Y14),PI()/4*(Y14*INDEX(LenF,MATCH($Y$7,LenU,0)))^2*N(AB14)*INDEX(LenF,MATCH($AB$7,LenU,0))+IF(AC14="",0,IF(AC14="Conical",PI()/12*(Y14*INDEX(LenF,MATCH($Y$7,LenU,0)))^2*(0),INDEX(HeadK,MATCH(AC14,HeadU,0))*(Y14*INDEX(LenF,MATCH($Y$7,LenU,0)))^3)),0),"") | AE14: =IF(OR(E14="",E14="Piping"),"",IF(E14="Exchanger",AQ14*AR14+IF(P14="",0,IF(P14="Conical",PI()/12*(SQRT(4*AQ14/PI()))^2*(0),INDEX(HeadK,MATCH(P14,HeadU,0))*(SQRT(4*AQ14/PI()))^3))-IF(AND(ISNUMBER(S14),ISNUMBER(V14)),S14*PI()/4*AP14^2*V14*INDEX(LenF,MATCH($V$7,LenU,0)),0),IF(ISNUMBER(N14),PI()/4*(N14*INDEX(LenF,MATCH($N$7,LenU,0)))^2*N(O14)*INDEX(LenF,MATCH($O$7,LenU,0))+IF(P14="",0,IF(P14="Conical",PI()/12*(N14*INDEX(LenF,MATCH($N$7,LenU,0)))^2*(N(R14)*INDEX(LenF,MATCH($R$7,LenU,0))),INDEX(HeadK,MATCH(P14,HeadU,0))*(N14*INDEX(LenF,MATCH($N$7,LenU,0)))^3))+IF(Q14="",0,IF(Q14="Conical",PI()/12*(N14*INDEX(LenF,MATCH($N$7,LenU,0)))^2*(N(R14)*INDEX(LenF,MATCH($R$7,LenU,0))),INDEX(HeadK,MATCH(Q14,HeadU,0))*(N14*INDEX(LenF,MATCH($N$7,LenU,0)))^3)),0))) | AF14: =IF(E14<>"Piping","",IF(AND(ISNUMBER(AS14),ISNUMBER(M14)),PI()/4*(AS14/1000)^2*M14*INDEX(LenF,MATCH($M$7,LenU,0)),0)) | AG14: =IF(E14="","",N(AD14)+N(AE14)+N(AF14)) | AH14: =IF(ISNUMBER(I14),I14*INDEX(WtF,MATCH($I$7,WtU,0))/CC_WaterRho,"") | AM14: =IF(AO14="","",AO14*IF(ISNUMBER(AK14),AK14,CC_DefFills)*(1+IF(ISNUMBER(AL14),AL14,CC_DefAllow))) | AN14: =IF(G14="Given volume",IF(ISNUMBER(H14),H14*INDEX(VolF,MATCH($H$7,VolU,0)),""),IF(G14="Water weight",AH14,IF(N(AG14)=0,"",AG14))) | AO14: =IF(N(AN14)=0,"",AN14*AT14*IF(ISNUMBER(AJ14),AJ14,CC_DefCirc)) | AP14: =IF(ISNUMBER(T14),T14*INDEX(LenF,MATCH($T$7,LenU,0)),IF(ISNUMBER(W14),W14*INDEX(LenF,MATCH($W$7,LenU,0))/CC_PitchRatio,0)) -> 0 | AQ14: =IF(ISNUMBER(N14),PI()/4*(N14*INDEX(LenF,MATCH($N$7,LenU,0)))^2,IF(AND(ISNUMBER(S14),ISNUMBER(W14),X14<>""),S14*(W14*INDEX(LenF,MATCH($W$7,LenU,0)))^2*INDEX(LayoutF,MATCH(X14,LayoutU,0)),0)) -> 0 | AR14: =IF(ISNUMBER(O14),O14*INDEX(LenF,MATCH($O$7,LenU,0)),IF(ISNUMBER(V14),V14*INDEX(LenF,MATCH($V$7,LenU,0)),0)) -> 0 | AS14: =IF(ISNUMBER(L14),L14*INDEX(LenF,MATCH($L$7,LenU,0))*1000,IF(OR(J14="",K14=""),"",IFERROR(IF(INDEX(PipeWT,MATCH(J14,NPSU,0),MATCH(K14,SchU,0))="","Sch n/a",INDEX(PipeOD,MATCH(J14,NPSU,0))-2*INDEX(PipeWT,MATCH(J14,NPSU,0),MATCH(K14,SchU,0))),""))) | AT14: =IF(ISNUMBER(AI14),AI14,IFERROR(INDEX(IF(CC_JobType="Decontamination",CC_TypeFillDC,CC_TypeFillCC),MATCH(E14,CC_TypeL,0)),1)) -> 1 | AU14: 1
A15: 6 | AD15: =IF(E15="Exchanger",IF(AND(ISNUMBER(S15),ISNUMBER(U15),ISNUMBER(V15)),S15*PI()/4*(U15*INDEX(LenF,MATCH($U$7,LenU,0)))^2*V15*INDEX(LenF,MATCH($V$7,LenU,0)),0)+IF(ISNUMBER(Y15),PI()/4*(Y15*INDEX(LenF,MATCH($Y$7,LenU,0)))^2*N(Z15)*INDEX(LenF,MATCH($Z$7,LenU,0))+IF(AA15="",0,IF(AA15="Conical",PI()/12*(Y15*INDEX(LenF,MATCH($Y$7,LenU,0)))^2*(0),INDEX(HeadK,MATCH(AA15,HeadU,0))*(Y15*INDEX(LenF,MATCH($Y$7,LenU,0)))^3)),0)+IF(ISNUMBER(Y15),PI()/4*(Y15*INDEX(LenF,MATCH($Y$7,LenU,0)))^2*N(AB15)*INDEX(LenF,MATCH($AB$7,LenU,0))+IF(AC15="",0,IF(AC15="Conical",PI()/12*(Y15*INDEX(LenF,MATCH($Y$7,LenU,0)))^2*(0),INDEX(HeadK,MATCH(AC15,HeadU,0))*(Y15*INDEX(LenF,MATCH($Y$7,LenU,0)))^3)),0),"") | AE15: =IF(OR(E15="",E15="Piping"),"",IF(E15="Exchanger",AQ15*AR15+IF(P15="",0,IF(P15="Conical",PI()/12*(SQRT(4*AQ15/PI()))^2*(0),INDEX(HeadK,MATCH(P15,HeadU,0))*(SQRT(4*AQ15/PI()))^3))-IF(AND(ISNUMBER(S15),ISNUMBER(V15)),S15*PI()/4*AP15^2*V15*INDEX(LenF,MATCH($V$7,LenU,0)),0),IF(ISNUMBER(N15),PI()/4*(N15*INDEX(LenF,MATCH($N$7,LenU,0)))^2*N(O15)*INDEX(LenF,MATCH($O$7,LenU,0))+IF(P15="",0,IF(P15="Conical",PI()/12*(N15*INDEX(LenF,MATCH($N$7,LenU,0)))^2*(N(R15)*INDEX(LenF,MATCH($R$7,LenU,0))),INDEX(HeadK,MATCH(P15,HeadU,0))*(N15*INDEX(LenF,MATCH($N$7,LenU,0)))^3))+IF(Q15="",0,IF(Q15="Conical",PI()/12*(N15*INDEX(LenF,MATCH($N$7,LenU,0)))^2*(N(R15)*INDEX(LenF,MATCH($R$7,LenU,0))),INDEX(HeadK,MATCH(Q15,HeadU,0))*(N15*INDEX(LenF,MATCH($N$7,LenU,0)))^3)),0))) | AF15: =IF(E15<>"Piping","",IF(AND(ISNUMBER(AS15),ISNUMBER(M15)),PI()/4*(AS15/1000)^2*M15*INDEX(LenF,MATCH($M$7,LenU,0)),0)) | AG15: =IF(E15="","",N(AD15)+N(AE15)+N(AF15)) | AH15: =IF(ISNUMBER(I15),I15*INDEX(WtF,MATCH($I$7,WtU,0))/CC_WaterRho,"") | AM15: =IF(AO15="","",AO15*IF(ISNUMBER(AK15),AK15,CC_DefFills)*(1+IF(ISNUMBER(AL15),AL15,CC_DefAllow))) | AN15: =IF(G15="Given volume",IF(ISNUMBER(H15),H15*INDEX(VolF,MATCH($H$7,VolU,0)),""),IF(G15="Water weight",AH15,IF(N(AG15)=0,"",AG15))) | AO15: =IF(N(AN15)=0,"",AN15*AT15*IF(ISNUMBER(AJ15),AJ15,CC_DefCirc)) | AP15: =IF(ISNUMBER(T15),T15*INDEX(LenF,MATCH($T$7,LenU,0)),IF(ISNUMBER(W15),W15*INDEX(LenF,MATCH($W$7,LenU,0))/CC_PitchRatio,0)) -> 0 | AQ15: =IF(ISNUMBER(N15),PI()/4*(N15*INDEX(LenF,MATCH($N$7,LenU,0)))^2,IF(AND(ISNUMBER(S15),ISNUMBER(W15),X15<>""),S15*(W15*INDEX(LenF,MATCH($W$7,LenU,0)))^2*INDEX(LayoutF,MATCH(X15,LayoutU,0)),0)) -> 0 | AR15: =IF(ISNUMBER(O15),O15*INDEX(LenF,MATCH($O$7,LenU,0)),IF(ISNUMBER(V15),V15*INDEX(LenF,MATCH($V$7,LenU,0)),0)) -> 0 | AS15: =IF(ISNUMBER(L15),L15*INDEX(LenF,MATCH($L$7,LenU,0))*1000,IF(OR(J15="",K15=""),"",IFERROR(IF(INDEX(PipeWT,MATCH(J15,NPSU,0),MATCH(K15,SchU,0))="","Sch n/a",INDEX(PipeOD,MATCH(J15,NPSU,0))-2*INDEX(PipeWT,MATCH(J15,NPSU,0),MATCH(K15,SchU,0))),""))) | AT15: =IF(ISNUMBER(AI15),AI15,IFERROR(INDEX(IF(CC_JobType="Decontamination",CC_TypeFillDC,CC_TypeFillCC),MATCH(E15,CC_TypeL,0)),1)) -> 1 | AU15: 1
A16: 7 | AD16: =IF(E16="Exchanger",IF(AND(ISNUMBER(S16),ISNUMBER(U16),ISNUMBER(V16)),S16*PI()/4*(U16*INDEX(LenF,MATCH($U$7,LenU,0)))^2*V16*INDEX(LenF,MATCH($V$7,LenU,0)),0)+IF(ISNUMBER(Y16),PI()/4*(Y16*INDEX(LenF,MATCH($Y$7,LenU,0)))^2*N(Z16)*INDEX(LenF,MATCH($Z$7,LenU,0))+IF(AA16="",0,IF(AA16="Conical",PI()/12*(Y16*INDEX(LenF,MATCH($Y$7,LenU,0)))^2*(0),INDEX(HeadK,MATCH(AA16,HeadU,0))*(Y16*INDEX(LenF,MATCH($Y$7,LenU,0)))^3)),0)+IF(ISNUMBER(Y16),PI()/4*(Y16*INDEX(LenF,MATCH($Y$7,LenU,0)))^2*N(AB16)*INDEX(LenF,MATCH($AB$7,LenU,0))+IF(AC16="",0,IF(AC16="Conical",PI()/12*(Y16*INDEX(LenF,MATCH($Y$7,LenU,0)))^2*(0),INDEX(HeadK,MATCH(AC16,HeadU,0))*(Y16*INDEX(LenF,MATCH($Y$7,LenU,0)))^3)),0),"") | AE16: =IF(OR(E16="",E16="Piping"),"",IF(E16="Exchanger",AQ16*AR16+IF(P16="",0,IF(P16="Conical",PI()/12*(SQRT(4*AQ16/PI()))^2*(0),INDEX(HeadK,MATCH(P16,HeadU,0))*(SQRT(4*AQ16/PI()))^3))-IF(AND(ISNUMBER(S16),ISNUMBER(V16)),S16*PI()/4*AP16^2*V16*INDEX(LenF,MATCH($V$7,LenU,0)),0),IF(ISNUMBER(N16),PI()/4*(N16*INDEX(LenF,MATCH($N$7,LenU,0)))^2*N(O16)*INDEX(LenF,MATCH($O$7,LenU,0))+IF(P16="",0,IF(P16="Conical",PI()/12*(N16*INDEX(LenF,MATCH($N$7,LenU,0)))^2*(N(R16)*INDEX(LenF,MATCH($R$7,LenU,0))),INDEX(HeadK,MATCH(P16,HeadU,0))*(N16*INDEX(LenF,MATCH($N$7,LenU,0)))^3))+IF(Q16="",0,IF(Q16="Conical",PI()/12*(N16*INDEX(LenF,MATCH($N$7,LenU,0)))^2*(N(R16)*INDEX(LenF,MATCH($R$7,LenU,0))),INDEX(HeadK,MATCH(Q16,HeadU,0))*(N16*INDEX(LenF,MATCH($N$7,LenU,0)))^3)),0))) | AF16: =IF(E16<>"Piping","",IF(AND(ISNUMBER(AS16),ISNUMBER(M16)),PI()/4*(AS16/1000)^2*M16*INDEX(LenF,MATCH($M$7,LenU,0)),0)) | AG16: =IF(E16="","",N(AD16)+N(AE16)+N(AF16)) | AH16: =IF(ISNUMBER(I16),I16*INDEX(WtF,MATCH($I$7,WtU,0))/CC_WaterRho,"") | AM16: =IF(AO16="","",AO16*IF(ISNUMBER(AK16),AK16,CC_DefFills)*(1+IF(ISNUMBER(AL16),AL16,CC_DefAllow))) | AN16: =IF(G16="Given volume",IF(ISNUMBER(H16),H16*INDEX(VolF,MATCH($H$7,VolU,0)),""),IF(G16="Water weight",AH16,IF(N(AG16)=0,"",AG16))) | AO16: =IF(N(AN16)=0,"",AN16*AT16*IF(ISNUMBER(AJ16),AJ16,CC_DefCirc)) | AP16: =IF(ISNUMBER(T16),T16*INDEX(LenF,MATCH($T$7,LenU,0)),IF(ISNUMBER(W16),W16*INDEX(LenF,MATCH($W$7,LenU,0))/CC_PitchRatio,0)) -> 0 | AQ16: =IF(ISNUMBER(N16),PI()/4*(N16*INDEX(LenF,MATCH($N$7,LenU,0)))^2,IF(AND(ISNUMBER(S16),ISNUMBER(W16),X16<>""),S16*(W16*INDEX(LenF,MATCH($W$7,LenU,0)))^2*INDEX(LayoutF,MATCH(X16,LayoutU,0)),0)) -> 0 | AR16: =IF(ISNUMBER(O16),O16*INDEX(LenF,MATCH($O$7,LenU,0)),IF(ISNUMBER(V16),V16*INDEX(LenF,MATCH($V$7,LenU,0)),0)) -> 0 | AS16: =IF(ISNUMBER(L16),L16*INDEX(LenF,MATCH($L$7,LenU,0))*1000,IF(OR(J16="",K16=""),"",IFERROR(IF(INDEX(PipeWT,MATCH(J16,NPSU,0),MATCH(K16,SchU,0))="","Sch n/a",INDEX(PipeOD,MATCH(J16,NPSU,0))-2*INDEX(PipeWT,MATCH(J16,NPSU,0),MATCH(K16,SchU,0))),""))) | AT16: =IF(ISNUMBER(AI16),AI16,IFERROR(INDEX(IF(CC_JobType="Decontamination",CC_TypeFillDC,CC_TypeFillCC),MATCH(E16,CC_TypeL,0)),1)) -> 1 | AU16: 1
A17: 8 | AD17: =IF(E17="Exchanger",IF(AND(ISNUMBER(S17),ISNUMBER(U17),ISNUMBER(V17)),S17*PI()/4*(U17*INDEX(LenF,MATCH($U$7,LenU,0)))^2*V17*INDEX(LenF,MATCH($V$7,LenU,0)),0)+IF(ISNUMBER(Y17),PI()/4*(Y17*INDEX(LenF,MATCH($Y$7,LenU,0)))^2*N(Z17)*INDEX(LenF,MATCH($Z$7,LenU,0))+IF(AA17="",0,IF(AA17="Conical",PI()/12*(Y17*INDEX(LenF,MATCH($Y$7,LenU,0)))^2*(0),INDEX(HeadK,MATCH(AA17,HeadU,0))*(Y17*INDEX(LenF,MATCH($Y$7,LenU,0)))^3)),0)+IF(ISNUMBER(Y17),PI()/4*(Y17*INDEX(LenF,MATCH($Y$7,LenU,0)))^2*N(AB17)*INDEX(LenF,MATCH($AB$7,LenU,0))+IF(AC17="",0,IF(AC17="Conical",PI()/12*(Y17*INDEX(LenF,MATCH($Y$7,LenU,0)))^2*(0),INDEX(HeadK,MATCH(AC17,HeadU,0))*(Y17*INDEX(LenF,MATCH($Y$7,LenU,0)))^3)),0),"") | AE17: =IF(OR(E17="",E17="Piping"),"",IF(E17="Exchanger",AQ17*AR17+IF(P17="",0,IF(P17="Conical",PI()/12*(SQRT(4*AQ17/PI()))^2*(0),INDEX(HeadK,MATCH(P17,HeadU,0))*(SQRT(4*AQ17/PI()))^3))-IF(AND(ISNUMBER(S17),ISNUMBER(V17)),S17*PI()/4*AP17^2*V17*INDEX(LenF,MATCH($V$7,LenU,0)),0),IF(ISNUMBER(N17),PI()/4*(N17*INDEX(LenF,MATCH($N$7,LenU,0)))^2*N(O17)*INDEX(LenF,MATCH($O$7,LenU,0))+IF(P17="",0,IF(P17="Conical",PI()/12*(N17*INDEX(LenF,MATCH($N$7,LenU,0)))^2*(N(R17)*INDEX(LenF,MATCH($R$7,LenU,0))),INDEX(HeadK,MATCH(P17,HeadU,0))*(N17*INDEX(LenF,MATCH($N$7,LenU,0)))^3))+IF(Q17="",0,IF(Q17="Conical",PI()/12*(N17*INDEX(LenF,MATCH($N$7,LenU,0)))^2*(N(R17)*INDEX(LenF,MATCH($R$7,LenU,0))),INDEX(HeadK,MATCH(Q17,HeadU,0))*(N17*INDEX(LenF,MATCH($N$7,LenU,0)))^3)),0))) | AF17: =IF(E17<>"Piping","",IF(AND(ISNUMBER(AS17),ISNUMBER(M17)),PI()/4*(AS17/1000)^2*M17*INDEX(LenF,MATCH($M$7,LenU,0)),0)) | AG17: =IF(E17="","",N(AD17)+N(AE17)+N(AF17)) | AH17: =IF(ISNUMBER(I17),I17*INDEX(WtF,MATCH($I$7,WtU,0))/CC_WaterRho,"") | AM17: =IF(AO17="","",AO17*IF(ISNUMBER(AK17),AK17,CC_DefFills)*(1+IF(ISNUMBER(AL17),AL17,CC_DefAllow))) | AN17: =IF(G17="Given volume",IF(ISNUMBER(H17),H17*INDEX(VolF,MATCH($H$7,VolU,0)),""),IF(G17="Water weight",AH17,IF(N(AG17)=0,"",AG17))) | AO17: =IF(N(AN17)=0,"",AN17*AT17*IF(ISNUMBER(AJ17),AJ17,CC_DefCirc)) | AP17: =IF(ISNUMBER(T17),T17*INDEX(LenF,MATCH($T$7,LenU,0)),IF(ISNUMBER(W17),W17*INDEX(LenF,MATCH($W$7,LenU,0))/CC_PitchRatio,0)) -> 0 | AQ17: =IF(ISNUMBER(N17),PI()/4*(N17*INDEX(LenF,MATCH($N$7,LenU,0)))^2,IF(AND(ISNUMBER(S17),ISNUMBER(W17),X17<>""),S17*(W17*INDEX(LenF,MATCH($W$7,LenU,0)))^2*INDEX(LayoutF,MATCH(X17,LayoutU,0)),0)) -> 0 | AR17: =IF(ISNUMBER(O17),O17*INDEX(LenF,MATCH($O$7,LenU,0)),IF(ISNUMBER(V17),V17*INDEX(LenF,MATCH($V$7,LenU,0)),0)) -> 0 | AS17: =IF(ISNUMBER(L17),L17*INDEX(LenF,MATCH($L$7,LenU,0))*1000,IF(OR(J17="",K17=""),"",IFERROR(IF(INDEX(PipeWT,MATCH(J17,NPSU,0),MATCH(K17,SchU,0))="","Sch n/a",INDEX(PipeOD,MATCH(J17,NPSU,0))-2*INDEX(PipeWT,MATCH(J17,NPSU,0),MATCH(K17,SchU,0))),""))) | AT17: =IF(ISNUMBER(AI17),AI17,IFERROR(INDEX(IF(CC_JobType="Decontamination",CC_TypeFillDC,CC_TypeFillCC),MATCH(E17,CC_TypeL,0)),1)) -> 1 | AU17: 1
A18: 9 | AD18: =IF(E18="Exchanger",IF(AND(ISNUMBER(S18),ISNUMBER(U18),ISNUMBER(V18)),S18*PI()/4*(U18*INDEX(LenF,MATCH($U$7,LenU,0)))^2*V18*INDEX(LenF,MATCH($V$7,LenU,0)),0)+IF(ISNUMBER(Y18),PI()/4*(Y18*INDEX(LenF,MATCH($Y$7,LenU,0)))^2*N(Z18)*INDEX(LenF,MATCH($Z$7,LenU,0))+IF(AA18="",0,IF(AA18="Conical",PI()/12*(Y18*INDEX(LenF,MATCH($Y$7,LenU,0)))^2*(0),INDEX(HeadK,MATCH(AA18,HeadU,0))*(Y18*INDEX(LenF,MATCH($Y$7,LenU,0)))^3)),0)+IF(ISNUMBER(Y18),PI()/4*(Y18*INDEX(LenF,MATCH($Y$7,LenU,0)))^2*N(AB18)*INDEX(LenF,MATCH($AB$7,LenU,0))+IF(AC18="",0,IF(AC18="Conical",PI()/12*(Y18*INDEX(LenF,MATCH($Y$7,LenU,0)))^2*(0),INDEX(HeadK,MATCH(AC18,HeadU,0))*(Y18*INDEX(LenF,MATCH($Y$7,LenU,0)))^3)),0),"") | AE18: =IF(OR(E18="",E18="Piping"),"",IF(E18="Exchanger",AQ18*AR18+IF(P18="",0,IF(P18="Conical",PI()/12*(SQRT(4*AQ18/PI()))^2*(0),INDEX(HeadK,MATCH(P18,HeadU,0))*(SQRT(4*AQ18/PI()))^3))-IF(AND(ISNUMBER(S18),ISNUMBER(V18)),S18*PI()/4*AP18^2*V18*INDEX(LenF,MATCH($V$7,LenU,0)),0),IF(ISNUMBER(N18),PI()/4*(N18*INDEX(LenF,MATCH($N$7,LenU,0)))^2*N(O18)*INDEX(LenF,MATCH($O$7,LenU,0))+IF(P18="",0,IF(P18="Conical",PI()/12*(N18*INDEX(LenF,MATCH($N$7,LenU,0)))^2*(N(R18)*INDEX(LenF,MATCH($R$7,LenU,0))),INDEX(HeadK,MATCH(P18,HeadU,0))*(N18*INDEX(LenF,MATCH($N$7,LenU,0)))^3))+IF(Q18="",0,IF(Q18="Conical",PI()/12*(N18*INDEX(LenF,MATCH($N$7,LenU,0)))^2*(N(R18)*INDEX(LenF,MATCH($R$7,LenU,0))),INDEX(HeadK,MATCH(Q18,HeadU,0))*(N18*INDEX(LenF,MATCH($N$7,LenU,0)))^3)),0))) | AF18: =IF(E18<>"Piping","",IF(AND(ISNUMBER(AS18),ISNUMBER(M18)),PI()/4*(AS18/1000)^2*M18*INDEX(LenF,MATCH($M$7,LenU,0)),0)) | AG18: =IF(E18="","",N(AD18)+N(AE18)+N(AF18)) | AH18: =IF(ISNUMBER(I18),I18*INDEX(WtF,MATCH($I$7,WtU,0))/CC_WaterRho,"") | AM18: =IF(AO18="","",AO18*IF(ISNUMBER(AK18),AK18,CC_DefFills)*(1+IF(ISNUMBER(AL18),AL18,CC_DefAllow))) | AN18: =IF(G18="Given volume",IF(ISNUMBER(H18),H18*INDEX(VolF,MATCH($H$7,VolU,0)),""),IF(G18="Water weight",AH18,IF(N(AG18)=0,"",AG18))) | AO18: =IF(N(AN18)=0,"",AN18*AT18*IF(ISNUMBER(AJ18),AJ18,CC_DefCirc)) | AP18: =IF(ISNUMBER(T18),T18*INDEX(LenF,MATCH($T$7,LenU,0)),IF(ISNUMBER(W18),W18*INDEX(LenF,MATCH($W$7,LenU,0))/CC_PitchRatio,0)) -> 0 | AQ18: =IF(ISNUMBER(N18),PI()/4*(N18*INDEX(LenF,MATCH($N$7,LenU,0)))^2,IF(AND(ISNUMBER(S18),ISNUMBER(W18),X18<>""),S18*(W18*INDEX(LenF,MATCH($W$7,LenU,0)))^2*INDEX(LayoutF,MATCH(X18,LayoutU,0)),0)) -> 0 | AR18: =IF(ISNUMBER(O18),O18*INDEX(LenF,MATCH($O$7,LenU,0)),IF(ISNUMBER(V18),V18*INDEX(LenF,MATCH($V$7,LenU,0)),0)) -> 0 | AS18: =IF(ISNUMBER(L18),L18*INDEX(LenF,MATCH($L$7,LenU,0))*1000,IF(OR(J18="",K18=""),"",IFERROR(IF(INDEX(PipeWT,MATCH(J18,NPSU,0),MATCH(K18,SchU,0))="","Sch n/a",INDEX(PipeOD,MATCH(J18,NPSU,0))-2*INDEX(PipeWT,MATCH(J18,NPSU,0),MATCH(K18,SchU,0))),""))) | AT18: =IF(ISNUMBER(AI18),AI18,IFERROR(INDEX(IF(CC_JobType="Decontamination",CC_TypeFillDC,CC_TypeFillCC),MATCH(E18,CC_TypeL,0)),1)) -> 1 | AU18: 1
A19: 10 | AD19: =IF(E19="Exchanger",IF(AND(ISNUMBER(S19),ISNUMBER(U19),ISNUMBER(V19)),S19*PI()/4*(U19*INDEX(LenF,MATCH($U$7,LenU,0)))^2*V19*INDEX(LenF,MATCH($V$7,LenU,0)),0)+IF(ISNUMBER(Y19),PI()/4*(Y19*INDEX(LenF,MATCH($Y$7,LenU,0)))^2*N(Z19)*INDEX(LenF,MATCH($Z$7,LenU,0))+IF(AA19="",0,IF(AA19="Conical",PI()/12*(Y19*INDEX(LenF,MATCH($Y$7,LenU,0)))^2*(0),INDEX(HeadK,MATCH(AA19,HeadU,0))*(Y19*INDEX(LenF,MATCH($Y$7,LenU,0)))^3)),0)+IF(ISNUMBER(Y19),PI()/4*(Y19*INDEX(LenF,MATCH($Y$7,LenU,0)))^2*N(AB19)*INDEX(LenF,MATCH($AB$7,LenU,0))+IF(AC19="",0,IF(AC19="Conical",PI()/12*(Y19*INDEX(LenF,MATCH($Y$7,LenU,0)))^2*(0),INDEX(HeadK,MATCH(AC19,HeadU,0))*(Y19*INDEX(LenF,MATCH($Y$7,LenU,0)))^3)),0),"") | AE19: =IF(OR(E19="",E19="Piping"),"",IF(E19="Exchanger",AQ19*AR19+IF(P19="",0,IF(P19="Conical",PI()/12*(SQRT(4*AQ19/PI()))^2*(0),INDEX(HeadK,MATCH(P19,HeadU,0))*(SQRT(4*AQ19/PI()))^3))-IF(AND(ISNUMBER(S19),ISNUMBER(V19)),S19*PI()/4*AP19^2*V19*INDEX(LenF,MATCH($V$7,LenU,0)),0),IF(ISNUMBER(N19),PI()/4*(N19*INDEX(LenF,MATCH($N$7,LenU,0)))^2*N(O19)*INDEX(LenF,MATCH($O$7,LenU,0))+IF(P19="",0,IF(P19="Conical",PI()/12*(N19*INDEX(LenF,MATCH($N$7,LenU,0)))^2*(N(R19)*INDEX(LenF,MATCH($R$7,LenU,0))),INDEX(HeadK,MATCH(P19,HeadU,0))*(N19*INDEX(LenF,MATCH($N$7,LenU,0)))^3))+IF(Q19="",0,IF(Q19="Conical",PI()/12*(N19*INDEX(LenF,MATCH($N$7,LenU,0)))^2*(N(R19)*INDEX(LenF,MATCH($R$7,LenU,0))),INDEX(HeadK,MATCH(Q19,HeadU,0))*(N19*INDEX(LenF,MATCH($N$7,LenU,0)))^3)),0))) | AF19: =IF(E19<>"Piping","",IF(AND(ISNUMBER(AS19),ISNUMBER(M19)),PI()/4*(AS19/1000)^2*M19*INDEX(LenF,MATCH($M$7,LenU,0)),0)) | AG19: =IF(E19="","",N(AD19)+N(AE19)+N(AF19)) | AH19: =IF(ISNUMBER(I19),I19*INDEX(WtF,MATCH($I$7,WtU,0))/CC_WaterRho,"") | AM19: =IF(AO19="","",AO19*IF(ISNUMBER(AK19),AK19,CC_DefFills)*(1+IF(ISNUMBER(AL19),AL19,CC_DefAllow))) | AN19: =IF(G19="Given volume",IF(ISNUMBER(H19),H19*INDEX(VolF,MATCH($H$7,VolU,0)),""),IF(G19="Water weight",AH19,IF(N(AG19)=0,"",AG19))) | AO19: =IF(N(AN19)=0,"",AN19*AT19*IF(ISNUMBER(AJ19),AJ19,CC_DefCirc)) | AP19: =IF(ISNUMBER(T19),T19*INDEX(LenF,MATCH($T$7,LenU,0)),IF(ISNUMBER(W19),W19*INDEX(LenF,MATCH($W$7,LenU,0))/CC_PitchRatio,0)) -> 0 | AQ19: =IF(ISNUMBER(N19),PI()/4*(N19*INDEX(LenF,MATCH($N$7,LenU,0)))^2,IF(AND(ISNUMBER(S19),ISNUMBER(W19),X19<>""),S19*(W19*INDEX(LenF,MATCH($W$7,LenU,0)))^2*INDEX(LayoutF,MATCH(X19,LayoutU,0)),0)) -> 0 | AR19: =IF(ISNUMBER(O19),O19*INDEX(LenF,MATCH($O$7,LenU,0)),IF(ISNUMBER(V19),V19*INDEX(LenF,MATCH($V$7,LenU,0)),0)) -> 0 | AS19: =IF(ISNUMBER(L19),L19*INDEX(LenF,MATCH($L$7,LenU,0))*1000,IF(OR(J19="",K19=""),"",IFERROR(IF(INDEX(PipeWT,MATCH(J19,NPSU,0),MATCH(K19,SchU,0))="","Sch n/a",INDEX(PipeOD,MATCH(J19,NPSU,0))-2*INDEX(PipeWT,MATCH(J19,NPSU,0),MATCH(K19,SchU,0))),""))) | AT19: =IF(ISNUMBER(AI19),AI19,IFERROR(INDEX(IF(CC_JobType="Decontamination",CC_TypeFillDC,CC_TypeFillCC),MATCH(E19,CC_TypeL,0)),1)) -> 1 | AU19: 1
A20: 11 | AD20: =IF(E20="Exchanger",IF(AND(ISNUMBER(S20),ISNUMBER(U20),ISNUMBER(V20)),S20*PI()/4*(U20*INDEX(LenF,MATCH($U$7,LenU,0)))^2*V20*INDEX(LenF,MATCH($V$7,LenU,0)),0)+IF(ISNUMBER(Y20),PI()/4*(Y20*INDEX(LenF,MATCH($Y$7,LenU,0)))^2*N(Z20)*INDEX(LenF,MATCH($Z$7,LenU,0))+IF(AA20="",0,IF(AA20="Conical",PI()/12*(Y20*INDEX(LenF,MATCH($Y$7,LenU,0)))^2*(0),INDEX(HeadK,MATCH(AA20,HeadU,0))*(Y20*INDEX(LenF,MATCH($Y$7,LenU,0)))^3)),0)+IF(ISNUMBER(Y20),PI()/4*(Y20*INDEX(LenF,MATCH($Y$7,LenU,0)))^2*N(AB20)*INDEX(LenF,MATCH($AB$7,LenU,0))+IF(AC20="",0,IF(AC20="Conical",PI()/12*(Y20*INDEX(LenF,MATCH($Y$7,LenU,0)))^2*(0),INDEX(HeadK,MATCH(AC20,HeadU,0))*(Y20*INDEX(LenF,MATCH($Y$7,LenU,0)))^3)),0),"") | AE20: =IF(OR(E20="",E20="Piping"),"",IF(E20="Exchanger",AQ20*AR20+IF(P20="",0,IF(P20="Conical",PI()/12*(SQRT(4*AQ20/PI()))^2*(0),INDEX(HeadK,MATCH(P20,HeadU,0))*(SQRT(4*AQ20/PI()))^3))-IF(AND(ISNUMBER(S20),ISNUMBER(V20)),S20*PI()/4*AP20^2*V20*INDEX(LenF,MATCH($V$7,LenU,0)),0),IF(ISNUMBER(N20),PI()/4*(N20*INDEX(LenF,MATCH($N$7,LenU,0)))^2*N(O20)*INDEX(LenF,MATCH($O$7,LenU,0))+IF(P20="",0,IF(P20="Conical",PI()/12*(N20*INDEX(LenF,MATCH($N$7,LenU,0)))^2*(N(R20)*INDEX(LenF,MATCH($R$7,LenU,0))),INDEX(HeadK,MATCH(P20,HeadU,0))*(N20*INDEX(LenF,MATCH($N$7,LenU,0)))^3))+IF(Q20="",0,IF(Q20="Conical",PI()/12*(N20*INDEX(LenF,MATCH($N$7,LenU,0)))^2*(N(R20)*INDEX(LenF,MATCH($R$7,LenU,0))),INDEX(HeadK,MATCH(Q20,HeadU,0))*(N20*INDEX(LenF,MATCH($N$7,LenU,0)))^3)),0))) | AF20: =IF(E20<>"Piping","",IF(AND(ISNUMBER(AS20),ISNUMBER(M20)),PI()/4*(AS20/1000)^2*M20*INDEX(LenF,MATCH($M$7,LenU,0)),0)) | AG20: =IF(E20="","",N(AD20)+N(AE20)+N(AF20)) | AH20: =IF(ISNUMBER(I20),I20*INDEX(WtF,MATCH($I$7,WtU,0))/CC_WaterRho,"") | AM20: =IF(AO20="","",AO20*IF(ISNUMBER(AK20),AK20,CC_DefFills)*(1+IF(ISNUMBER(AL20),AL20,CC_DefAllow))) | AN20: =IF(G20="Given volume",IF(ISNUMBER(H20),H20*INDEX(VolF,MATCH($H$7,VolU,0)),""),IF(G20="Water weight",AH20,IF(N(AG20)=0,"",AG20))) | AO20: =IF(N(AN20)=0,"",AN20*AT20*IF(ISNUMBER(AJ20),AJ20,CC_DefCirc)) | AP20: =IF(ISNUMBER(T20),T20*INDEX(LenF,MATCH($T$7,LenU,0)),IF(ISNUMBER(W20),W20*INDEX(LenF,MATCH($W$7,LenU,0))/CC_PitchRatio,0)) -> 0 | AQ20: =IF(ISNUMBER(N20),PI()/4*(N20*INDEX(LenF,MATCH($N$7,LenU,0)))^2,IF(AND(ISNUMBER(S20),ISNUMBER(W20),X20<>""),S20*(W20*INDEX(LenF,MATCH($W$7,LenU,0)))^2*INDEX(LayoutF,MATCH(X20,LayoutU,0)),0)) -> 0 | AR20: =IF(ISNUMBER(O20),O20*INDEX(LenF,MATCH($O$7,LenU,0)),IF(ISNUMBER(V20),V20*INDEX(LenF,MATCH($V$7,LenU,0)),0)) -> 0 | AS20: =IF(ISNUMBER(L20),L20*INDEX(LenF,MATCH($L$7,LenU,0))*1000,IF(OR(J20="",K20=""),"",IFERROR(IF(INDEX(PipeWT,MATCH(J20,NPSU,0),MATCH(K20,SchU,0))="","Sch n/a",INDEX(PipeOD,MATCH(J20,NPSU,0))-2*INDEX(PipeWT,MATCH(J20,NPSU,0),MATCH(K20,SchU,0))),""))) | AT20: =IF(ISNUMBER(AI20),AI20,IFERROR(INDEX(IF(CC_JobType="Decontamination",CC_TypeFillDC,CC_TypeFillCC),MATCH(E20,CC_TypeL,0)),1)) -> 1 | AU20: 1
A21: 12 | AD21: =IF(E21="Exchanger",IF(AND(ISNUMBER(S21),ISNUMBER(U21),ISNUMBER(V21)),S21*PI()/4*(U21*INDEX(LenF,MATCH($U$7,LenU,0)))^2*V21*INDEX(LenF,MATCH($V$7,LenU,0)),0)+IF(ISNUMBER(Y21),PI()/4*(Y21*INDEX(LenF,MATCH($Y$7,LenU,0)))^2*N(Z21)*INDEX(LenF,MATCH($Z$7,LenU,0))+IF(AA21="",0,IF(AA21="Conical",PI()/12*(Y21*INDEX(LenF,MATCH($Y$7,LenU,0)))^2*(0),INDEX(HeadK,MATCH(AA21,HeadU,0))*(Y21*INDEX(LenF,MATCH($Y$7,LenU,0)))^3)),0)+IF(ISNUMBER(Y21),PI()/4*(Y21*INDEX(LenF,MATCH($Y$7,LenU,0)))^2*N(AB21)*INDEX(LenF,MATCH($AB$7,LenU,0))+IF(AC21="",0,IF(AC21="Conical",PI()/12*(Y21*INDEX(LenF,MATCH($Y$7,LenU,0)))^2*(0),INDEX(HeadK,MATCH(AC21,HeadU,0))*(Y21*INDEX(LenF,MATCH($Y$7,LenU,0)))^3)),0),"") | AE21: =IF(OR(E21="",E21="Piping"),"",IF(E21="Exchanger",AQ21*AR21+IF(P21="",0,IF(P21="Conical",PI()/12*(SQRT(4*AQ21/PI()))^2*(0),INDEX(HeadK,MATCH(P21,HeadU,0))*(SQRT(4*AQ21/PI()))^3))-IF(AND(ISNUMBER(S21),ISNUMBER(V21)),S21*PI()/4*AP21^2*V21*INDEX(LenF,MATCH($V$7,LenU,0)),0),IF(ISNUMBER(N21),PI()/4*(N21*INDEX(LenF,MATCH($N$7,LenU,0)))^2*N(O21)*INDEX(LenF,MATCH($O$7,LenU,0))+IF(P21="",0,IF(P21="Conical",PI()/12*(N21*INDEX(LenF,MATCH($N$7,LenU,0)))^2*(N(R21)*INDEX(LenF,MATCH($R$7,LenU,0))),INDEX(HeadK,MATCH(P21,HeadU,0))*(N21*INDEX(LenF,MATCH($N$7,LenU,0)))^3))+IF(Q21="",0,IF(Q21="Conical",PI()/12*(N21*INDEX(LenF,MATCH($N$7,LenU,0)))^2*(N(R21)*INDEX(LenF,MATCH($R$7,LenU,0))),INDEX(HeadK,MATCH(Q21,HeadU,0))*(N21*INDEX(LenF,MATCH($N$7,LenU,0)))^3)),0))) | AF21: =IF(E21<>"Piping","",IF(AND(ISNUMBER(AS21),ISNUMBER(M21)),PI()/4*(AS21/1000)^2*M21*INDEX(LenF,MATCH($M$7,LenU,0)),0)) | AG21: =IF(E21="","",N(AD21)+N(AE21)+N(AF21)) | AH21: =IF(ISNUMBER(I21),I21*INDEX(WtF,MATCH($I$7,WtU,0))/CC_WaterRho,"") | AM21: =IF(AO21="","",AO21*IF(ISNUMBER(AK21),AK21,CC_DefFills)*(1+IF(ISNUMBER(AL21),AL21,CC_DefAllow))) | AN21: =IF(G21="Given volume",IF(ISNUMBER(H21),H21*INDEX(VolF,MATCH($H$7,VolU,0)),""),IF(G21="Water weight",AH21,IF(N(AG21)=0,"",AG21))) | AO21: =IF(N(AN21)=0,"",AN21*AT21*IF(ISNUMBER(AJ21),AJ21,CC_DefCirc)) | AP21: =IF(ISNUMBER(T21),T21*INDEX(LenF,MATCH($T$7,LenU,0)),IF(ISNUMBER(W21),W21*INDEX(LenF,MATCH($W$7,LenU,0))/CC_PitchRatio,0)) -> 0 | AQ21: =IF(ISNUMBER(N21),PI()/4*(N21*INDEX(LenF,MATCH($N$7,LenU,0)))^2,IF(AND(ISNUMBER(S21),ISNUMBER(W21),X21<>""),S21*(W21*INDEX(LenF,MATCH($W$7,LenU,0)))^2*INDEX(LayoutF,MATCH(X21,LayoutU,0)),0)) -> 0 | AR21: =IF(ISNUMBER(O21),O21*INDEX(LenF,MATCH($O$7,LenU,0)),IF(ISNUMBER(V21),V21*INDEX(LenF,MATCH($V$7,LenU,0)),0)) -> 0 | AS21: =IF(ISNUMBER(L21),L21*INDEX(LenF,MATCH($L$7,LenU,0))*1000,IF(OR(J21="",K21=""),"",IFERROR(IF(INDEX(PipeWT,MATCH(J21,NPSU,0),MATCH(K21,SchU,0))="","Sch n/a",INDEX(PipeOD,MATCH(J21,NPSU,0))-2*INDEX(PipeWT,MATCH(J21,NPSU,0),MATCH(K21,SchU,0))),""))) | AT21: =IF(ISNUMBER(AI21),AI21,IFERROR(INDEX(IF(CC_JobType="Decontamination",CC_TypeFillDC,CC_TypeFillCC),MATCH(E21,CC_TypeL,0)),1)) -> 1 | AU21: 1
A22: 13 | AD22: =IF(E22="Exchanger",IF(AND(ISNUMBER(S22),ISNUMBER(U22),ISNUMBER(V22)),S22*PI()/4*(U22*INDEX(LenF,MATCH($U$7,LenU,0)))^2*V22*INDEX(LenF,MATCH($V$7,LenU,0)),0)+IF(ISNUMBER(Y22),PI()/4*(Y22*INDEX(LenF,MATCH($Y$7,LenU,0)))^2*N(Z22)*INDEX(LenF,MATCH($Z$7,LenU,0))+IF(AA22="",0,IF(AA22="Conical",PI()/12*(Y22*INDEX(LenF,MATCH($Y$7,LenU,0)))^2*(0),INDEX(HeadK,MATCH(AA22,HeadU,0))*(Y22*INDEX(LenF,MATCH($Y$7,LenU,0)))^3)),0)+IF(ISNUMBER(Y22),PI()/4*(Y22*INDEX(LenF,MATCH($Y$7,LenU,0)))^2*N(AB22)*INDEX(LenF,MATCH($AB$7,LenU,0))+IF(AC22="",0,IF(AC22="Conical",PI()/12*(Y22*INDEX(LenF,MATCH($Y$7,LenU,0)))^2*(0),INDEX(HeadK,MATCH(AC22,HeadU,0))*(Y22*INDEX(LenF,MATCH($Y$7,LenU,0)))^3)),0),"") | AE22: =IF(OR(E22="",E22="Piping"),"",IF(E22="Exchanger",AQ22*AR22+IF(P22="",0,IF(P22="Conical",PI()/12*(SQRT(4*AQ22/PI()))^2*(0),INDEX(HeadK,MATCH(P22,HeadU,0))*(SQRT(4*AQ22/PI()))^3))-IF(AND(ISNUMBER(S22),ISNUMBER(V22)),S22*PI()/4*AP22^2*V22*INDEX(LenF,MATCH($V$7,LenU,0)),0),IF(ISNUMBER(N22),PI()/4*(N22*INDEX(LenF,MATCH($N$7,LenU,0)))^2*N(O22)*INDEX(LenF,MATCH($O$7,LenU,0))+IF(P22="",0,IF(P22="Conical",PI()/12*(N22*INDEX(LenF,MATCH($N$7,LenU,0)))^2*(N(R22)*INDEX(LenF,MATCH($R$7,LenU,0))),INDEX(HeadK,MATCH(P22,HeadU,0))*(N22*INDEX(LenF,MATCH($N$7,LenU,0)))^3))+IF(Q22="",0,IF(Q22="Conical",PI()/12*(N22*INDEX(LenF,MATCH($N$7,LenU,0)))^2*(N(R22)*INDEX(LenF,MATCH($R$7,LenU,0))),INDEX(HeadK,MATCH(Q22,HeadU,0))*(N22*INDEX(LenF,MATCH($N$7,LenU,0)))^3)),0))) | AF22: =IF(E22<>"Piping","",IF(AND(ISNUMBER(AS22),ISNUMBER(M22)),PI()/4*(AS22/1000)^2*M22*INDEX(LenF,MATCH($M$7,LenU,0)),0)) | AG22: =IF(E22="","",N(AD22)+N(AE22)+N(AF22)) | AH22: =IF(ISNUMBER(I22),I22*INDEX(WtF,MATCH($I$7,WtU,0))/CC_WaterRho,"") | AM22: =IF(AO22="","",AO22*IF(ISNUMBER(AK22),AK22,CC_DefFills)*(1+IF(ISNUMBER(AL22),AL22,CC_DefAllow))) | AN22: =IF(G22="Given volume",IF(ISNUMBER(H22),H22*INDEX(VolF,MATCH($H$7,VolU,0)),""),IF(G22="Water weight",AH22,IF(N(AG22)=0,"",AG22))) | AO22: =IF(N(AN22)=0,"",AN22*AT22*IF(ISNUMBER(AJ22),AJ22,CC_DefCirc)) | AP22: =IF(ISNUMBER(T22),T22*INDEX(LenF,MATCH($T$7,LenU,0)),IF(ISNUMBER(W22),W22*INDEX(LenF,MATCH($W$7,LenU,0))/CC_PitchRatio,0)) -> 0 | AQ22: =IF(ISNUMBER(N22),PI()/4*(N22*INDEX(LenF,MATCH($N$7,LenU,0)))^2,IF(AND(ISNUMBER(S22),ISNUMBER(W22),X22<>""),S22*(W22*INDEX(LenF,MATCH($W$7,LenU,0)))^2*INDEX(LayoutF,MATCH(X22,LayoutU,0)),0)) -> 0 | AR22: =IF(ISNUMBER(O22),O22*INDEX(LenF,MATCH($O$7,LenU,0)),IF(ISNUMBER(V22),V22*INDEX(LenF,MATCH($V$7,LenU,0)),0)) -> 0 | AS22: =IF(ISNUMBER(L22),L22*INDEX(LenF,MATCH($L$7,LenU,0))*1000,IF(OR(J22="",K22=""),"",IFERROR(IF(INDEX(PipeWT,MATCH(J22,NPSU,0),MATCH(K22,SchU,0))="","Sch n/a",INDEX(PipeOD,MATCH(J22,NPSU,0))-2*INDEX(PipeWT,MATCH(J22,NPSU,0),MATCH(K22,SchU,0))),""))) | AT22: =IF(ISNUMBER(AI22),AI22,IFERROR(INDEX(IF(CC_JobType="Decontamination",CC_TypeFillDC,CC_TypeFillCC),MATCH(E22,CC_TypeL,0)),1)) -> 1 | AU22: 1
A23: 14 | AD23: =IF(E23="Exchanger",IF(AND(ISNUMBER(S23),ISNUMBER(U23),ISNUMBER(V23)),S23*PI()/4*(U23*INDEX(LenF,MATCH($U$7,LenU,0)))^2*V23*INDEX(LenF,MATCH($V$7,LenU,0)),0)+IF(ISNUMBER(Y23),PI()/4*(Y23*INDEX(LenF,MATCH($Y$7,LenU,0)))^2*N(Z23)*INDEX(LenF,MATCH($Z$7,LenU,0))+IF(AA23="",0,IF(AA23="Conical",PI()/12*(Y23*INDEX(LenF,MATCH($Y$7,LenU,0)))^2*(0),INDEX(HeadK,MATCH(AA23,HeadU,0))*(Y23*INDEX(LenF,MATCH($Y$7,LenU,0)))^3)),0)+IF(ISNUMBER(Y23),PI()/4*(Y23*INDEX(LenF,MATCH($Y$7,LenU,0)))^2*N(AB23)*INDEX(LenF,MATCH($AB$7,LenU,0))+IF(AC23="",0,IF(AC23="Conical",PI()/12*(Y23*INDEX(LenF,MATCH($Y$7,LenU,0)))^2*(0),INDEX(HeadK,MATCH(AC23,HeadU,0))*(Y23*INDEX(LenF,MATCH($Y$7,LenU,0)))^3)),0),"") | AE23: =IF(OR(E23="",E23="Piping"),"",IF(E23="Exchanger",AQ23*AR23+IF(P23="",0,IF(P23="Conical",PI()/12*(SQRT(4*AQ23/PI()))^2*(0),INDEX(HeadK,MATCH(P23,HeadU,0))*(SQRT(4*AQ23/PI()))^3))-IF(AND(ISNUMBER(S23),ISNUMBER(V23)),S23*PI()/4*AP23^2*V23*INDEX(LenF,MATCH($V$7,LenU,0)),0),IF(ISNUMBER(N23),PI()/4*(N23*INDEX(LenF,MATCH($N$7,LenU,0)))^2*N(O23)*INDEX(LenF,MATCH($O$7,LenU,0))+IF(P23="",0,IF(P23="Conical",PI()/12*(N23*INDEX(LenF,MATCH($N$7,LenU,0)))^2*(N(R23)*INDEX(LenF,MATCH($R$7,LenU,0))),INDEX(HeadK,MATCH(P23,HeadU,0))*(N23*INDEX(LenF,MATCH($N$7,LenU,0)))^3))+IF(Q23="",0,IF(Q23="Conical",PI()/12*(N23*INDEX(LenF,MATCH($N$7,LenU,0)))^2*(N(R23)*INDEX(LenF,MATCH($R$7,LenU,0))),INDEX(HeadK,MATCH(Q23,HeadU,0))*(N23*INDEX(LenF,MATCH($N$7,LenU,0)))^3)),0))) | AF23: =IF(E23<>"Piping","",IF(AND(ISNUMBER(AS23),ISNUMBER(M23)),PI()/4*(AS23/1000)^2*M23*INDEX(LenF,MATCH($M$7,LenU,0)),0)) | AG23: =IF(E23="","",N(AD23)+N(AE23)+N(AF23)) | AH23: =IF(ISNUMBER(I23),I23*INDEX(WtF,MATCH($I$7,WtU,0))/CC_WaterRho,"") | AM23: =IF(AO23="","",AO23*IF(ISNUMBER(AK23),AK23,CC_DefFills)*(1+IF(ISNUMBER(AL23),AL23,CC_DefAllow))) | AN23: =IF(G23="Given volume",IF(ISNUMBER(H23),H23*INDEX(VolF,MATCH($H$7,VolU,0)),""),IF(G23="Water weight",AH23,IF(N(AG23)=0,"",AG23))) | AO23: =IF(N(AN23)=0,"",AN23*AT23*IF(ISNUMBER(AJ23),AJ23,CC_DefCirc)) | AP23: =IF(ISNUMBER(T23),T23*INDEX(LenF,MATCH($T$7,LenU,0)),IF(ISNUMBER(W23),W23*INDEX(LenF,MATCH($W$7,LenU,0))/CC_PitchRatio,0)) -> 0 | AQ23: =IF(ISNUMBER(N23),PI()/4*(N23*INDEX(LenF,MATCH($N$7,LenU,0)))^2,IF(AND(ISNUMBER(S23),ISNUMBER(W23),X23<>""),S23*(W23*INDEX(LenF,MATCH($W$7,LenU,0)))^2*INDEX(LayoutF,MATCH(X23,LayoutU,0)),0)) -> 0 | AR23: =IF(ISNUMBER(O23),O23*INDEX(LenF,MATCH($O$7,LenU,0)),IF(ISNUMBER(V23),V23*INDEX(LenF,MATCH($V$7,LenU,0)),0)) -> 0 | AS23: =IF(ISNUMBER(L23),L23*INDEX(LenF,MATCH($L$7,LenU,0))*1000,IF(OR(J23="",K23=""),"",IFERROR(IF(INDEX(PipeWT,MATCH(J23,NPSU,0),MATCH(K23,SchU,0))="","Sch n/a",INDEX(PipeOD,MATCH(J23,NPSU,0))-2*INDEX(PipeWT,MATCH(J23,NPSU,0),MATCH(K23,SchU,0))),""))) | AT23: =IF(ISNUMBER(AI23),AI23,IFERROR(INDEX(IF(CC_JobType="Decontamination",CC_TypeFillDC,CC_TypeFillCC),MATCH(E23,CC_TypeL,0)),1)) -> 1 | AU23: 1
A24: 15 | AD24: =IF(E24="Exchanger",IF(AND(ISNUMBER(S24),ISNUMBER(U24),ISNUMBER(V24)),S24*PI()/4*(U24*INDEX(LenF,MATCH($U$7,LenU,0)))^2*V24*INDEX(LenF,MATCH($V$7,LenU,0)),0)+IF(ISNUMBER(Y24),PI()/4*(Y24*INDEX(LenF,MATCH($Y$7,LenU,0)))^2*N(Z24)*INDEX(LenF,MATCH($Z$7,LenU,0))+IF(AA24="",0,IF(AA24="Conical",PI()/12*(Y24*INDEX(LenF,MATCH($Y$7,LenU,0)))^2*(0),INDEX(HeadK,MATCH(AA24,HeadU,0))*(Y24*INDEX(LenF,MATCH($Y$7,LenU,0)))^3)),0)+IF(ISNUMBER(Y24),PI()/4*(Y24*INDEX(LenF,MATCH($Y$7,LenU,0)))^2*N(AB24)*INDEX(LenF,MATCH($AB$7,LenU,0))+IF(AC24="",0,IF(AC24="Conical",PI()/12*(Y24*INDEX(LenF,MATCH($Y$7,LenU,0)))^2*(0),INDEX(HeadK,MATCH(AC24,HeadU,0))*(Y24*INDEX(LenF,MATCH($Y$7,LenU,0)))^3)),0),"") | AE24: =IF(OR(E24="",E24="Piping"),"",IF(E24="Exchanger",AQ24*AR24+IF(P24="",0,IF(P24="Conical",PI()/12*(SQRT(4*AQ24/PI()))^2*(0),INDEX(HeadK,MATCH(P24,HeadU,0))*(SQRT(4*AQ24/PI()))^3))-IF(AND(ISNUMBER(S24),ISNUMBER(V24)),S24*PI()/4*AP24^2*V24*INDEX(LenF,MATCH($V$7,LenU,0)),0),IF(ISNUMBER(N24),PI()/4*(N24*INDEX(LenF,MATCH($N$7,LenU,0)))^2*N(O24)*INDEX(LenF,MATCH($O$7,LenU,0))+IF(P24="",0,IF(P24="Conical",PI()/12*(N24*INDEX(LenF,MATCH($N$7,LenU,0)))^2*(N(R24)*INDEX(LenF,MATCH($R$7,LenU,0))),INDEX(HeadK,MATCH(P24,HeadU,0))*(N24*INDEX(LenF,MATCH($N$7,LenU,0)))^3))+IF(Q24="",0,IF(Q24="Conical",PI()/12*(N24*INDEX(LenF,MATCH($N$7,LenU,0)))^2*(N(R24)*INDEX(LenF,MATCH($R$7,LenU,0))),INDEX(HeadK,MATCH(Q24,HeadU,0))*(N24*INDEX(LenF,MATCH($N$7,LenU,0)))^3)),0))) | AF24: =IF(E24<>"Piping","",IF(AND(ISNUMBER(AS24),ISNUMBER(M24)),PI()/4*(AS24/1000)^2*M24*INDEX(LenF,MATCH($M$7,LenU,0)),0)) | AG24: =IF(E24="","",N(AD24)+N(AE24)+N(AF24)) | AH24: =IF(ISNUMBER(I24),I24*INDEX(WtF,MATCH($I$7,WtU,0))/CC_WaterRho,"") | AM24: =IF(AO24="","",AO24*IF(ISNUMBER(AK24),AK24,CC_DefFills)*(1+IF(ISNUMBER(AL24),AL24,CC_DefAllow))) | AN24: =IF(G24="Given volume",IF(ISNUMBER(H24),H24*INDEX(VolF,MATCH($H$7,VolU,0)),""),IF(G24="Water weight",AH24,IF(N(AG24)=0,"",AG24))) | AO24: =IF(N(AN24)=0,"",AN24*AT24*IF(ISNUMBER(AJ24),AJ24,CC_DefCirc)) | AP24: =IF(ISNUMBER(T24),T24*INDEX(LenF,MATCH($T$7,LenU,0)),IF(ISNUMBER(W24),W24*INDEX(LenF,MATCH($W$7,LenU,0))/CC_PitchRatio,0)) -> 0 | AQ24: =IF(ISNUMBER(N24),PI()/4*(N24*INDEX(LenF,MATCH($N$7,LenU,0)))^2,IF(AND(ISNUMBER(S24),ISNUMBER(W24),X24<>""),S24*(W24*INDEX(LenF,MATCH($W$7,LenU,0)))^2*INDEX(LayoutF,MATCH(X24,LayoutU,0)),0)) -> 0 | AR24: =IF(ISNUMBER(O24),O24*INDEX(LenF,MATCH($O$7,LenU,0)),IF(ISNUMBER(V24),V24*INDEX(LenF,MATCH($V$7,LenU,0)),0)) -> 0 | AS24: =IF(ISNUMBER(L24),L24*INDEX(LenF,MATCH($L$7,LenU,0))*1000,IF(OR(J24="",K24=""),"",IFERROR(IF(INDEX(PipeWT,MATCH(J24,NPSU,0),MATCH(K24,SchU,0))="","Sch n/a",INDEX(PipeOD,MATCH(J24,NPSU,0))-2*INDEX(PipeWT,MATCH(J24,NPSU,0),MATCH(K24,SchU,0))),""))) | AT24: =IF(ISNUMBER(AI24),AI24,IFERROR(INDEX(IF(CC_JobType="Decontamination",CC_TypeFillDC,CC_TypeFillCC),MATCH(E24,CC_TypeL,0)),1)) -> 1 | AU24: 1
A25: 16 | AD25: =IF(E25="Exchanger",IF(AND(ISNUMBER(S25),ISNUMBER(U25),ISNUMBER(V25)),S25*PI()/4*(U25*INDEX(LenF,MATCH($U$7,LenU,0)))^2*V25*INDEX(LenF,MATCH($V$7,LenU,0)),0)+IF(ISNUMBER(Y25),PI()/4*(Y25*INDEX(LenF,MATCH($Y$7,LenU,0)))^2*N(Z25)*INDEX(LenF,MATCH($Z$7,LenU,0))+IF(AA25="",0,IF(AA25="Conical",PI()/12*(Y25*INDEX(LenF,MATCH($Y$7,LenU,0)))^2*(0),INDEX(HeadK,MATCH(AA25,HeadU,0))*(Y25*INDEX(LenF,MATCH($Y$7,LenU,0)))^3)),0)+IF(ISNUMBER(Y25),PI()/4*(Y25*INDEX(LenF,MATCH($Y$7,LenU,0)))^2*N(AB25)*INDEX(LenF,MATCH($AB$7,LenU,0))+IF(AC25="",0,IF(AC25="Conical",PI()/12*(Y25*INDEX(LenF,MATCH($Y$7,LenU,0)))^2*(0),INDEX(HeadK,MATCH(AC25,HeadU,0))*(Y25*INDEX(LenF,MATCH($Y$7,LenU,0)))^3)),0),"") | AE25: =IF(OR(E25="",E25="Piping"),"",IF(E25="Exchanger",AQ25*AR25+IF(P25="",0,IF(P25="Conical",PI()/12*(SQRT(4*AQ25/PI()))^2*(0),INDEX(HeadK,MATCH(P25,HeadU,0))*(SQRT(4*AQ25/PI()))^3))-IF(AND(ISNUMBER(S25),ISNUMBER(V25)),S25*PI()/4*AP25^2*V25*INDEX(LenF,MATCH($V$7,LenU,0)),0),IF(ISNUMBER(N25),PI()/4*(N25*INDEX(LenF,MATCH($N$7,LenU,0)))^2*N(O25)*INDEX(LenF,MATCH($O$7,LenU,0))+IF(P25="",0,IF(P25="Conical",PI()/12*(N25*INDEX(LenF,MATCH($N$7,LenU,0)))^2*(N(R25)*INDEX(LenF,MATCH($R$7,LenU,0))),INDEX(HeadK,MATCH(P25,HeadU,0))*(N25*INDEX(LenF,MATCH($N$7,LenU,0)))^3))+IF(Q25="",0,IF(Q25="Conical",PI()/12*(N25*INDEX(LenF,MATCH($N$7,LenU,0)))^2*(N(R25)*INDEX(LenF,MATCH($R$7,LenU,0))),INDEX(HeadK,MATCH(Q25,HeadU,0))*(N25*INDEX(LenF,MATCH($N$7,LenU,0)))^3)),0))) | AF25: =IF(E25<>"Piping","",IF(AND(ISNUMBER(AS25),ISNUMBER(M25)),PI()/4*(AS25/1000)^2*M25*INDEX(LenF,MATCH($M$7,LenU,0)),0)) | AG25: =IF(E25="","",N(AD25)+N(AE25)+N(AF25)) | AH25: =IF(ISNUMBER(I25),I25*INDEX(WtF,MATCH($I$7,WtU,0))/CC_WaterRho,"") | AM25: =IF(AO25="","",AO25*IF(ISNUMBER(AK25),AK25,CC_DefFills)*(1+IF(ISNUMBER(AL25),AL25,CC_DefAllow))) | AN25: =IF(G25="Given volume",IF(ISNUMBER(H25),H25*INDEX(VolF,MATCH($H$7,VolU,0)),""),IF(G25="Water weight",AH25,IF(N(AG25)=0,"",AG25))) | AO25: =IF(N(AN25)=0,"",AN25*AT25*IF(ISNUMBER(AJ25),AJ25,CC_DefCirc)) | AP25: =IF(ISNUMBER(T25),T25*INDEX(LenF,MATCH($T$7,LenU,0)),IF(ISNUMBER(W25),W25*INDEX(LenF,MATCH($W$7,LenU,0))/CC_PitchRatio,0)) -> 0 | AQ25: =IF(ISNUMBER(N25),PI()/4*(N25*INDEX(LenF,MATCH($N$7,LenU,0)))^2,IF(AND(ISNUMBER(S25),ISNUMBER(W25),X25<>""),S25*(W25*INDEX(LenF,MATCH($W$7,LenU,0)))^2*INDEX(LayoutF,MATCH(X25,LayoutU,0)),0)) -> 0 | AR25: =IF(ISNUMBER(O25),O25*INDEX(LenF,MATCH($O$7,LenU,0)),IF(ISNUMBER(V25),V25*INDEX(LenF,MATCH($V$7,LenU,0)),0)) -> 0 | AS25: =IF(ISNUMBER(L25),L25*INDEX(LenF,MATCH($L$7,LenU,0))*1000,IF(OR(J25="",K25=""),"",IFERROR(IF(INDEX(PipeWT,MATCH(J25,NPSU,0),MATCH(K25,SchU,0))="","Sch n/a",INDEX(PipeOD,MATCH(J25,NPSU,0))-2*INDEX(PipeWT,MATCH(J25,NPSU,0),MATCH(K25,SchU,0))),""))) | AT25: =IF(ISNUMBER(AI25),AI25,IFERROR(INDEX(IF(CC_JobType="Decontamination",CC_TypeFillDC,CC_TypeFillCC),MATCH(E25,CC_TypeL,0)),1)) -> 1 | AU25: 1
... A39: 30 | AD39: =IF(E39="Exchanger",IF(AND(ISNUMBER(S39),ISNUMBER(U39),ISNUMBER(V39)),S39*PI()/4*(U39*INDEX(LenF,MATCH($U$7,LenU,0)))^2*V39*INDEX(LenF,MATCH($V$7,LenU,0)),0)+IF(ISNUMBER(Y39),PI()/4*(Y39*INDEX(LenF,MATCH($Y$7,LenU,0)))^2*N(Z39)*INDEX(LenF,MATCH($Z$7,LenU,0))+IF(AA39="",0,IF(AA39="Conical",PI()/12*(Y39*INDEX(LenF,MATCH($Y$7,LenU,0)))^2*(0),INDEX(HeadK,MATCH(AA39,HeadU,0))*(Y39*INDEX(LenF,MATCH($Y$7,LenU,0)))^3)),0)+IF(ISNUMBER(Y39),PI()/4*(Y39*INDEX(LenF,MATCH($Y$7,LenU,0)))^2*N(AB39)*INDEX(LenF,MATCH($AB$7,LenU,0))+IF(AC39="",0,IF(AC39="Conical",PI()/12*(Y39*INDEX(LenF,MATCH($Y$7,LenU,0)))^2*(0),INDEX(HeadK,MATCH(AC39,HeadU,0))*(Y39*INDEX(LenF,MATCH($Y$7,LenU,0)))^3)),0),"") | AE39: =IF(OR(E39="",E39="Piping"),"",IF(E39="Exchanger",AQ39*AR39+IF(P39="",0,IF(P39="Conical",PI()/12*(SQRT(4*AQ39/PI()))^2*(0),INDEX(HeadK,MATCH(P39,HeadU,0))*(SQRT(4*AQ39/PI()))^3))-IF(AND(ISNUMBER(S39),ISNUMBER(V39)),S39*PI()/4*AP39^2*V39*INDEX(LenF,MATCH($V$7,LenU,0)),0),IF(ISNUMBER(N39),PI()/4*(N39*INDEX(LenF,MATCH($N$7,LenU,0)))^2*N(O39)*INDEX(LenF,MATCH($O$7,LenU,0))+IF(P39="",0,IF(P39="Conical",PI()/12*(N39*INDEX(LenF,MATCH($N$7,LenU,0)))^2*(N(R39)*INDEX(LenF,MATCH($R$7,LenU,0))),INDEX(HeadK,MATCH(P39,HeadU,0))*(N39*INDEX(LenF,MATCH($N$7,LenU,0)))^3))+IF(Q39="",0,IF(Q39="Conical",PI()/12*(N39*INDEX(LenF,MATCH($N$7,LenU,0)))^2*(N(R39)*INDEX(LenF,MATCH($R$7,LenU,0))),INDEX(HeadK,MATCH(Q39,HeadU,0))*(N39*INDEX(LenF,MATCH($N$7,LenU,0)))^3)),0))) | AF39: =IF(E39<>"Piping","",IF(AND(ISNUMBER(AS39),ISNUMBER(M39)),PI()/4*(AS39/1000)^2*M39*INDEX(LenF,MATCH($M$7,LenU,0)),0)) | AG39: =IF(E39="","",N(AD39)+N(AE39)+N(AF39)) | AH39: =IF(ISNUMBER(I39),I39*INDEX(WtF,MATCH($I$7,WtU,0))/CC_WaterRho,"") | AM39: =IF(AO39="","",AO39*IF(ISNUMBER(AK39),AK39,CC_DefFills)*(1+IF(ISNUMBER(AL39),AL39,CC_DefAllow))) | AN39: =IF(G39="Given volume",IF(ISNUMBER(H39),H39*INDEX(VolF,MATCH($H$7,VolU,0)),""),IF(G39="Water weight",AH39,IF(N(AG39)=0,"",AG39))) | AO39: =IF(N(AN39)=0,"",AN39*AT39*IF(ISNUMBER(AJ39),AJ39,CC_DefCirc)) | AP39: =IF(ISNUMBER(T39),T39*INDEX(LenF,MATCH($T$7,LenU,0)),IF(ISNUMBER(W39),W39*INDEX(LenF,MATCH($W$7,LenU,0))/CC_PitchRatio,0)) -> 0 | AQ39: =IF(ISNUMBER(N39),PI()/4*(N39*INDEX(LenF,MATCH($N$7,LenU,0)))^2,IF(AND(ISNUMBER(S39),ISNUMBER(W39),X39<>""),S39*(W39*INDEX(LenF,MATCH($W$7,LenU,0)))^2*INDEX(LayoutF,MATCH(X39,LayoutU,0)),0)) -> 0 | AR39: =IF(ISNUMBER(O39),O39*INDEX(LenF,MATCH($O$7,LenU,0)),IF(ISNUMBER(V39),V39*INDEX(LenF,MATCH($V$7,LenU,0)),0)) -> 0 | AS39: =IF(ISNUMBER(L39),L39*INDEX(LenF,MATCH($L$7,LenU,0))*1000,IF(OR(J39="",K39=""),"",IFERROR(IF(INDEX(PipeWT,MATCH(J39,NPSU,0),MATCH(K39,SchU,0))="","Sch n/a",INDEX(PipeOD,MATCH(J39,NPSU,0))-2*INDEX(PipeWT,MATCH(J39,NPSU,0),MATCH(K39,SchU,0))),""))) | AT39: =IF(ISNUMBER(AI39),AI39,IFERROR(INDEX(IF(CC_JobType="Decontamination",CC_TypeFillDC,CC_TypeFillCC),MATCH(E39,CC_TypeL,0)),1)) -> 1 | AU39: 1
A40: ="TOTAL – "&INDEX(CC_UnitNames,1) -> TOTAL – Unit 1 | S40: =COUNT(AN10:AN39)&" items" -> 4 items | AD40: =SUM(AD10:AD39) -> 1.1132452 | AE40: =SUM(AE10:AE39) -> 23.09113 | AF40: =SUM(AF10:AF39) -> 2.2375032 | AG40: =SUM(AG10:AG39) -> 26.441878 | AH40: =SUM(AH10:AH39) -> 0 | AM40: =SUM(AM10:AM39) -> 256.98561 | AN40: =SUM(AN10:AN39) -> 53.556878 | AO40: =SUM(AO10:AO39) -> 41.117698
A42: ="UNIT 2: "&INDEX(CC_UnitNames,2) -> UNIT 2: Unit 2
A43: 1 | AD43: =IF(E43="Exchanger",IF(AND(ISNUMBER(S43),ISNUMBER(U43),ISNUMBER(V43)),S43*PI()/4*(U43*INDEX(LenF,MATCH($U$7,LenU,0)))^2*V43*INDEX(LenF,MATCH($V$7,LenU,0)),0)+IF(ISNUMBER(Y43),PI()/4*(Y43*INDEX(LenF,MATCH($Y$7,LenU,0)))^2*N(Z43)*INDEX(LenF,MATCH($Z$7,LenU,0))+IF(AA43="",0,IF(AA43="Conical",PI()/12*(Y43*INDEX(LenF,MATCH($Y$7,LenU,0)))^2*(0),INDEX(HeadK,MATCH(AA43,HeadU,0))*(Y43*INDEX(LenF,MATCH($Y$7,LenU,0)))^3)),0)+IF(ISNUMBER(Y43),PI()/4*(Y43*INDEX(LenF,MATCH($Y$7,LenU,0)))^2*N(AB43)*INDEX(LenF,MATCH($AB$7,LenU,0))+IF(AC43="",0,IF(AC43="Conical",PI()/12*(Y43*INDEX(LenF,MATCH($Y$7,LenU,0)))^2*(0),INDEX(HeadK,MATCH(AC43,HeadU,0))*(Y43*INDEX(LenF,MATCH($Y$7,LenU,0)))^3)),0),"") | AE43: =IF(OR(E43="",E43="Piping"),"",IF(E43="Exchanger",AQ43*AR43+IF(P43="",0,IF(P43="Conical",PI()/12*(SQRT(4*AQ43/PI()))^2*(0),INDEX(HeadK,MATCH(P43,HeadU,0))*(SQRT(4*AQ43/PI()))^3))-IF(AND(ISNUMBER(S43),ISNUMBER(V43)),S43*PI()/4*AP43^2*V43*INDEX(LenF,MATCH($V$7,LenU,0)),0),IF(ISNUMBER(N43),PI()/4*(N43*INDEX(LenF,MATCH($N$7,LenU,0)))^2*N(O43)*INDEX(LenF,MATCH($O$7,LenU,0))+IF(P43="",0,IF(P43="Conical",PI()/12*(N43*INDEX(LenF,MATCH($N$7,LenU,0)))^2*(N(R43)*INDEX(LenF,MATCH($R$7,LenU,0))),INDEX(HeadK,MATCH(P43,HeadU,0))*(N43*INDEX(LenF,MATCH($N$7,LenU,0)))^3))+IF(Q43="",0,IF(Q43="Conical",PI()/12*(N43*INDEX(LenF,MATCH($N$7,LenU,0)))^2*(N(R43)*INDEX(LenF,MATCH($R$7,LenU,0))),INDEX(HeadK,MATCH(Q43,HeadU,0))*(N43*INDEX(LenF,MATCH($N$7,LenU,0)))^3)),0))) | AF43: =IF(E43<>"Piping","",IF(AND(ISNUMBER(AS43),ISNUMBER(M43)),PI()/4*(AS43/1000)^2*M43*INDEX(LenF,MATCH($M$7,LenU,0)),0)) | AG43: =IF(E43="","",N(AD43)+N(AE43)+N(AF43)) | AH43: =IF(ISNUMBER(I43),I43*INDEX(WtF,MATCH($I$7,WtU,0))/CC_WaterRho,"") | AM43: =IF(AO43="","",AO43*IF(ISNUMBER(AK43),AK43,CC_DefFills)*(1+IF(ISNUMBER(AL43),AL43,CC_DefAllow))) | AN43: =IF(G43="Given volume",IF(ISNUMBER(H43),H43*INDEX(VolF,MATCH($H$7,VolU,0)),""),IF(G43="Water weight",AH43,IF(N(AG43)=0,"",AG43))) | AO43: =IF(N(AN43)=0,"",AN43*AT43*IF(ISNUMBER(AJ43),AJ43,CC_DefCirc)) | AP43: =IF(ISNUMBER(T43),T43*INDEX(LenF,MATCH($T$7,LenU,0)),IF(ISNUMBER(W43),W43*INDEX(LenF,MATCH($W$7,LenU,0))/CC_PitchRatio,0)) -> 0 | AQ43: =IF(ISNUMBER(N43),PI()/4*(N43*INDEX(LenF,MATCH($N$7,LenU,0)))^2,IF(AND(ISNUMBER(S43),ISNUMBER(W43),X43<>""),S43*(W43*INDEX(LenF,MATCH($W$7,LenU,0)))^2*INDEX(LayoutF,MATCH(X43,LayoutU,0)),0)) -> 0 | AR43: =IF(ISNUMBER(O43),O43*INDEX(LenF,MATCH($O$7,LenU,0)),IF(ISNUMBER(V43),V43*INDEX(LenF,MATCH($V$7,LenU,0)),0)) -> 0 | AS43: =IF(ISNUMBER(L43),L43*INDEX(LenF,MATCH($L$7,LenU,0))*1000,IF(OR(J43="",K43=""),"",IFERROR(IF(INDEX(PipeWT,MATCH(J43,NPSU,0),MATCH(K43,SchU,0))="","Sch n/a",INDEX(PipeOD,MATCH(J43,NPSU,0))-2*INDEX(PipeWT,MATCH(J43,NPSU,0),MATCH(K43,SchU,0))),""))) | AT43: =IF(ISNUMBER(AI43),AI43,IFERROR(INDEX(IF(CC_JobType="Decontamination",CC_TypeFillDC,CC_TypeFillCC),MATCH(E43,CC_TypeL,0)),1)) -> 1 | AU43: 2
A44: 2 | AD44: =IF(E44="Exchanger",IF(AND(ISNUMBER(S44),ISNUMBER(U44),ISNUMBER(V44)),S44*PI()/4*(U44*INDEX(LenF,MATCH($U$7,LenU,0)))^2*V44*INDEX(LenF,MATCH($V$7,LenU,0)),0)+IF(ISNUMBER(Y44),PI()/4*(Y44*INDEX(LenF,MATCH($Y$7,LenU,0)))^2*N(Z44)*INDEX(LenF,MATCH($Z$7,LenU,0))+IF(AA44="",0,IF(AA44="Conical",PI()/12*(Y44*INDEX(LenF,MATCH($Y$7,LenU,0)))^2*(0),INDEX(HeadK,MATCH(AA44,HeadU,0))*(Y44*INDEX(LenF,MATCH($Y$7,LenU,0)))^3)),0)+IF(ISNUMBER(Y44),PI()/4*(Y44*INDEX(LenF,MATCH($Y$7,LenU,0)))^2*N(AB44)*INDEX(LenF,MATCH($AB$7,LenU,0))+IF(AC44="",0,IF(AC44="Conical",PI()/12*(Y44*INDEX(LenF,MATCH($Y$7,LenU,0)))^2*(0),INDEX(HeadK,MATCH(AC44,HeadU,0))*(Y44*INDEX(LenF,MATCH($Y$7,LenU,0)))^3)),0),"") | AE44: =IF(OR(E44="",E44="Piping"),"",IF(E44="Exchanger",AQ44*AR44+IF(P44="",0,IF(P44="Conical",PI()/12*(SQRT(4*AQ44/PI()))^2*(0),INDEX(HeadK,MATCH(P44,HeadU,0))*(SQRT(4*AQ44/PI()))^3))-IF(AND(ISNUMBER(S44),ISNUMBER(V44)),S44*PI()/4*AP44^2*V44*INDEX(LenF,MATCH($V$7,LenU,0)),0),IF(ISNUMBER(N44),PI()/4*(N44*INDEX(LenF,MATCH($N$7,LenU,0)))^2*N(O44)*INDEX(LenF,MATCH($O$7,LenU,0))+IF(P44="",0,IF(P44="Conical",PI()/12*(N44*INDEX(LenF,MATCH($N$7,LenU,0)))^2*(N(R44)*INDEX(LenF,MATCH($R$7,LenU,0))),INDEX(HeadK,MATCH(P44,HeadU,0))*(N44*INDEX(LenF,MATCH($N$7,LenU,0)))^3))+IF(Q44="",0,IF(Q44="Conical",PI()/12*(N44*INDEX(LenF,MATCH($N$7,LenU,0)))^2*(N(R44)*INDEX(LenF,MATCH($R$7,LenU,0))),INDEX(HeadK,MATCH(Q44,HeadU,0))*(N44*INDEX(LenF,MATCH($N$7,LenU,0)))^3)),0))) | AF44: =IF(E44<>"Piping","",IF(AND(ISNUMBER(AS44),ISNUMBER(M44)),PI()/4*(AS44/1000)^2*M44*INDEX(LenF,MATCH($M$7,LenU,0)),0)) | AG44: =IF(E44="","",N(AD44)+N(AE44)+N(AF44)) | AH44: =IF(ISNUMBER(I44),I44*INDEX(WtF,MATCH($I$7,WtU,0))/CC_WaterRho,"") | AM44: =IF(AO44="","",AO44*IF(ISNUMBER(AK44),AK44,CC_DefFills)*(1+IF(ISNUMBER(AL44),AL44,CC_DefAllow))) | AN44: =IF(G44="Given volume",IF(ISNUMBER(H44),H44*INDEX(VolF,MATCH($H$7,VolU,0)),""),IF(G44="Water weight",AH44,IF(N(AG44)=0,"",AG44))) | AO44: =IF(N(AN44)=0,"",AN44*AT44*IF(ISNUMBER(AJ44),AJ44,CC_DefCirc)) | AP44: =IF(ISNUMBER(T44),T44*INDEX(LenF,MATCH($T$7,LenU,0)),IF(ISNUMBER(W44),W44*INDEX(LenF,MATCH($W$7,LenU,0))/CC_PitchRatio,0)) -> 0 | AQ44: =IF(ISNUMBER(N44),PI()/4*(N44*INDEX(LenF,MATCH($N$7,LenU,0)))^2,IF(AND(ISNUMBER(S44),ISNUMBER(W44),X44<>""),S44*(W44*INDEX(LenF,MATCH($W$7,LenU,0)))^2*INDEX(LayoutF,MATCH(X44,LayoutU,0)),0)) -> 0 | AR44: =IF(ISNUMBER(O44),O44*INDEX(LenF,MATCH($O$7,LenU,0)),IF(ISNUMBER(V44),V44*INDEX(LenF,MATCH($V$7,LenU,0)),0)) -> 0 | AS44: =IF(ISNUMBER(L44),L44*INDEX(LenF,MATCH($L$7,LenU,0))*1000,IF(OR(J44="",K44=""),"",IFERROR(IF(INDEX(PipeWT,MATCH(J44,NPSU,0),MATCH(K44,SchU,0))="","Sch n/a",INDEX(PipeOD,MATCH(J44,NPSU,0))-2*INDEX(PipeWT,MATCH(J44,NPSU,0),MATCH(K44,SchU,0))),""))) | AT44: =IF(ISNUMBER(AI44),AI44,IFERROR(INDEX(IF(CC_JobType="Decontamination",CC_TypeFillDC,CC_TypeFillCC),MATCH(E44,CC_TypeL,0)),1)) -> 1 | AU44: 2
A45: 3 | AD45: =IF(E45="Exchanger",IF(AND(ISNUMBER(S45),ISNUMBER(U45),ISNUMBER(V45)),S45*PI()/4*(U45*INDEX(LenF,MATCH($U$7,LenU,0)))^2*V45*INDEX(LenF,MATCH($V$7,LenU,0)),0)+IF(ISNUMBER(Y45),PI()/4*(Y45*INDEX(LenF,MATCH($Y$7,LenU,0)))^2*N(Z45)*INDEX(LenF,MATCH($Z$7,LenU,0))+IF(AA45="",0,IF(AA45="Conical",PI()/12*(Y45*INDEX(LenF,MATCH($Y$7,LenU,0)))^2*(0),INDEX(HeadK,MATCH(AA45,HeadU,0))*(Y45*INDEX(LenF,MATCH($Y$7,LenU,0)))^3)),0)+IF(ISNUMBER(Y45),PI()/4*(Y45*INDEX(LenF,MATCH($Y$7,LenU,0)))^2*N(AB45)*INDEX(LenF,MATCH($AB$7,LenU,0))+IF(AC45="",0,IF(AC45="Conical",PI()/12*(Y45*INDEX(LenF,MATCH($Y$7,LenU,0)))^2*(0),INDEX(HeadK,MATCH(AC45,HeadU,0))*(Y45*INDEX(LenF,MATCH($Y$7,LenU,0)))^3)),0),"") | AE45: =IF(OR(E45="",E45="Piping"),"",IF(E45="Exchanger",AQ45*AR45+IF(P45="",0,IF(P45="Conical",PI()/12*(SQRT(4*AQ45/PI()))^2*(0),INDEX(HeadK,MATCH(P45,HeadU,0))*(SQRT(4*AQ45/PI()))^3))-IF(AND(ISNUMBER(S45),ISNUMBER(V45)),S45*PI()/4*AP45^2*V45*INDEX(LenF,MATCH($V$7,LenU,0)),0),IF(ISNUMBER(N45),PI()/4*(N45*INDEX(LenF,MATCH($N$7,LenU,0)))^2*N(O45)*INDEX(LenF,MATCH($O$7,LenU,0))+IF(P45="",0,IF(P45="Conical",PI()/12*(N45*INDEX(LenF,MATCH($N$7,LenU,0)))^2*(N(R45)*INDEX(LenF,MATCH($R$7,LenU,0))),INDEX(HeadK,MATCH(P45,HeadU,0))*(N45*INDEX(LenF,MATCH($N$7,LenU,0)))^3))+IF(Q45="",0,IF(Q45="Conical",PI()/12*(N45*INDEX(LenF,MATCH($N$7,LenU,0)))^2*(N(R45)*INDEX(LenF,MATCH($R$7,LenU,0))),INDEX(HeadK,MATCH(Q45,HeadU,0))*(N45*INDEX(LenF,MATCH($N$7,LenU,0)))^3)),0))) | AF45: =IF(E45<>"Piping","",IF(AND(ISNUMBER(AS45),ISNUMBER(M45)),PI()/4*(AS45/1000)^2*M45*INDEX(LenF,MATCH($M$7,LenU,0)),0)) | AG45: =IF(E45="","",N(AD45)+N(AE45)+N(AF45)) | AH45: =IF(ISNUMBER(I45),I45*INDEX(WtF,MATCH($I$7,WtU,0))/CC_WaterRho,"") | AM45: =IF(AO45="","",AO45*IF(ISNUMBER(AK45),AK45,CC_DefFills)*(1+IF(ISNUMBER(AL45),AL45,CC_DefAllow))) | AN45: =IF(G45="Given volume",IF(ISNUMBER(H45),H45*INDEX(VolF,MATCH($H$7,VolU,0)),""),IF(G45="Water weight",AH45,IF(N(AG45)=0,"",AG45))) | AO45: =IF(N(AN45)=0,"",AN45*AT45*IF(ISNUMBER(AJ45),AJ45,CC_DefCirc)) | AP45: =IF(ISNUMBER(T45),T45*INDEX(LenF,MATCH($T$7,LenU,0)),IF(ISNUMBER(W45),W45*INDEX(LenF,MATCH($W$7,LenU,0))/CC_PitchRatio,0)) -> 0 | AQ45: =IF(ISNUMBER(N45),PI()/4*(N45*INDEX(LenF,MATCH($N$7,LenU,0)))^2,IF(AND(ISNUMBER(S45),ISNUMBER(W45),X45<>""),S45*(W45*INDEX(LenF,MATCH($W$7,LenU,0)))^2*INDEX(LayoutF,MATCH(X45,LayoutU,0)),0)) -> 0 | AR45: =IF(ISNUMBER(O45),O45*INDEX(LenF,MATCH($O$7,LenU,0)),IF(ISNUMBER(V45),V45*INDEX(LenF,MATCH($V$7,LenU,0)),0)) -> 0 | AS45: =IF(ISNUMBER(L45),L45*INDEX(LenF,MATCH($L$7,LenU,0))*1000,IF(OR(J45="",K45=""),"",IFERROR(IF(INDEX(PipeWT,MATCH(J45,NPSU,0),MATCH(K45,SchU,0))="","Sch n/a",INDEX(PipeOD,MATCH(J45,NPSU,0))-2*INDEX(PipeWT,MATCH(J45,NPSU,0),MATCH(K45,SchU,0))),""))) | AT45: =IF(ISNUMBER(AI45),AI45,IFERROR(INDEX(IF(CC_JobType="Decontamination",CC_TypeFillDC,CC_TypeFillCC),MATCH(E45,CC_TypeL,0)),1)) -> 1 | AU45: 2
A46: 4 | AD46: =IF(E46="Exchanger",IF(AND(ISNUMBER(S46),ISNUMBER(U46),ISNUMBER(V46)),S46*PI()/4*(U46*INDEX(LenF,MATCH($U$7,LenU,0)))^2*V46*INDEX(LenF,MATCH($V$7,LenU,0)),0)+IF(ISNUMBER(Y46),PI()/4*(Y46*INDEX(LenF,MATCH($Y$7,LenU,0)))^2*N(Z46)*INDEX(LenF,MATCH($Z$7,LenU,0))+IF(AA46="",0,IF(AA46="Conical",PI()/12*(Y46*INDEX(LenF,MATCH($Y$7,LenU,0)))^2*(0),INDEX(HeadK,MATCH(AA46,HeadU,0))*(Y46*INDEX(LenF,MATCH($Y$7,LenU,0)))^3)),0)+IF(ISNUMBER(Y46),PI()/4*(Y46*INDEX(LenF,MATCH($Y$7,LenU,0)))^2*N(AB46)*INDEX(LenF,MATCH($AB$7,LenU,0))+IF(AC46="",0,IF(AC46="Conical",PI()/12*(Y46*INDEX(LenF,MATCH($Y$7,LenU,0)))^2*(0),INDEX(HeadK,MATCH(AC46,HeadU,0))*(Y46*INDEX(LenF,MATCH($Y$7,LenU,0)))^3)),0),"") | AE46: =IF(OR(E46="",E46="Piping"),"",IF(E46="Exchanger",AQ46*AR46+IF(P46="",0,IF(P46="Conical",PI()/12*(SQRT(4*AQ46/PI()))^2*(0),INDEX(HeadK,MATCH(P46,HeadU,0))*(SQRT(4*AQ46/PI()))^3))-IF(AND(ISNUMBER(S46),ISNUMBER(V46)),S46*PI()/4*AP46^2*V46*INDEX(LenF,MATCH($V$7,LenU,0)),0),IF(ISNUMBER(N46),PI()/4*(N46*INDEX(LenF,MATCH($N$7,LenU,0)))^2*N(O46)*INDEX(LenF,MATCH($O$7,LenU,0))+IF(P46="",0,IF(P46="Conical",PI()/12*(N46*INDEX(LenF,MATCH($N$7,LenU,0)))^2*(N(R46)*INDEX(LenF,MATCH($R$7,LenU,0))),INDEX(HeadK,MATCH(P46,HeadU,0))*(N46*INDEX(LenF,MATCH($N$7,LenU,0)))^3))+IF(Q46="",0,IF(Q46="Conical",PI()/12*(N46*INDEX(LenF,MATCH($N$7,LenU,0)))^2*(N(R46)*INDEX(LenF,MATCH($R$7,LenU,0))),INDEX(HeadK,MATCH(Q46,HeadU,0))*(N46*INDEX(LenF,MATCH($N$7,LenU,0)))^3)),0))) | AF46: =IF(E46<>"Piping","",IF(AND(ISNUMBER(AS46),ISNUMBER(M46)),PI()/4*(AS46/1000)^2*M46*INDEX(LenF,MATCH($M$7,LenU,0)),0)) | AG46: =IF(E46="","",N(AD46)+N(AE46)+N(AF46)) | AH46: =IF(ISNUMBER(I46),I46*INDEX(WtF,MATCH($I$7,WtU,0))/CC_WaterRho,"") | AM46: =IF(AO46="","",AO46*IF(ISNUMBER(AK46),AK46,CC_DefFills)*(1+IF(ISNUMBER(AL46),AL46,CC_DefAllow))) | AN46: =IF(G46="Given volume",IF(ISNUMBER(H46),H46*INDEX(VolF,MATCH($H$7,VolU,0)),""),IF(G46="Water weight",AH46,IF(N(AG46)=0,"",AG46))) | AO46: =IF(N(AN46)=0,"",AN46*AT46*IF(ISNUMBER(AJ46),AJ46,CC_DefCirc)) | AP46: =IF(ISNUMBER(T46),T46*INDEX(LenF,MATCH($T$7,LenU,0)),IF(ISNUMBER(W46),W46*INDEX(LenF,MATCH($W$7,LenU,0))/CC_PitchRatio,0)) -> 0 | AQ46: =IF(ISNUMBER(N46),PI()/4*(N46*INDEX(LenF,MATCH($N$7,LenU,0)))^2,IF(AND(ISNUMBER(S46),ISNUMBER(W46),X46<>""),S46*(W46*INDEX(LenF,MATCH($W$7,LenU,0)))^2*INDEX(LayoutF,MATCH(X46,LayoutU,0)),0)) -> 0 | AR46: =IF(ISNUMBER(O46),O46*INDEX(LenF,MATCH($O$7,LenU,0)),IF(ISNUMBER(V46),V46*INDEX(LenF,MATCH($V$7,LenU,0)),0)) -> 0 | AS46: =IF(ISNUMBER(L46),L46*INDEX(LenF,MATCH($L$7,LenU,0))*1000,IF(OR(J46="",K46=""),"",IFERROR(IF(INDEX(PipeWT,MATCH(J46,NPSU,0),MATCH(K46,SchU,0))="","Sch n/a",INDEX(PipeOD,MATCH(J46,NPSU,0))-2*INDEX(PipeWT,MATCH(J46,NPSU,0),MATCH(K46,SchU,0))),""))) | AT46: =IF(ISNUMBER(AI46),AI46,IFERROR(INDEX(IF(CC_JobType="Decontamination",CC_TypeFillDC,CC_TypeFillCC),MATCH(E46,CC_TypeL,0)),1)) -> 1 | AU46: 2
A47: 5 | AD47: =IF(E47="Exchanger",IF(AND(ISNUMBER(S47),ISNUMBER(U47),ISNUMBER(V47)),S47*PI()/4*(U47*INDEX(LenF,MATCH($U$7,LenU,0)))^2*V47*INDEX(LenF,MATCH($V$7,LenU,0)),0)+IF(ISNUMBER(Y47),PI()/4*(Y47*INDEX(LenF,MATCH($Y$7,LenU,0)))^2*N(Z47)*INDEX(LenF,MATCH($Z$7,LenU,0))+IF(AA47="",0,IF(AA47="Conical",PI()/12*(Y47*INDEX(LenF,MATCH($Y$7,LenU,0)))^2*(0),INDEX(HeadK,MATCH(AA47,HeadU,0))*(Y47*INDEX(LenF,MATCH($Y$7,LenU,0)))^3)),0)+IF(ISNUMBER(Y47),PI()/4*(Y47*INDEX(LenF,MATCH($Y$7,LenU,0)))^2*N(AB47)*INDEX(LenF,MATCH($AB$7,LenU,0))+IF(AC47="",0,IF(AC47="Conical",PI()/12*(Y47*INDEX(LenF,MATCH($Y$7,LenU,0)))^2*(0),INDEX(HeadK,MATCH(AC47,HeadU,0))*(Y47*INDEX(LenF,MATCH($Y$7,LenU,0)))^3)),0),"") | AE47: =IF(OR(E47="",E47="Piping"),"",IF(E47="Exchanger",AQ47*AR47+IF(P47="",0,IF(P47="Conical",PI()/12*(SQRT(4*AQ47/PI()))^2*(0),INDEX(HeadK,MATCH(P47,HeadU,0))*(SQRT(4*AQ47/PI()))^3))-IF(AND(ISNUMBER(S47),ISNUMBER(V47)),S47*PI()/4*AP47^2*V47*INDEX(LenF,MATCH($V$7,LenU,0)),0),IF(ISNUMBER(N47),PI()/4*(N47*INDEX(LenF,MATCH($N$7,LenU,0)))^2*N(O47)*INDEX(LenF,MATCH($O$7,LenU,0))+IF(P47="",0,IF(P47="Conical",PI()/12*(N47*INDEX(LenF,MATCH($N$7,LenU,0)))^2*(N(R47)*INDEX(LenF,MATCH($R$7,LenU,0))),INDEX(HeadK,MATCH(P47,HeadU,0))*(N47*INDEX(LenF,MATCH($N$7,LenU,0)))^3))+IF(Q47="",0,IF(Q47="Conical",PI()/12*(N47*INDEX(LenF,MATCH($N$7,LenU,0)))^2*(N(R47)*INDEX(LenF,MATCH($R$7,LenU,0))),INDEX(HeadK,MATCH(Q47,HeadU,0))*(N47*INDEX(LenF,MATCH($N$7,LenU,0)))^3)),0))) | AF47: =IF(E47<>"Piping","",IF(AND(ISNUMBER(AS47),ISNUMBER(M47)),PI()/4*(AS47/1000)^2*M47*INDEX(LenF,MATCH($M$7,LenU,0)),0)) | AG47: =IF(E47="","",N(AD47)+N(AE47)+N(AF47)) | AH47: =IF(ISNUMBER(I47),I47*INDEX(WtF,MATCH($I$7,WtU,0))/CC_WaterRho,"") | AM47: =IF(AO47="","",AO47*IF(ISNUMBER(AK47),AK47,CC_DefFills)*(1+IF(ISNUMBER(AL47),AL47,CC_DefAllow))) | AN47: =IF(G47="Given volume",IF(ISNUMBER(H47),H47*INDEX(VolF,MATCH($H$7,VolU,0)),""),IF(G47="Water weight",AH47,IF(N(AG47)=0,"",AG47))) | AO47: =IF(N(AN47)=0,"",AN47*AT47*IF(ISNUMBER(AJ47),AJ47,CC_DefCirc)) | AP47: =IF(ISNUMBER(T47),T47*INDEX(LenF,MATCH($T$7,LenU,0)),IF(ISNUMBER(W47),W47*INDEX(LenF,MATCH($W$7,LenU,0))/CC_PitchRatio,0)) -> 0 | AQ47: =IF(ISNUMBER(N47),PI()/4*(N47*INDEX(LenF,MATCH($N$7,LenU,0)))^2,IF(AND(ISNUMBER(S47),ISNUMBER(W47),X47<>""),S47*(W47*INDEX(LenF,MATCH($W$7,LenU,0)))^2*INDEX(LayoutF,MATCH(X47,LayoutU,0)),0)) -> 0 | AR47: =IF(ISNUMBER(O47),O47*INDEX(LenF,MATCH($O$7,LenU,0)),IF(ISNUMBER(V47),V47*INDEX(LenF,MATCH($V$7,LenU,0)),0)) -> 0 | AS47: =IF(ISNUMBER(L47),L47*INDEX(LenF,MATCH($L$7,LenU,0))*1000,IF(OR(J47="",K47=""),"",IFERROR(IF(INDEX(PipeWT,MATCH(J47,NPSU,0),MATCH(K47,SchU,0))="","Sch n/a",INDEX(PipeOD,MATCH(J47,NPSU,0))-2*INDEX(PipeWT,MATCH(J47,NPSU,0),MATCH(K47,SchU,0))),""))) | AT47: =IF(ISNUMBER(AI47),AI47,IFERROR(INDEX(IF(CC_JobType="Decontamination",CC_TypeFillDC,CC_TypeFillCC),MATCH(E47,CC_TypeL,0)),1)) -> 1 | AU47: 2
A48: 6 | AD48: =IF(E48="Exchanger",IF(AND(ISNUMBER(S48),ISNUMBER(U48),ISNUMBER(V48)),S48*PI()/4*(U48*INDEX(LenF,MATCH($U$7,LenU,0)))^2*V48*INDEX(LenF,MATCH($V$7,LenU,0)),0)+IF(ISNUMBER(Y48),PI()/4*(Y48*INDEX(LenF,MATCH($Y$7,LenU,0)))^2*N(Z48)*INDEX(LenF,MATCH($Z$7,LenU,0))+IF(AA48="",0,IF(AA48="Conical",PI()/12*(Y48*INDEX(LenF,MATCH($Y$7,LenU,0)))^2*(0),INDEX(HeadK,MATCH(AA48,HeadU,0))*(Y48*INDEX(LenF,MATCH($Y$7,LenU,0)))^3)),0)+IF(ISNUMBER(Y48),PI()/4*(Y48*INDEX(LenF,MATCH($Y$7,LenU,0)))^2*N(AB48)*INDEX(LenF,MATCH($AB$7,LenU,0))+IF(AC48="",0,IF(AC48="Conical",PI()/12*(Y48*INDEX(LenF,MATCH($Y$7,LenU,0)))^2*(0),INDEX(HeadK,MATCH(AC48,HeadU,0))*(Y48*INDEX(LenF,MATCH($Y$7,LenU,0)))^3)),0),"") | AE48: =IF(OR(E48="",E48="Piping"),"",IF(E48="Exchanger",AQ48*AR48+IF(P48="",0,IF(P48="Conical",PI()/12*(SQRT(4*AQ48/PI()))^2*(0),INDEX(HeadK,MATCH(P48,HeadU,0))*(SQRT(4*AQ48/PI()))^3))-IF(AND(ISNUMBER(S48),ISNUMBER(V48)),S48*PI()/4*AP48^2*V48*INDEX(LenF,MATCH($V$7,LenU,0)),0),IF(ISNUMBER(N48),PI()/4*(N48*INDEX(LenF,MATCH($N$7,LenU,0)))^2*N(O48)*INDEX(LenF,MATCH($O$7,LenU,0))+IF(P48="",0,IF(P48="Conical",PI()/12*(N48*INDEX(LenF,MATCH($N$7,LenU,0)))^2*(N(R48)*INDEX(LenF,MATCH($R$7,LenU,0))),INDEX(HeadK,MATCH(P48,HeadU,0))*(N48*INDEX(LenF,MATCH($N$7,LenU,0)))^3))+IF(Q48="",0,IF(Q48="Conical",PI()/12*(N48*INDEX(LenF,MATCH($N$7,LenU,0)))^2*(N(R48)*INDEX(LenF,MATCH($R$7,LenU,0))),INDEX(HeadK,MATCH(Q48,HeadU,0))*(N48*INDEX(LenF,MATCH($N$7,LenU,0)))^3)),0))) | AF48: =IF(E48<>"Piping","",IF(AND(ISNUMBER(AS48),ISNUMBER(M48)),PI()/4*(AS48/1000)^2*M48*INDEX(LenF,MATCH($M$7,LenU,0)),0)) | AG48: =IF(E48="","",N(AD48)+N(AE48)+N(AF48)) | AH48: =IF(ISNUMBER(I48),I48*INDEX(WtF,MATCH($I$7,WtU,0))/CC_WaterRho,"") | AM48: =IF(AO48="","",AO48*IF(ISNUMBER(AK48),AK48,CC_DefFills)*(1+IF(ISNUMBER(AL48),AL48,CC_DefAllow))) | AN48: =IF(G48="Given volume",IF(ISNUMBER(H48),H48*INDEX(VolF,MATCH($H$7,VolU,0)),""),IF(G48="Water weight",AH48,IF(N(AG48)=0,"",AG48))) | AO48: =IF(N(AN48)=0,"",AN48*AT48*IF(ISNUMBER(AJ48),AJ48,CC_DefCirc)) | AP48: =IF(ISNUMBER(T48),T48*INDEX(LenF,MATCH($T$7,LenU,0)),IF(ISNUMBER(W48),W48*INDEX(LenF,MATCH($W$7,LenU,0))/CC_PitchRatio,0)) -> 0 | AQ48: =IF(ISNUMBER(N48),PI()/4*(N48*INDEX(LenF,MATCH($N$7,LenU,0)))^2,IF(AND(ISNUMBER(S48),ISNUMBER(W48),X48<>""),S48*(W48*INDEX(LenF,MATCH($W$7,LenU,0)))^2*INDEX(LayoutF,MATCH(X48,LayoutU,0)),0)) -> 0 | AR48: =IF(ISNUMBER(O48),O48*INDEX(LenF,MATCH($O$7,LenU,0)),IF(ISNUMBER(V48),V48*INDEX(LenF,MATCH($V$7,LenU,0)),0)) -> 0 | AS48: =IF(ISNUMBER(L48),L48*INDEX(LenF,MATCH($L$7,LenU,0))*1000,IF(OR(J48="",K48=""),"",IFERROR(IF(INDEX(PipeWT,MATCH(J48,NPSU,0),MATCH(K48,SchU,0))="","Sch n/a",INDEX(PipeOD,MATCH(J48,NPSU,0))-2*INDEX(PipeWT,MATCH(J48,NPSU,0),MATCH(K48,SchU,0))),""))) | AT48: =IF(ISNUMBER(AI48),AI48,IFERROR(INDEX(IF(CC_JobType="Decontamination",CC_TypeFillDC,CC_TypeFillCC),MATCH(E48,CC_TypeL,0)),1)) -> 1 | AU48: 2
A49: 7 | AD49: =IF(E49="Exchanger",IF(AND(ISNUMBER(S49),ISNUMBER(U49),ISNUMBER(V49)),S49*PI()/4*(U49*INDEX(LenF,MATCH($U$7,LenU,0)))^2*V49*INDEX(LenF,MATCH($V$7,LenU,0)),0)+IF(ISNUMBER(Y49),PI()/4*(Y49*INDEX(LenF,MATCH($Y$7,LenU,0)))^2*N(Z49)*INDEX(LenF,MATCH($Z$7,LenU,0))+IF(AA49="",0,IF(AA49="Conical",PI()/12*(Y49*INDEX(LenF,MATCH($Y$7,LenU,0)))^2*(0),INDEX(HeadK,MATCH(AA49,HeadU,0))*(Y49*INDEX(LenF,MATCH($Y$7,LenU,0)))^3)),0)+IF(ISNUMBER(Y49),PI()/4*(Y49*INDEX(LenF,MATCH($Y$7,LenU,0)))^2*N(AB49)*INDEX(LenF,MATCH($AB$7,LenU,0))+IF(AC49="",0,IF(AC49="Conical",PI()/12*(Y49*INDEX(LenF,MATCH($Y$7,LenU,0)))^2*(0),INDEX(HeadK,MATCH(AC49,HeadU,0))*(Y49*INDEX(LenF,MATCH($Y$7,LenU,0)))^3)),0),"") | AE49: =IF(OR(E49="",E49="Piping"),"",IF(E49="Exchanger",AQ49*AR49+IF(P49="",0,IF(P49="Conical",PI()/12*(SQRT(4*AQ49/PI()))^2*(0),INDEX(HeadK,MATCH(P49,HeadU,0))*(SQRT(4*AQ49/PI()))^3))-IF(AND(ISNUMBER(S49),ISNUMBER(V49)),S49*PI()/4*AP49^2*V49*INDEX(LenF,MATCH($V$7,LenU,0)),0),IF(ISNUMBER(N49),PI()/4*(N49*INDEX(LenF,MATCH($N$7,LenU,0)))^2*N(O49)*INDEX(LenF,MATCH($O$7,LenU,0))+IF(P49="",0,IF(P49="Conical",PI()/12*(N49*INDEX(LenF,MATCH($N$7,LenU,0)))^2*(N(R49)*INDEX(LenF,MATCH($R$7,LenU,0))),INDEX(HeadK,MATCH(P49,HeadU,0))*(N49*INDEX(LenF,MATCH($N$7,LenU,0)))^3))+IF(Q49="",0,IF(Q49="Conical",PI()/12*(N49*INDEX(LenF,MATCH($N$7,LenU,0)))^2*(N(R49)*INDEX(LenF,MATCH($R$7,LenU,0))),INDEX(HeadK,MATCH(Q49,HeadU,0))*(N49*INDEX(LenF,MATCH($N$7,LenU,0)))^3)),0))) | AF49: =IF(E49<>"Piping","",IF(AND(ISNUMBER(AS49),ISNUMBER(M49)),PI()/4*(AS49/1000)^2*M49*INDEX(LenF,MATCH($M$7,LenU,0)),0)) | AG49: =IF(E49="","",N(AD49)+N(AE49)+N(AF49)) | AH49: =IF(ISNUMBER(I49),I49*INDEX(WtF,MATCH($I$7,WtU,0))/CC_WaterRho,"") | AM49: =IF(AO49="","",AO49*IF(ISNUMBER(AK49),AK49,CC_DefFills)*(1+IF(ISNUMBER(AL49),AL49,CC_DefAllow))) | AN49: =IF(G49="Given volume",IF(ISNUMBER(H49),H49*INDEX(VolF,MATCH($H$7,VolU,0)),""),IF(G49="Water weight",AH49,IF(N(AG49)=0,"",AG49))) | AO49: =IF(N(AN49)=0,"",AN49*AT49*IF(ISNUMBER(AJ49),AJ49,CC_DefCirc)) | AP49: =IF(ISNUMBER(T49),T49*INDEX(LenF,MATCH($T$7,LenU,0)),IF(ISNUMBER(W49),W49*INDEX(LenF,MATCH($W$7,LenU,0))/CC_PitchRatio,0)) -> 0 | AQ49: =IF(ISNUMBER(N49),PI()/4*(N49*INDEX(LenF,MATCH($N$7,LenU,0)))^2,IF(AND(ISNUMBER(S49),ISNUMBER(W49),X49<>""),S49*(W49*INDEX(LenF,MATCH($W$7,LenU,0)))^2*INDEX(LayoutF,MATCH(X49,LayoutU,0)),0)) -> 0 | AR49: =IF(ISNUMBER(O49),O49*INDEX(LenF,MATCH($O$7,LenU,0)),IF(ISNUMBER(V49),V49*INDEX(LenF,MATCH($V$7,LenU,0)),0)) -> 0 | AS49: =IF(ISNUMBER(L49),L49*INDEX(LenF,MATCH($L$7,LenU,0))*1000,IF(OR(J49="",K49=""),"",IFERROR(IF(INDEX(PipeWT,MATCH(J49,NPSU,0),MATCH(K49,SchU,0))="","Sch n/a",INDEX(PipeOD,MATCH(J49,NPSU,0))-2*INDEX(PipeWT,MATCH(J49,NPSU,0),MATCH(K49,SchU,0))),""))) | AT49: =IF(ISNUMBER(AI49),AI49,IFERROR(INDEX(IF(CC_JobType="Decontamination",CC_TypeFillDC,CC_TypeFillCC),MATCH(E49,CC_TypeL,0)),1)) -> 1 | AU49: 2
A50: 8 | AD50: =IF(E50="Exchanger",IF(AND(ISNUMBER(S50),ISNUMBER(U50),ISNUMBER(V50)),S50*PI()/4*(U50*INDEX(LenF,MATCH($U$7,LenU,0)))^2*V50*INDEX(LenF,MATCH($V$7,LenU,0)),0)+IF(ISNUMBER(Y50),PI()/4*(Y50*INDEX(LenF,MATCH($Y$7,LenU,0)))^2*N(Z50)*INDEX(LenF,MATCH($Z$7,LenU,0))+IF(AA50="",0,IF(AA50="Conical",PI()/12*(Y50*INDEX(LenF,MATCH($Y$7,LenU,0)))^2*(0),INDEX(HeadK,MATCH(AA50,HeadU,0))*(Y50*INDEX(LenF,MATCH($Y$7,LenU,0)))^3)),0)+IF(ISNUMBER(Y50),PI()/4*(Y50*INDEX(LenF,MATCH($Y$7,LenU,0)))^2*N(AB50)*INDEX(LenF,MATCH($AB$7,LenU,0))+IF(AC50="",0,IF(AC50="Conical",PI()/12*(Y50*INDEX(LenF,MATCH($Y$7,LenU,0)))^2*(0),INDEX(HeadK,MATCH(AC50,HeadU,0))*(Y50*INDEX(LenF,MATCH($Y$7,LenU,0)))^3)),0),"") | AE50: =IF(OR(E50="",E50="Piping"),"",IF(E50="Exchanger",AQ50*AR50+IF(P50="",0,IF(P50="Conical",PI()/12*(SQRT(4*AQ50/PI()))^2*(0),INDEX(HeadK,MATCH(P50,HeadU,0))*(SQRT(4*AQ50/PI()))^3))-IF(AND(ISNUMBER(S50),ISNUMBER(V50)),S50*PI()/4*AP50^2*V50*INDEX(LenF,MATCH($V$7,LenU,0)),0),IF(ISNUMBER(N50),PI()/4*(N50*INDEX(LenF,MATCH($N$7,LenU,0)))^2*N(O50)*INDEX(LenF,MATCH($O$7,LenU,0))+IF(P50="",0,IF(P50="Conical",PI()/12*(N50*INDEX(LenF,MATCH($N$7,LenU,0)))^2*(N(R50)*INDEX(LenF,MATCH($R$7,LenU,0))),INDEX(HeadK,MATCH(P50,HeadU,0))*(N50*INDEX(LenF,MATCH($N$7,LenU,0)))^3))+IF(Q50="",0,IF(Q50="Conical",PI()/12*(N50*INDEX(LenF,MATCH($N$7,LenU,0)))^2*(N(R50)*INDEX(LenF,MATCH($R$7,LenU,0))),INDEX(HeadK,MATCH(Q50,HeadU,0))*(N50*INDEX(LenF,MATCH($N$7,LenU,0)))^3)),0))) | AF50: =IF(E50<>"Piping","",IF(AND(ISNUMBER(AS50),ISNUMBER(M50)),PI()/4*(AS50/1000)^2*M50*INDEX(LenF,MATCH($M$7,LenU,0)),0)) | AG50: =IF(E50="","",N(AD50)+N(AE50)+N(AF50)) | AH50: =IF(ISNUMBER(I50),I50*INDEX(WtF,MATCH($I$7,WtU,0))/CC_WaterRho,"") | AM50: =IF(AO50="","",AO50*IF(ISNUMBER(AK50),AK50,CC_DefFills)*(1+IF(ISNUMBER(AL50),AL50,CC_DefAllow))) | AN50: =IF(G50="Given volume",IF(ISNUMBER(H50),H50*INDEX(VolF,MATCH($H$7,VolU,0)),""),IF(G50="Water weight",AH50,IF(N(AG50)=0,"",AG50))) | AO50: =IF(N(AN50)=0,"",AN50*AT50*IF(ISNUMBER(AJ50),AJ50,CC_DefCirc)) | AP50: =IF(ISNUMBER(T50),T50*INDEX(LenF,MATCH($T$7,LenU,0)),IF(ISNUMBER(W50),W50*INDEX(LenF,MATCH($W$7,LenU,0))/CC_PitchRatio,0)) -> 0 | AQ50: =IF(ISNUMBER(N50),PI()/4*(N50*INDEX(LenF,MATCH($N$7,LenU,0)))^2,IF(AND(ISNUMBER(S50),ISNUMBER(W50),X50<>""),S50*(W50*INDEX(LenF,MATCH($W$7,LenU,0)))^2*INDEX(LayoutF,MATCH(X50,LayoutU,0)),0)) -> 0 | AR50: =IF(ISNUMBER(O50),O50*INDEX(LenF,MATCH($O$7,LenU,0)),IF(ISNUMBER(V50),V50*INDEX(LenF,MATCH($V$7,LenU,0)),0)) -> 0 | AS50: =IF(ISNUMBER(L50),L50*INDEX(LenF,MATCH($L$7,LenU,0))*1000,IF(OR(J50="",K50=""),"",IFERROR(IF(INDEX(PipeWT,MATCH(J50,NPSU,0),MATCH(K50,SchU,0))="","Sch n/a",INDEX(PipeOD,MATCH(J50,NPSU,0))-2*INDEX(PipeWT,MATCH(J50,NPSU,0),MATCH(K50,SchU,0))),""))) | AT50: =IF(ISNUMBER(AI50),AI50,IFERROR(INDEX(IF(CC_JobType="Decontamination",CC_TypeFillDC,CC_TypeFillCC),MATCH(E50,CC_TypeL,0)),1)) -> 1 | AU50: 2
A51: 9 | AD51: =IF(E51="Exchanger",IF(AND(ISNUMBER(S51),ISNUMBER(U51),ISNUMBER(V51)),S51*PI()/4*(U51*INDEX(LenF,MATCH($U$7,LenU,0)))^2*V51*INDEX(LenF,MATCH($V$7,LenU,0)),0)+IF(ISNUMBER(Y51),PI()/4*(Y51*INDEX(LenF,MATCH($Y$7,LenU,0)))^2*N(Z51)*INDEX(LenF,MATCH($Z$7,LenU,0))+IF(AA51="",0,IF(AA51="Conical",PI()/12*(Y51*INDEX(LenF,MATCH($Y$7,LenU,0)))^2*(0),INDEX(HeadK,MATCH(AA51,HeadU,0))*(Y51*INDEX(LenF,MATCH($Y$7,LenU,0)))^3)),0)+IF(ISNUMBER(Y51),PI()/4*(Y51*INDEX(LenF,MATCH($Y$7,LenU,0)))^2*N(AB51)*INDEX(LenF,MATCH($AB$7,LenU,0))+IF(AC51="",0,IF(AC51="Conical",PI()/12*(Y51*INDEX(LenF,MATCH($Y$7,LenU,0)))^2*(0),INDEX(HeadK,MATCH(AC51,HeadU,0))*(Y51*INDEX(LenF,MATCH($Y$7,LenU,0)))^3)),0),"") | AE51: =IF(OR(E51="",E51="Piping"),"",IF(E51="Exchanger",AQ51*AR51+IF(P51="",0,IF(P51="Conical",PI()/12*(SQRT(4*AQ51/PI()))^2*(0),INDEX(HeadK,MATCH(P51,HeadU,0))*(SQRT(4*AQ51/PI()))^3))-IF(AND(ISNUMBER(S51),ISNUMBER(V51)),S51*PI()/4*AP51^2*V51*INDEX(LenF,MATCH($V$7,LenU,0)),0),IF(ISNUMBER(N51),PI()/4*(N51*INDEX(LenF,MATCH($N$7,LenU,0)))^2*N(O51)*INDEX(LenF,MATCH($O$7,LenU,0))+IF(P51="",0,IF(P51="Conical",PI()/12*(N51*INDEX(LenF,MATCH($N$7,LenU,0)))^2*(N(R51)*INDEX(LenF,MATCH($R$7,LenU,0))),INDEX(HeadK,MATCH(P51,HeadU,0))*(N51*INDEX(LenF,MATCH($N$7,LenU,0)))^3))+IF(Q51="",0,IF(Q51="Conical",PI()/12*(N51*INDEX(LenF,MATCH($N$7,LenU,0)))^2*(N(R51)*INDEX(LenF,MATCH($R$7,LenU,0))),INDEX(HeadK,MATCH(Q51,HeadU,0))*(N51*INDEX(LenF,MATCH($N$7,LenU,0)))^3)),0))) | AF51: =IF(E51<>"Piping","",IF(AND(ISNUMBER(AS51),ISNUMBER(M51)),PI()/4*(AS51/1000)^2*M51*INDEX(LenF,MATCH($M$7,LenU,0)),0)) | AG51: =IF(E51="","",N(AD51)+N(AE51)+N(AF51)) | AH51: =IF(ISNUMBER(I51),I51*INDEX(WtF,MATCH($I$7,WtU,0))/CC_WaterRho,"") | AM51: =IF(AO51="","",AO51*IF(ISNUMBER(AK51),AK51,CC_DefFills)*(1+IF(ISNUMBER(AL51),AL51,CC_DefAllow))) | AN51: =IF(G51="Given volume",IF(ISNUMBER(H51),H51*INDEX(VolF,MATCH($H$7,VolU,0)),""),IF(G51="Water weight",AH51,IF(N(AG51)=0,"",AG51))) | AO51: =IF(N(AN51)=0,"",AN51*AT51*IF(ISNUMBER(AJ51),AJ51,CC_DefCirc)) | AP51: =IF(ISNUMBER(T51),T51*INDEX(LenF,MATCH($T$7,LenU,0)),IF(ISNUMBER(W51),W51*INDEX(LenF,MATCH($W$7,LenU,0))/CC_PitchRatio,0)) -> 0 | AQ51: =IF(ISNUMBER(N51),PI()/4*(N51*INDEX(LenF,MATCH($N$7,LenU,0)))^2,IF(AND(ISNUMBER(S51),ISNUMBER(W51),X51<>""),S51*(W51*INDEX(LenF,MATCH($W$7,LenU,0)))^2*INDEX(LayoutF,MATCH(X51,LayoutU,0)),0)) -> 0 | AR51: =IF(ISNUMBER(O51),O51*INDEX(LenF,MATCH($O$7,LenU,0)),IF(ISNUMBER(V51),V51*INDEX(LenF,MATCH($V$7,LenU,0)),0)) -> 0 | AS51: =IF(ISNUMBER(L51),L51*INDEX(LenF,MATCH($L$7,LenU,0))*1000,IF(OR(J51="",K51=""),"",IFERROR(IF(INDEX(PipeWT,MATCH(J51,NPSU,0),MATCH(K51,SchU,0))="","Sch n/a",INDEX(PipeOD,MATCH(J51,NPSU,0))-2*INDEX(PipeWT,MATCH(J51,NPSU,0),MATCH(K51,SchU,0))),""))) | AT51: =IF(ISNUMBER(AI51),AI51,IFERROR(INDEX(IF(CC_JobType="Decontamination",CC_TypeFillDC,CC_TypeFillCC),MATCH(E51,CC_TypeL,0)),1)) -> 1 | AU51: 2
A52: 10 | AD52: =IF(E52="Exchanger",IF(AND(ISNUMBER(S52),ISNUMBER(U52),ISNUMBER(V52)),S52*PI()/4*(U52*INDEX(LenF,MATCH($U$7,LenU,0)))^2*V52*INDEX(LenF,MATCH($V$7,LenU,0)),0)+IF(ISNUMBER(Y52),PI()/4*(Y52*INDEX(LenF,MATCH($Y$7,LenU,0)))^2*N(Z52)*INDEX(LenF,MATCH($Z$7,LenU,0))+IF(AA52="",0,IF(AA52="Conical",PI()/12*(Y52*INDEX(LenF,MATCH($Y$7,LenU,0)))^2*(0),INDEX(HeadK,MATCH(AA52,HeadU,0))*(Y52*INDEX(LenF,MATCH($Y$7,LenU,0)))^3)),0)+IF(ISNUMBER(Y52),PI()/4*(Y52*INDEX(LenF,MATCH($Y$7,LenU,0)))^2*N(AB52)*INDEX(LenF,MATCH($AB$7,LenU,0))+IF(AC52="",0,IF(AC52="Conical",PI()/12*(Y52*INDEX(LenF,MATCH($Y$7,LenU,0)))^2*(0),INDEX(HeadK,MATCH(AC52,HeadU,0))*(Y52*INDEX(LenF,MATCH($Y$7,LenU,0)))^3)),0),"") | AE52: =IF(OR(E52="",E52="Piping"),"",IF(E52="Exchanger",AQ52*AR52+IF(P52="",0,IF(P52="Conical",PI()/12*(SQRT(4*AQ52/PI()))^2*(0),INDEX(HeadK,MATCH(P52,HeadU,0))*(SQRT(4*AQ52/PI()))^3))-IF(AND(ISNUMBER(S52),ISNUMBER(V52)),S52*PI()/4*AP52^2*V52*INDEX(LenF,MATCH($V$7,LenU,0)),0),IF(ISNUMBER(N52),PI()/4*(N52*INDEX(LenF,MATCH($N$7,LenU,0)))^2*N(O52)*INDEX(LenF,MATCH($O$7,LenU,0))+IF(P52="",0,IF(P52="Conical",PI()/12*(N52*INDEX(LenF,MATCH($N$7,LenU,0)))^2*(N(R52)*INDEX(LenF,MATCH($R$7,LenU,0))),INDEX(HeadK,MATCH(P52,HeadU,0))*(N52*INDEX(LenF,MATCH($N$7,LenU,0)))^3))+IF(Q52="",0,IF(Q52="Conical",PI()/12*(N52*INDEX(LenF,MATCH($N$7,LenU,0)))^2*(N(R52)*INDEX(LenF,MATCH($R$7,LenU,0))),INDEX(HeadK,MATCH(Q52,HeadU,0))*(N52*INDEX(LenF,MATCH($N$7,LenU,0)))^3)),0))) | AF52: =IF(E52<>"Piping","",IF(AND(ISNUMBER(AS52),ISNUMBER(M52)),PI()/4*(AS52/1000)^2*M52*INDEX(LenF,MATCH($M$7,LenU,0)),0)) | AG52: =IF(E52="","",N(AD52)+N(AE52)+N(AF52)) | AH52: =IF(ISNUMBER(I52),I52*INDEX(WtF,MATCH($I$7,WtU,0))/CC_WaterRho,"") | AM52: =IF(AO52="","",AO52*IF(ISNUMBER(AK52),AK52,CC_DefFills)*(1+IF(ISNUMBER(AL52),AL52,CC_DefAllow))) | AN52: =IF(G52="Given volume",IF(ISNUMBER(H52),H52*INDEX(VolF,MATCH($H$7,VolU,0)),""),IF(G52="Water weight",AH52,IF(N(AG52)=0,"",AG52))) | AO52: =IF(N(AN52)=0,"",AN52*AT52*IF(ISNUMBER(AJ52),AJ52,CC_DefCirc)) | AP52: =IF(ISNUMBER(T52),T52*INDEX(LenF,MATCH($T$7,LenU,0)),IF(ISNUMBER(W52),W52*INDEX(LenF,MATCH($W$7,LenU,0))/CC_PitchRatio,0)) -> 0 | AQ52: =IF(ISNUMBER(N52),PI()/4*(N52*INDEX(LenF,MATCH($N$7,LenU,0)))^2,IF(AND(ISNUMBER(S52),ISNUMBER(W52),X52<>""),S52*(W52*INDEX(LenF,MATCH($W$7,LenU,0)))^2*INDEX(LayoutF,MATCH(X52,LayoutU,0)),0)) -> 0 | AR52: =IF(ISNUMBER(O52),O52*INDEX(LenF,MATCH($O$7,LenU,0)),IF(ISNUMBER(V52),V52*INDEX(LenF,MATCH($V$7,LenU,0)),0)) -> 0 | AS52: =IF(ISNUMBER(L52),L52*INDEX(LenF,MATCH($L$7,LenU,0))*1000,IF(OR(J52="",K52=""),"",IFERROR(IF(INDEX(PipeWT,MATCH(J52,NPSU,0),MATCH(K52,SchU,0))="","Sch n/a",INDEX(PipeOD,MATCH(J52,NPSU,0))-2*INDEX(PipeWT,MATCH(J52,NPSU,0),MATCH(K52,SchU,0))),""))) | AT52: =IF(ISNUMBER(AI52),AI52,IFERROR(INDEX(IF(CC_JobType="Decontamination",CC_TypeFillDC,CC_TypeFillCC),MATCH(E52,CC_TypeL,0)),1)) -> 1 | AU52: 2
A53: 11 | AD53: =IF(E53="Exchanger",IF(AND(ISNUMBER(S53),ISNUMBER(U53),ISNUMBER(V53)),S53*PI()/4*(U53*INDEX(LenF,MATCH($U$7,LenU,0)))^2*V53*INDEX(LenF,MATCH($V$7,LenU,0)),0)+IF(ISNUMBER(Y53),PI()/4*(Y53*INDEX(LenF,MATCH($Y$7,LenU,0)))^2*N(Z53)*INDEX(LenF,MATCH($Z$7,LenU,0))+IF(AA53="",0,IF(AA53="Conical",PI()/12*(Y53*INDEX(LenF,MATCH($Y$7,LenU,0)))^2*(0),INDEX(HeadK,MATCH(AA53,HeadU,0))*(Y53*INDEX(LenF,MATCH($Y$7,LenU,0)))^3)),0)+IF(ISNUMBER(Y53),PI()/4*(Y53*INDEX(LenF,MATCH($Y$7,LenU,0)))^2*N(AB53)*INDEX(LenF,MATCH($AB$7,LenU,0))+IF(AC53="",0,IF(AC53="Conical",PI()/12*(Y53*INDEX(LenF,MATCH($Y$7,LenU,0)))^2*(0),INDEX(HeadK,MATCH(AC53,HeadU,0))*(Y53*INDEX(LenF,MATCH($Y$7,LenU,0)))^3)),0),"") | AE53: =IF(OR(E53="",E53="Piping"),"",IF(E53="Exchanger",AQ53*AR53+IF(P53="",0,IF(P53="Conical",PI()/12*(SQRT(4*AQ53/PI()))^2*(0),INDEX(HeadK,MATCH(P53,HeadU,0))*(SQRT(4*AQ53/PI()))^3))-IF(AND(ISNUMBER(S53),ISNUMBER(V53)),S53*PI()/4*AP53^2*V53*INDEX(LenF,MATCH($V$7,LenU,0)),0),IF(ISNUMBER(N53),PI()/4*(N53*INDEX(LenF,MATCH($N$7,LenU,0)))^2*N(O53)*INDEX(LenF,MATCH($O$7,LenU,0))+IF(P53="",0,IF(P53="Conical",PI()/12*(N53*INDEX(LenF,MATCH($N$7,LenU,0)))^2*(N(R53)*INDEX(LenF,MATCH($R$7,LenU,0))),INDEX(HeadK,MATCH(P53,HeadU,0))*(N53*INDEX(LenF,MATCH($N$7,LenU,0)))^3))+IF(Q53="",0,IF(Q53="Conical",PI()/12*(N53*INDEX(LenF,MATCH($N$7,LenU,0)))^2*(N(R53)*INDEX(LenF,MATCH($R$7,LenU,0))),INDEX(HeadK,MATCH(Q53,HeadU,0))*(N53*INDEX(LenF,MATCH($N$7,LenU,0)))^3)),0))) | AF53: =IF(E53<>"Piping","",IF(AND(ISNUMBER(AS53),ISNUMBER(M53)),PI()/4*(AS53/1000)^2*M53*INDEX(LenF,MATCH($M$7,LenU,0)),0)) | AG53: =IF(E53="","",N(AD53)+N(AE53)+N(AF53)) | AH53: =IF(ISNUMBER(I53),I53*INDEX(WtF,MATCH($I$7,WtU,0))/CC_WaterRho,"") | AM53: =IF(AO53="","",AO53*IF(ISNUMBER(AK53),AK53,CC_DefFills)*(1+IF(ISNUMBER(AL53),AL53,CC_DefAllow))) | AN53: =IF(G53="Given volume",IF(ISNUMBER(H53),H53*INDEX(VolF,MATCH($H$7,VolU,0)),""),IF(G53="Water weight",AH53,IF(N(AG53)=0,"",AG53))) | AO53: =IF(N(AN53)=0,"",AN53*AT53*IF(ISNUMBER(AJ53),AJ53,CC_DefCirc)) | AP53: =IF(ISNUMBER(T53),T53*INDEX(LenF,MATCH($T$7,LenU,0)),IF(ISNUMBER(W53),W53*INDEX(LenF,MATCH($W$7,LenU,0))/CC_PitchRatio,0)) -> 0 | AQ53: =IF(ISNUMBER(N53),PI()/4*(N53*INDEX(LenF,MATCH($N$7,LenU,0)))^2,IF(AND(ISNUMBER(S53),ISNUMBER(W53),X53<>""),S53*(W53*INDEX(LenF,MATCH($W$7,LenU,0)))^2*INDEX(LayoutF,MATCH(X53,LayoutU,0)),0)) -> 0 | AR53: =IF(ISNUMBER(O53),O53*INDEX(LenF,MATCH($O$7,LenU,0)),IF(ISNUMBER(V53),V53*INDEX(LenF,MATCH($V$7,LenU,0)),0)) -> 0 | AS53: =IF(ISNUMBER(L53),L53*INDEX(LenF,MATCH($L$7,LenU,0))*1000,IF(OR(J53="",K53=""),"",IFERROR(IF(INDEX(PipeWT,MATCH(J53,NPSU,0),MATCH(K53,SchU,0))="","Sch n/a",INDEX(PipeOD,MATCH(J53,NPSU,0))-2*INDEX(PipeWT,MATCH(J53,NPSU,0),MATCH(K53,SchU,0))),""))) | AT53: =IF(ISNUMBER(AI53),AI53,IFERROR(INDEX(IF(CC_JobType="Decontamination",CC_TypeFillDC,CC_TypeFillCC),MATCH(E53,CC_TypeL,0)),1)) -> 1 | AU53: 2
A54: 12 | AD54: =IF(E54="Exchanger",IF(AND(ISNUMBER(S54),ISNUMBER(U54),ISNUMBER(V54)),S54*PI()/4*(U54*INDEX(LenF,MATCH($U$7,LenU,0)))^2*V54*INDEX(LenF,MATCH($V$7,LenU,0)),0)+IF(ISNUMBER(Y54),PI()/4*(Y54*INDEX(LenF,MATCH($Y$7,LenU,0)))^2*N(Z54)*INDEX(LenF,MATCH($Z$7,LenU,0))+IF(AA54="",0,IF(AA54="Conical",PI()/12*(Y54*INDEX(LenF,MATCH($Y$7,LenU,0)))^2*(0),INDEX(HeadK,MATCH(AA54,HeadU,0))*(Y54*INDEX(LenF,MATCH($Y$7,LenU,0)))^3)),0)+IF(ISNUMBER(Y54),PI()/4*(Y54*INDEX(LenF,MATCH($Y$7,LenU,0)))^2*N(AB54)*INDEX(LenF,MATCH($AB$7,LenU,0))+IF(AC54="",0,IF(AC54="Conical",PI()/12*(Y54*INDEX(LenF,MATCH($Y$7,LenU,0)))^2*(0),INDEX(HeadK,MATCH(AC54,HeadU,0))*(Y54*INDEX(LenF,MATCH($Y$7,LenU,0)))^3)),0),"") | AE54: =IF(OR(E54="",E54="Piping"),"",IF(E54="Exchanger",AQ54*AR54+IF(P54="",0,IF(P54="Conical",PI()/12*(SQRT(4*AQ54/PI()))^2*(0),INDEX(HeadK,MATCH(P54,HeadU,0))*(SQRT(4*AQ54/PI()))^3))-IF(AND(ISNUMBER(S54),ISNUMBER(V54)),S54*PI()/4*AP54^2*V54*INDEX(LenF,MATCH($V$7,LenU,0)),0),IF(ISNUMBER(N54),PI()/4*(N54*INDEX(LenF,MATCH($N$7,LenU,0)))^2*N(O54)*INDEX(LenF,MATCH($O$7,LenU,0))+IF(P54="",0,IF(P54="Conical",PI()/12*(N54*INDEX(LenF,MATCH($N$7,LenU,0)))^2*(N(R54)*INDEX(LenF,MATCH($R$7,LenU,0))),INDEX(HeadK,MATCH(P54,HeadU,0))*(N54*INDEX(LenF,MATCH($N$7,LenU,0)))^3))+IF(Q54="",0,IF(Q54="Conical",PI()/12*(N54*INDEX(LenF,MATCH($N$7,LenU,0)))^2*(N(R54)*INDEX(LenF,MATCH($R$7,LenU,0))),INDEX(HeadK,MATCH(Q54,HeadU,0))*(N54*INDEX(LenF,MATCH($N$7,LenU,0)))^3)),0))) | AF54: =IF(E54<>"Piping","",IF(AND(ISNUMBER(AS54),ISNUMBER(M54)),PI()/4*(AS54/1000)^2*M54*INDEX(LenF,MATCH($M$7,LenU,0)),0)) | AG54: =IF(E54="","",N(AD54)+N(AE54)+N(AF54)) | AH54: =IF(ISNUMBER(I54),I54*INDEX(WtF,MATCH($I$7,WtU,0))/CC_WaterRho,"") | AM54: =IF(AO54="","",AO54*IF(ISNUMBER(AK54),AK54,CC_DefFills)*(1+IF(ISNUMBER(AL54),AL54,CC_DefAllow))) | AN54: =IF(G54="Given volume",IF(ISNUMBER(H54),H54*INDEX(VolF,MATCH($H$7,VolU,0)),""),IF(G54="Water weight",AH54,IF(N(AG54)=0,"",AG54))) | AO54: =IF(N(AN54)=0,"",AN54*AT54*IF(ISNUMBER(AJ54),AJ54,CC_DefCirc)) | AP54: =IF(ISNUMBER(T54),T54*INDEX(LenF,MATCH($T$7,LenU,0)),IF(ISNUMBER(W54),W54*INDEX(LenF,MATCH($W$7,LenU,0))/CC_PitchRatio,0)) -> 0 | AQ54: =IF(ISNUMBER(N54),PI()/4*(N54*INDEX(LenF,MATCH($N$7,LenU,0)))^2,IF(AND(ISNUMBER(S54),ISNUMBER(W54),X54<>""),S54*(W54*INDEX(LenF,MATCH($W$7,LenU,0)))^2*INDEX(LayoutF,MATCH(X54,LayoutU,0)),0)) -> 0 | AR54: =IF(ISNUMBER(O54),O54*INDEX(LenF,MATCH($O$7,LenU,0)),IF(ISNUMBER(V54),V54*INDEX(LenF,MATCH($V$7,LenU,0)),0)) -> 0 | AS54: =IF(ISNUMBER(L54),L54*INDEX(LenF,MATCH($L$7,LenU,0))*1000,IF(OR(J54="",K54=""),"",IFERROR(IF(INDEX(PipeWT,MATCH(J54,NPSU,0),MATCH(K54,SchU,0))="","Sch n/a",INDEX(PipeOD,MATCH(J54,NPSU,0))-2*INDEX(PipeWT,MATCH(J54,NPSU,0),MATCH(K54,SchU,0))),""))) | AT54: =IF(ISNUMBER(AI54),AI54,IFERROR(INDEX(IF(CC_JobType="Decontamination",CC_TypeFillDC,CC_TypeFillCC),MATCH(E54,CC_TypeL,0)),1)) -> 1 | AU54: 2
... A72: 30 | AD72: =IF(E72="Exchanger",IF(AND(ISNUMBER(S72),ISNUMBER(U72),ISNUMBER(V72)),S72*PI()/4*(U72*INDEX(LenF,MATCH($U$7,LenU,0)))^2*V72*INDEX(LenF,MATCH($V$7,LenU,0)),0)+IF(ISNUMBER(Y72),PI()/4*(Y72*INDEX(LenF,MATCH($Y$7,LenU,0)))^2*N(Z72)*INDEX(LenF,MATCH($Z$7,LenU,0))+IF(AA72="",0,IF(AA72="Conical",PI()/12*(Y72*INDEX(LenF,MATCH($Y$7,LenU,0)))^2*(0),INDEX(HeadK,MATCH(AA72,HeadU,0))*(Y72*INDEX(LenF,MATCH($Y$7,LenU,0)))^3)),0)+IF(ISNUMBER(Y72),PI()/4*(Y72*INDEX(LenF,MATCH($Y$7,LenU,0)))^2*N(AB72)*INDEX(LenF,MATCH($AB$7,LenU,0))+IF(AC72="",0,IF(AC72="Conical",PI()/12*(Y72*INDEX(LenF,MATCH($Y$7,LenU,0)))^2*(0),INDEX(HeadK,MATCH(AC72,HeadU,0))*(Y72*INDEX(LenF,MATCH($Y$7,LenU,0)))^3)),0),"") | AE72: =IF(OR(E72="",E72="Piping"),"",IF(E72="Exchanger",AQ72*AR72+IF(P72="",0,IF(P72="Conical",PI()/12*(SQRT(4*AQ72/PI()))^2*(0),INDEX(HeadK,MATCH(P72,HeadU,0))*(SQRT(4*AQ72/PI()))^3))-IF(AND(ISNUMBER(S72),ISNUMBER(V72)),S72*PI()/4*AP72^2*V72*INDEX(LenF,MATCH($V$7,LenU,0)),0),IF(ISNUMBER(N72),PI()/4*(N72*INDEX(LenF,MATCH($N$7,LenU,0)))^2*N(O72)*INDEX(LenF,MATCH($O$7,LenU,0))+IF(P72="",0,IF(P72="Conical",PI()/12*(N72*INDEX(LenF,MATCH($N$7,LenU,0)))^2*(N(R72)*INDEX(LenF,MATCH($R$7,LenU,0))),INDEX(HeadK,MATCH(P72,HeadU,0))*(N72*INDEX(LenF,MATCH($N$7,LenU,0)))^3))+IF(Q72="",0,IF(Q72="Conical",PI()/12*(N72*INDEX(LenF,MATCH($N$7,LenU,0)))^2*(N(R72)*INDEX(LenF,MATCH($R$7,LenU,0))),INDEX(HeadK,MATCH(Q72,HeadU,0))*(N72*INDEX(LenF,MATCH($N$7,LenU,0)))^3)),0))) | AF72: =IF(E72<>"Piping","",IF(AND(ISNUMBER(AS72),ISNUMBER(M72)),PI()/4*(AS72/1000)^2*M72*INDEX(LenF,MATCH($M$7,LenU,0)),0)) | AG72: =IF(E72="","",N(AD72)+N(AE72)+N(AF72)) | AH72: =IF(ISNUMBER(I72),I72*INDEX(WtF,MATCH($I$7,WtU,0))/CC_WaterRho,"") | AM72: =IF(AO72="","",AO72*IF(ISNUMBER(AK72),AK72,CC_DefFills)*(1+IF(ISNUMBER(AL72),AL72,CC_DefAllow))) | AN72: =IF(G72="Given volume",IF(ISNUMBER(H72),H72*INDEX(VolF,MATCH($H$7,VolU,0)),""),IF(G72="Water weight",AH72,IF(N(AG72)=0,"",AG72))) | AO72: =IF(N(AN72)=0,"",AN72*AT72*IF(ISNUMBER(AJ72),AJ72,CC_DefCirc)) | AP72: =IF(ISNUMBER(T72),T72*INDEX(LenF,MATCH($T$7,LenU,0)),IF(ISNUMBER(W72),W72*INDEX(LenF,MATCH($W$7,LenU,0))/CC_PitchRatio,0)) -> 0 | AQ72: =IF(ISNUMBER(N72),PI()/4*(N72*INDEX(LenF,MATCH($N$7,LenU,0)))^2,IF(AND(ISNUMBER(S72),ISNUMBER(W72),X72<>""),S72*(W72*INDEX(LenF,MATCH($W$7,LenU,0)))^2*INDEX(LayoutF,MATCH(X72,LayoutU,0)),0)) -> 0 | AR72: =IF(ISNUMBER(O72),O72*INDEX(LenF,MATCH($O$7,LenU,0)),IF(ISNUMBER(V72),V72*INDEX(LenF,MATCH($V$7,LenU,0)),0)) -> 0 | AS72: =IF(ISNUMBER(L72),L72*INDEX(LenF,MATCH($L$7,LenU,0))*1000,IF(OR(J72="",K72=""),"",IFERROR(IF(INDEX(PipeWT,MATCH(J72,NPSU,0),MATCH(K72,SchU,0))="","Sch n/a",INDEX(PipeOD,MATCH(J72,NPSU,0))-2*INDEX(PipeWT,MATCH(J72,NPSU,0),MATCH(K72,SchU,0))),""))) | AT72: =IF(ISNUMBER(AI72),AI72,IFERROR(INDEX(IF(CC_JobType="Decontamination",CC_TypeFillDC,CC_TypeFillCC),MATCH(E72,CC_TypeL,0)),1)) -> 1 | AU72: 2
A73: ="TOTAL – "&INDEX(CC_UnitNames,2) -> TOTAL – Unit 2 | S73: =COUNT(AN43:AN72)&" items" -> 0 items | AD73: =SUM(AD43:AD72) -> 0 | AE73: =SUM(AE43:AE72) -> 0 | AF73: =SUM(AF43:AF72) -> 0 | AG73: =SUM(AG43:AG72) -> 0 | AH73: =SUM(AH43:AH72) -> 0 | AM73: =SUM(AM43:AM72) -> 0 | AN73: =SUM(AN43:AN72) -> 0 | AO73: =SUM(AO43:AO72) -> 0
A75: ="UNIT 3: "&INDEX(CC_UnitNames,3) -> UNIT 3: Unit 3
A76: 1 | AD76: =IF(E76="Exchanger",IF(AND(ISNUMBER(S76),ISNUMBER(U76),ISNUMBER(V76)),S76*PI()/4*(U76*INDEX(LenF,MATCH($U$7,LenU,0)))^2*V76*INDEX(LenF,MATCH($V$7,LenU,0)),0)+IF(ISNUMBER(Y76),PI()/4*(Y76*INDEX(LenF,MATCH($Y$7,LenU,0)))^2*N(Z76)*INDEX(LenF,MATCH($Z$7,LenU,0))+IF(AA76="",0,IF(AA76="Conical",PI()/12*(Y76*INDEX(LenF,MATCH($Y$7,LenU,0)))^2*(0),INDEX(HeadK,MATCH(AA76,HeadU,0))*(Y76*INDEX(LenF,MATCH($Y$7,LenU,0)))^3)),0)+IF(ISNUMBER(Y76),PI()/4*(Y76*INDEX(LenF,MATCH($Y$7,LenU,0)))^2*N(AB76)*INDEX(LenF,MATCH($AB$7,LenU,0))+IF(AC76="",0,IF(AC76="Conical",PI()/12*(Y76*INDEX(LenF,MATCH($Y$7,LenU,0)))^2*(0),INDEX(HeadK,MATCH(AC76,HeadU,0))*(Y76*INDEX(LenF,MATCH($Y$7,LenU,0)))^3)),0),"") | AE76: =IF(OR(E76="",E76="Piping"),"",IF(E76="Exchanger",AQ76*AR76+IF(P76="",0,IF(P76="Conical",PI()/12*(SQRT(4*AQ76/PI()))^2*(0),INDEX(HeadK,MATCH(P76,HeadU,0))*(SQRT(4*AQ76/PI()))^3))-IF(AND(ISNUMBER(S76),ISNUMBER(V76)),S76*PI()/4*AP76^2*V76*INDEX(LenF,MATCH($V$7,LenU,0)),0),IF(ISNUMBER(N76),PI()/4*(N76*INDEX(LenF,MATCH($N$7,LenU,0)))^2*N(O76)*INDEX(LenF,MATCH($O$7,LenU,0))+IF(P76="",0,IF(P76="Conical",PI()/12*(N76*INDEX(LenF,MATCH($N$7,LenU,0)))^2*(N(R76)*INDEX(LenF,MATCH($R$7,LenU,0))),INDEX(HeadK,MATCH(P76,HeadU,0))*(N76*INDEX(LenF,MATCH($N$7,LenU,0)))^3))+IF(Q76="",0,IF(Q76="Conical",PI()/12*(N76*INDEX(LenF,MATCH($N$7,LenU,0)))^2*(N(R76)*INDEX(LenF,MATCH($R$7,LenU,0))),INDEX(HeadK,MATCH(Q76,HeadU,0))*(N76*INDEX(LenF,MATCH($N$7,LenU,0)))^3)),0))) | AF76: =IF(E76<>"Piping","",IF(AND(ISNUMBER(AS76),ISNUMBER(M76)),PI()/4*(AS76/1000)^2*M76*INDEX(LenF,MATCH($M$7,LenU,0)),0)) | AG76: =IF(E76="","",N(AD76)+N(AE76)+N(AF76)) | AH76: =IF(ISNUMBER(I76),I76*INDEX(WtF,MATCH($I$7,WtU,0))/CC_WaterRho,"") | AM76: =IF(AO76="","",AO76*IF(ISNUMBER(AK76),AK76,CC_DefFills)*(1+IF(ISNUMBER(AL76),AL76,CC_DefAllow))) | AN76: =IF(G76="Given volume",IF(ISNUMBER(H76),H76*INDEX(VolF,MATCH($H$7,VolU,0)),""),IF(G76="Water weight",AH76,IF(N(AG76)=0,"",AG76))) | AO76: =IF(N(AN76)=0,"",AN76*AT76*IF(ISNUMBER(AJ76),AJ76,CC_DefCirc)) | AP76: =IF(ISNUMBER(T76),T76*INDEX(LenF,MATCH($T$7,LenU,0)),IF(ISNUMBER(W76),W76*INDEX(LenF,MATCH($W$7,LenU,0))/CC_PitchRatio,0)) -> 0 | AQ76: =IF(ISNUMBER(N76),PI()/4*(N76*INDEX(LenF,MATCH($N$7,LenU,0)))^2,IF(AND(ISNUMBER(S76),ISNUMBER(W76),X76<>""),S76*(W76*INDEX(LenF,MATCH($W$7,LenU,0)))^2*INDEX(LayoutF,MATCH(X76,LayoutU,0)),0)) -> 0 | AR76: =IF(ISNUMBER(O76),O76*INDEX(LenF,MATCH($O$7,LenU,0)),IF(ISNUMBER(V76),V76*INDEX(LenF,MATCH($V$7,LenU,0)),0)) -> 0 | AS76: =IF(ISNUMBER(L76),L76*INDEX(LenF,MATCH($L$7,LenU,0))*1000,IF(OR(J76="",K76=""),"",IFERROR(IF(INDEX(PipeWT,MATCH(J76,NPSU,0),MATCH(K76,SchU,0))="","Sch n/a",INDEX(PipeOD,MATCH(J76,NPSU,0))-2*INDEX(PipeWT,MATCH(J76,NPSU,0),MATCH(K76,SchU,0))),""))) | AT76: =IF(ISNUMBER(AI76),AI76,IFERROR(INDEX(IF(CC_JobType="Decontamination",CC_TypeFillDC,CC_TypeFillCC),MATCH(E76,CC_TypeL,0)),1)) -> 1 | AU76: 3
A77: 2 | AD77: =IF(E77="Exchanger",IF(AND(ISNUMBER(S77),ISNUMBER(U77),ISNUMBER(V77)),S77*PI()/4*(U77*INDEX(LenF,MATCH($U$7,LenU,0)))^2*V77*INDEX(LenF,MATCH($V$7,LenU,0)),0)+IF(ISNUMBER(Y77),PI()/4*(Y77*INDEX(LenF,MATCH($Y$7,LenU,0)))^2*N(Z77)*INDEX(LenF,MATCH($Z$7,LenU,0))+IF(AA77="",0,IF(AA77="Conical",PI()/12*(Y77*INDEX(LenF,MATCH($Y$7,LenU,0)))^2*(0),INDEX(HeadK,MATCH(AA77,HeadU,0))*(Y77*INDEX(LenF,MATCH($Y$7,LenU,0)))^3)),0)+IF(ISNUMBER(Y77),PI()/4*(Y77*INDEX(LenF,MATCH($Y$7,LenU,0)))^2*N(AB77)*INDEX(LenF,MATCH($AB$7,LenU,0))+IF(AC77="",0,IF(AC77="Conical",PI()/12*(Y77*INDEX(LenF,MATCH($Y$7,LenU,0)))^2*(0),INDEX(HeadK,MATCH(AC77,HeadU,0))*(Y77*INDEX(LenF,MATCH($Y$7,LenU,0)))^3)),0),"") | AE77: =IF(OR(E77="",E77="Piping"),"",IF(E77="Exchanger",AQ77*AR77+IF(P77="",0,IF(P77="Conical",PI()/12*(SQRT(4*AQ77/PI()))^2*(0),INDEX(HeadK,MATCH(P77,HeadU,0))*(SQRT(4*AQ77/PI()))^3))-IF(AND(ISNUMBER(S77),ISNUMBER(V77)),S77*PI()/4*AP77^2*V77*INDEX(LenF,MATCH($V$7,LenU,0)),0),IF(ISNUMBER(N77),PI()/4*(N77*INDEX(LenF,MATCH($N$7,LenU,0)))^2*N(O77)*INDEX(LenF,MATCH($O$7,LenU,0))+IF(P77="",0,IF(P77="Conical",PI()/12*(N77*INDEX(LenF,MATCH($N$7,LenU,0)))^2*(N(R77)*INDEX(LenF,MATCH($R$7,LenU,0))),INDEX(HeadK,MATCH(P77,HeadU,0))*(N77*INDEX(LenF,MATCH($N$7,LenU,0)))^3))+IF(Q77="",0,IF(Q77="Conical",PI()/12*(N77*INDEX(LenF,MATCH($N$7,LenU,0)))^2*(N(R77)*INDEX(LenF,MATCH($R$7,LenU,0))),INDEX(HeadK,MATCH(Q77,HeadU,0))*(N77*INDEX(LenF,MATCH($N$7,LenU,0)))^3)),0))) | AF77: =IF(E77<>"Piping","",IF(AND(ISNUMBER(AS77),ISNUMBER(M77)),PI()/4*(AS77/1000)^2*M77*INDEX(LenF,MATCH($M$7,LenU,0)),0)) | AG77: =IF(E77="","",N(AD77)+N(AE77)+N(AF77)) | AH77: =IF(ISNUMBER(I77),I77*INDEX(WtF,MATCH($I$7,WtU,0))/CC_WaterRho,"") | AM77: =IF(AO77="","",AO77*IF(ISNUMBER(AK77),AK77,CC_DefFills)*(1+IF(ISNUMBER(AL77),AL77,CC_DefAllow))) | AN77: =IF(G77="Given volume",IF(ISNUMBER(H77),H77*INDEX(VolF,MATCH($H$7,VolU,0)),""),IF(G77="Water weight",AH77,IF(N(AG77)=0,"",AG77))) | AO77: =IF(N(AN77)=0,"",AN77*AT77*IF(ISNUMBER(AJ77),AJ77,CC_DefCirc)) | AP77: =IF(ISNUMBER(T77),T77*INDEX(LenF,MATCH($T$7,LenU,0)),IF(ISNUMBER(W77),W77*INDEX(LenF,MATCH($W$7,LenU,0))/CC_PitchRatio,0)) -> 0 | AQ77: =IF(ISNUMBER(N77),PI()/4*(N77*INDEX(LenF,MATCH($N$7,LenU,0)))^2,IF(AND(ISNUMBER(S77),ISNUMBER(W77),X77<>""),S77*(W77*INDEX(LenF,MATCH($W$7,LenU,0)))^2*INDEX(LayoutF,MATCH(X77,LayoutU,0)),0)) -> 0 | AR77: =IF(ISNUMBER(O77),O77*INDEX(LenF,MATCH($O$7,LenU,0)),IF(ISNUMBER(V77),V77*INDEX(LenF,MATCH($V$7,LenU,0)),0)) -> 0 | AS77: =IF(ISNUMBER(L77),L77*INDEX(LenF,MATCH($L$7,LenU,0))*1000,IF(OR(J77="",K77=""),"",IFERROR(IF(INDEX(PipeWT,MATCH(J77,NPSU,0),MATCH(K77,SchU,0))="","Sch n/a",INDEX(PipeOD,MATCH(J77,NPSU,0))-2*INDEX(PipeWT,MATCH(J77,NPSU,0),MATCH(K77,SchU,0))),""))) | AT77: =IF(ISNUMBER(AI77),AI77,IFERROR(INDEX(IF(CC_JobType="Decontamination",CC_TypeFillDC,CC_TypeFillCC),MATCH(E77,CC_TypeL,0)),1)) -> 1 | AU77: 3
A78: 3 | AD78: =IF(E78="Exchanger",IF(AND(ISNUMBER(S78),ISNUMBER(U78),ISNUMBER(V78)),S78*PI()/4*(U78*INDEX(LenF,MATCH($U$7,LenU,0)))^2*V78*INDEX(LenF,MATCH($V$7,LenU,0)),0)+IF(ISNUMBER(Y78),PI()/4*(Y78*INDEX(LenF,MATCH($Y$7,LenU,0)))^2*N(Z78)*INDEX(LenF,MATCH($Z$7,LenU,0))+IF(AA78="",0,IF(AA78="Conical",PI()/12*(Y78*INDEX(LenF,MATCH($Y$7,LenU,0)))^2*(0),INDEX(HeadK,MATCH(AA78,HeadU,0))*(Y78*INDEX(LenF,MATCH($Y$7,LenU,0)))^3)),0)+IF(ISNUMBER(Y78),PI()/4*(Y78*INDEX(LenF,MATCH($Y$7,LenU,0)))^2*N(AB78)*INDEX(LenF,MATCH($AB$7,LenU,0))+IF(AC78="",0,IF(AC78="Conical",PI()/12*(Y78*INDEX(LenF,MATCH($Y$7,LenU,0)))^2*(0),INDEX(HeadK,MATCH(AC78,HeadU,0))*(Y78*INDEX(LenF,MATCH($Y$7,LenU,0)))^3)),0),"") | AE78: =IF(OR(E78="",E78="Piping"),"",IF(E78="Exchanger",AQ78*AR78+IF(P78="",0,IF(P78="Conical",PI()/12*(SQRT(4*AQ78/PI()))^2*(0),INDEX(HeadK,MATCH(P78,HeadU,0))*(SQRT(4*AQ78/PI()))^3))-IF(AND(ISNUMBER(S78),ISNUMBER(V78)),S78*PI()/4*AP78^2*V78*INDEX(LenF,MATCH($V$7,LenU,0)),0),IF(ISNUMBER(N78),PI()/4*(N78*INDEX(LenF,MATCH($N$7,LenU,0)))^2*N(O78)*INDEX(LenF,MATCH($O$7,LenU,0))+IF(P78="",0,IF(P78="Conical",PI()/12*(N78*INDEX(LenF,MATCH($N$7,LenU,0)))^2*(N(R78)*INDEX(LenF,MATCH($R$7,LenU,0))),INDEX(HeadK,MATCH(P78,HeadU,0))*(N78*INDEX(LenF,MATCH($N$7,LenU,0)))^3))+IF(Q78="",0,IF(Q78="Conical",PI()/12*(N78*INDEX(LenF,MATCH($N$7,LenU,0)))^2*(N(R78)*INDEX(LenF,MATCH($R$7,LenU,0))),INDEX(HeadK,MATCH(Q78,HeadU,0))*(N78*INDEX(LenF,MATCH($N$7,LenU,0)))^3)),0))) | AF78: =IF(E78<>"Piping","",IF(AND(ISNUMBER(AS78),ISNUMBER(M78)),PI()/4*(AS78/1000)^2*M78*INDEX(LenF,MATCH($M$7,LenU,0)),0)) | AG78: =IF(E78="","",N(AD78)+N(AE78)+N(AF78)) | AH78: =IF(ISNUMBER(I78),I78*INDEX(WtF,MATCH($I$7,WtU,0))/CC_WaterRho,"") | AM78: =IF(AO78="","",AO78*IF(ISNUMBER(AK78),AK78,CC_DefFills)*(1+IF(ISNUMBER(AL78),AL78,CC_DefAllow))) | AN78: =IF(G78="Given volume",IF(ISNUMBER(H78),H78*INDEX(VolF,MATCH($H$7,VolU,0)),""),IF(G78="Water weight",AH78,IF(N(AG78)=0,"",AG78))) | AO78: =IF(N(AN78)=0,"",AN78*AT78*IF(ISNUMBER(AJ78),AJ78,CC_DefCirc)) | AP78: =IF(ISNUMBER(T78),T78*INDEX(LenF,MATCH($T$7,LenU,0)),IF(ISNUMBER(W78),W78*INDEX(LenF,MATCH($W$7,LenU,0))/CC_PitchRatio,0)) -> 0 | AQ78: =IF(ISNUMBER(N78),PI()/4*(N78*INDEX(LenF,MATCH($N$7,LenU,0)))^2,IF(AND(ISNUMBER(S78),ISNUMBER(W78),X78<>""),S78*(W78*INDEX(LenF,MATCH($W$7,LenU,0)))^2*INDEX(LayoutF,MATCH(X78,LayoutU,0)),0)) -> 0 | AR78: =IF(ISNUMBER(O78),O78*INDEX(LenF,MATCH($O$7,LenU,0)),IF(ISNUMBER(V78),V78*INDEX(LenF,MATCH($V$7,LenU,0)),0)) -> 0 | AS78: =IF(ISNUMBER(L78),L78*INDEX(LenF,MATCH($L$7,LenU,0))*1000,IF(OR(J78="",K78=""),"",IFERROR(IF(INDEX(PipeWT,MATCH(J78,NPSU,0),MATCH(K78,SchU,0))="","Sch n/a",INDEX(PipeOD,MATCH(J78,NPSU,0))-2*INDEX(PipeWT,MATCH(J78,NPSU,0),MATCH(K78,SchU,0))),""))) | AT78: =IF(ISNUMBER(AI78),AI78,IFERROR(INDEX(IF(CC_JobType="Decontamination",CC_TypeFillDC,CC_TypeFillCC),MATCH(E78,CC_TypeL,0)),1)) -> 1 | AU78: 3
A79: 4 | AD79: =IF(E79="Exchanger",IF(AND(ISNUMBER(S79),ISNUMBER(U79),ISNUMBER(V79)),S79*PI()/4*(U79*INDEX(LenF,MATCH($U$7,LenU,0)))^2*V79*INDEX(LenF,MATCH($V$7,LenU,0)),0)+IF(ISNUMBER(Y79),PI()/4*(Y79*INDEX(LenF,MATCH($Y$7,LenU,0)))^2*N(Z79)*INDEX(LenF,MATCH($Z$7,LenU,0))+IF(AA79="",0,IF(AA79="Conical",PI()/12*(Y79*INDEX(LenF,MATCH($Y$7,LenU,0)))^2*(0),INDEX(HeadK,MATCH(AA79,HeadU,0))*(Y79*INDEX(LenF,MATCH($Y$7,LenU,0)))^3)),0)+IF(ISNUMBER(Y79),PI()/4*(Y79*INDEX(LenF,MATCH($Y$7,LenU,0)))^2*N(AB79)*INDEX(LenF,MATCH($AB$7,LenU,0))+IF(AC79="",0,IF(AC79="Conical",PI()/12*(Y79*INDEX(LenF,MATCH($Y$7,LenU,0)))^2*(0),INDEX(HeadK,MATCH(AC79,HeadU,0))*(Y79*INDEX(LenF,MATCH($Y$7,LenU,0)))^3)),0),"") | AE79: =IF(OR(E79="",E79="Piping"),"",IF(E79="Exchanger",AQ79*AR79+IF(P79="",0,IF(P79="Conical",PI()/12*(SQRT(4*AQ79/PI()))^2*(0),INDEX(HeadK,MATCH(P79,HeadU,0))*(SQRT(4*AQ79/PI()))^3))-IF(AND(ISNUMBER(S79),ISNUMBER(V79)),S79*PI()/4*AP79^2*V79*INDEX(LenF,MATCH($V$7,LenU,0)),0),IF(ISNUMBER(N79),PI()/4*(N79*INDEX(LenF,MATCH($N$7,LenU,0)))^2*N(O79)*INDEX(LenF,MATCH($O$7,LenU,0))+IF(P79="",0,IF(P79="Conical",PI()/12*(N79*INDEX(LenF,MATCH($N$7,LenU,0)))^2*(N(R79)*INDEX(LenF,MATCH($R$7,LenU,0))),INDEX(HeadK,MATCH(P79,HeadU,0))*(N79*INDEX(LenF,MATCH($N$7,LenU,0)))^3))+IF(Q79="",0,IF(Q79="Conical",PI()/12*(N79*INDEX(LenF,MATCH($N$7,LenU,0)))^2*(N(R79)*INDEX(LenF,MATCH($R$7,LenU,0))),INDEX(HeadK,MATCH(Q79,HeadU,0))*(N79*INDEX(LenF,MATCH($N$7,LenU,0)))^3)),0))) | AF79: =IF(E79<>"Piping","",IF(AND(ISNUMBER(AS79),ISNUMBER(M79)),PI()/4*(AS79/1000)^2*M79*INDEX(LenF,MATCH($M$7,LenU,0)),0)) | AG79: =IF(E79="","",N(AD79)+N(AE79)+N(AF79)) | AH79: =IF(ISNUMBER(I79),I79*INDEX(WtF,MATCH($I$7,WtU,0))/CC_WaterRho,"") | AM79: =IF(AO79="","",AO79*IF(ISNUMBER(AK79),AK79,CC_DefFills)*(1+IF(ISNUMBER(AL79),AL79,CC_DefAllow))) | AN79: =IF(G79="Given volume",IF(ISNUMBER(H79),H79*INDEX(VolF,MATCH($H$7,VolU,0)),""),IF(G79="Water weight",AH79,IF(N(AG79)=0,"",AG79))) | AO79: =IF(N(AN79)=0,"",AN79*AT79*IF(ISNUMBER(AJ79),AJ79,CC_DefCirc)) | AP79: =IF(ISNUMBER(T79),T79*INDEX(LenF,MATCH($T$7,LenU,0)),IF(ISNUMBER(W79),W79*INDEX(LenF,MATCH($W$7,LenU,0))/CC_PitchRatio,0)) -> 0 | AQ79: =IF(ISNUMBER(N79),PI()/4*(N79*INDEX(LenF,MATCH($N$7,LenU,0)))^2,IF(AND(ISNUMBER(S79),ISNUMBER(W79),X79<>""),S79*(W79*INDEX(LenF,MATCH($W$7,LenU,0)))^2*INDEX(LayoutF,MATCH(X79,LayoutU,0)),0)) -> 0 | AR79: =IF(ISNUMBER(O79),O79*INDEX(LenF,MATCH($O$7,LenU,0)),IF(ISNUMBER(V79),V79*INDEX(LenF,MATCH($V$7,LenU,0)),0)) -> 0 | AS79: =IF(ISNUMBER(L79),L79*INDEX(LenF,MATCH($L$7,LenU,0))*1000,IF(OR(J79="",K79=""),"",IFERROR(IF(INDEX(PipeWT,MATCH(J79,NPSU,0),MATCH(K79,SchU,0))="","Sch n/a",INDEX(PipeOD,MATCH(J79,NPSU,0))-2*INDEX(PipeWT,MATCH(J79,NPSU,0),MATCH(K79,SchU,0))),""))) | AT79: =IF(ISNUMBER(AI79),AI79,IFERROR(INDEX(IF(CC_JobType="Decontamination",CC_TypeFillDC,CC_TypeFillCC),MATCH(E79,CC_TypeL,0)),1)) -> 1 | AU79: 3
A80: 5 | AD80: =IF(E80="Exchanger",IF(AND(ISNUMBER(S80),ISNUMBER(U80),ISNUMBER(V80)),S80*PI()/4*(U80*INDEX(LenF,MATCH($U$7,LenU,0)))^2*V80*INDEX(LenF,MATCH($V$7,LenU,0)),0)+IF(ISNUMBER(Y80),PI()/4*(Y80*INDEX(LenF,MATCH($Y$7,LenU,0)))^2*N(Z80)*INDEX(LenF,MATCH($Z$7,LenU,0))+IF(AA80="",0,IF(AA80="Conical",PI()/12*(Y80*INDEX(LenF,MATCH($Y$7,LenU,0)))^2*(0),INDEX(HeadK,MATCH(AA80,HeadU,0))*(Y80*INDEX(LenF,MATCH($Y$7,LenU,0)))^3)),0)+IF(ISNUMBER(Y80),PI()/4*(Y80*INDEX(LenF,MATCH($Y$7,LenU,0)))^2*N(AB80)*INDEX(LenF,MATCH($AB$7,LenU,0))+IF(AC80="",0,IF(AC80="Conical",PI()/12*(Y80*INDEX(LenF,MATCH($Y$7,LenU,0)))^2*(0),INDEX(HeadK,MATCH(AC80,HeadU,0))*(Y80*INDEX(LenF,MATCH($Y$7,LenU,0)))^3)),0),"") | AE80: =IF(OR(E80="",E80="Piping"),"",IF(E80="Exchanger",AQ80*AR80+IF(P80="",0,IF(P80="Conical",PI()/12*(SQRT(4*AQ80/PI()))^2*(0),INDEX(HeadK,MATCH(P80,HeadU,0))*(SQRT(4*AQ80/PI()))^3))-IF(AND(ISNUMBER(S80),ISNUMBER(V80)),S80*PI()/4*AP80^2*V80*INDEX(LenF,MATCH($V$7,LenU,0)),0),IF(ISNUMBER(N80),PI()/4*(N80*INDEX(LenF,MATCH($N$7,LenU,0)))^2*N(O80)*INDEX(LenF,MATCH($O$7,LenU,0))+IF(P80="",0,IF(P80="Conical",PI()/12*(N80*INDEX(LenF,MATCH($N$7,LenU,0)))^2*(N(R80)*INDEX(LenF,MATCH($R$7,LenU,0))),INDEX(HeadK,MATCH(P80,HeadU,0))*(N80*INDEX(LenF,MATCH($N$7,LenU,0)))^3))+IF(Q80="",0,IF(Q80="Conical",PI()/12*(N80*INDEX(LenF,MATCH($N$7,LenU,0)))^2*(N(R80)*INDEX(LenF,MATCH($R$7,LenU,0))),INDEX(HeadK,MATCH(Q80,HeadU,0))*(N80*INDEX(LenF,MATCH($N$7,LenU,0)))^3)),0))) | AF80: =IF(E80<>"Piping","",IF(AND(ISNUMBER(AS80),ISNUMBER(M80)),PI()/4*(AS80/1000)^2*M80*INDEX(LenF,MATCH($M$7,LenU,0)),0)) | AG80: =IF(E80="","",N(AD80)+N(AE80)+N(AF80)) | AH80: =IF(ISNUMBER(I80),I80*INDEX(WtF,MATCH($I$7,WtU,0))/CC_WaterRho,"") | AM80: =IF(AO80="","",AO80*IF(ISNUMBER(AK80),AK80,CC_DefFills)*(1+IF(ISNUMBER(AL80),AL80,CC_DefAllow))) | AN80: =IF(G80="Given volume",IF(ISNUMBER(H80),H80*INDEX(VolF,MATCH($H$7,VolU,0)),""),IF(G80="Water weight",AH80,IF(N(AG80)=0,"",AG80))) | AO80: =IF(N(AN80)=0,"",AN80*AT80*IF(ISNUMBER(AJ80),AJ80,CC_DefCirc)) | AP80: =IF(ISNUMBER(T80),T80*INDEX(LenF,MATCH($T$7,LenU,0)),IF(ISNUMBER(W80),W80*INDEX(LenF,MATCH($W$7,LenU,0))/CC_PitchRatio,0)) -> 0 | AQ80: =IF(ISNUMBER(N80),PI()/4*(N80*INDEX(LenF,MATCH($N$7,LenU,0)))^2,IF(AND(ISNUMBER(S80),ISNUMBER(W80),X80<>""),S80*(W80*INDEX(LenF,MATCH($W$7,LenU,0)))^2*INDEX(LayoutF,MATCH(X80,LayoutU,0)),0)) -> 0 | AR80: =IF(ISNUMBER(O80),O80*INDEX(LenF,MATCH($O$7,LenU,0)),IF(ISNUMBER(V80),V80*INDEX(LenF,MATCH($V$7,LenU,0)),0)) -> 0 | AS80: =IF(ISNUMBER(L80),L80*INDEX(LenF,MATCH($L$7,LenU,0))*1000,IF(OR(J80="",K80=""),"",IFERROR(IF(INDEX(PipeWT,MATCH(J80,NPSU,0),MATCH(K80,SchU,0))="","Sch n/a",INDEX(PipeOD,MATCH(J80,NPSU,0))-2*INDEX(PipeWT,MATCH(J80,NPSU,0),MATCH(K80,SchU,0))),""))) | AT80: =IF(ISNUMBER(AI80),AI80,IFERROR(INDEX(IF(CC_JobType="Decontamination",CC_TypeFillDC,CC_TypeFillCC),MATCH(E80,CC_TypeL,0)),1)) -> 1 | AU80: 3
A81: 6 | AD81: =IF(E81="Exchanger",IF(AND(ISNUMBER(S81),ISNUMBER(U81),ISNUMBER(V81)),S81*PI()/4*(U81*INDEX(LenF,MATCH($U$7,LenU,0)))^2*V81*INDEX(LenF,MATCH($V$7,LenU,0)),0)+IF(ISNUMBER(Y81),PI()/4*(Y81*INDEX(LenF,MATCH($Y$7,LenU,0)))^2*N(Z81)*INDEX(LenF,MATCH($Z$7,LenU,0))+IF(AA81="",0,IF(AA81="Conical",PI()/12*(Y81*INDEX(LenF,MATCH($Y$7,LenU,0)))^2*(0),INDEX(HeadK,MATCH(AA81,HeadU,0))*(Y81*INDEX(LenF,MATCH($Y$7,LenU,0)))^3)),0)+IF(ISNUMBER(Y81),PI()/4*(Y81*INDEX(LenF,MATCH($Y$7,LenU,0)))^2*N(AB81)*INDEX(LenF,MATCH($AB$7,LenU,0))+IF(AC81="",0,IF(AC81="Conical",PI()/12*(Y81*INDEX(LenF,MATCH($Y$7,LenU,0)))^2*(0),INDEX(HeadK,MATCH(AC81,HeadU,0))*(Y81*INDEX(LenF,MATCH($Y$7,LenU,0)))^3)),0),"") | AE81: =IF(OR(E81="",E81="Piping"),"",IF(E81="Exchanger",AQ81*AR81+IF(P81="",0,IF(P81="Conical",PI()/12*(SQRT(4*AQ81/PI()))^2*(0),INDEX(HeadK,MATCH(P81,HeadU,0))*(SQRT(4*AQ81/PI()))^3))-IF(AND(ISNUMBER(S81),ISNUMBER(V81)),S81*PI()/4*AP81^2*V81*INDEX(LenF,MATCH($V$7,LenU,0)),0),IF(ISNUMBER(N81),PI()/4*(N81*INDEX(LenF,MATCH($N$7,LenU,0)))^2*N(O81)*INDEX(LenF,MATCH($O$7,LenU,0))+IF(P81="",0,IF(P81="Conical",PI()/12*(N81*INDEX(LenF,MATCH($N$7,LenU,0)))^2*(N(R81)*INDEX(LenF,MATCH($R$7,LenU,0))),INDEX(HeadK,MATCH(P81,HeadU,0))*(N81*INDEX(LenF,MATCH($N$7,LenU,0)))^3))+IF(Q81="",0,IF(Q81="Conical",PI()/12*(N81*INDEX(LenF,MATCH($N$7,LenU,0)))^2*(N(R81)*INDEX(LenF,MATCH($R$7,LenU,0))),INDEX(HeadK,MATCH(Q81,HeadU,0))*(N81*INDEX(LenF,MATCH($N$7,LenU,0)))^3)),0))) | AF81: =IF(E81<>"Piping","",IF(AND(ISNUMBER(AS81),ISNUMBER(M81)),PI()/4*(AS81/1000)^2*M81*INDEX(LenF,MATCH($M$7,LenU,0)),0)) | AG81: =IF(E81="","",N(AD81)+N(AE81)+N(AF81)) | AH81: =IF(ISNUMBER(I81),I81*INDEX(WtF,MATCH($I$7,WtU,0))/CC_WaterRho,"") | AM81: =IF(AO81="","",AO81*IF(ISNUMBER(AK81),AK81,CC_DefFills)*(1+IF(ISNUMBER(AL81),AL81,CC_DefAllow))) | AN81: =IF(G81="Given volume",IF(ISNUMBER(H81),H81*INDEX(VolF,MATCH($H$7,VolU,0)),""),IF(G81="Water weight",AH81,IF(N(AG81)=0,"",AG81))) | AO81: =IF(N(AN81)=0,"",AN81*AT81*IF(ISNUMBER(AJ81),AJ81,CC_DefCirc)) | AP81: =IF(ISNUMBER(T81),T81*INDEX(LenF,MATCH($T$7,LenU,0)),IF(ISNUMBER(W81),W81*INDEX(LenF,MATCH($W$7,LenU,0))/CC_PitchRatio,0)) -> 0 | AQ81: =IF(ISNUMBER(N81),PI()/4*(N81*INDEX(LenF,MATCH($N$7,LenU,0)))^2,IF(AND(ISNUMBER(S81),ISNUMBER(W81),X81<>""),S81*(W81*INDEX(LenF,MATCH($W$7,LenU,0)))^2*INDEX(LayoutF,MATCH(X81,LayoutU,0)),0)) -> 0 | AR81: =IF(ISNUMBER(O81),O81*INDEX(LenF,MATCH($O$7,LenU,0)),IF(ISNUMBER(V81),V81*INDEX(LenF,MATCH($V$7,LenU,0)),0)) -> 0 | AS81: =IF(ISNUMBER(L81),L81*INDEX(LenF,MATCH($L$7,LenU,0))*1000,IF(OR(J81="",K81=""),"",IFERROR(IF(INDEX(PipeWT,MATCH(J81,NPSU,0),MATCH(K81,SchU,0))="","Sch n/a",INDEX(PipeOD,MATCH(J81,NPSU,0))-2*INDEX(PipeWT,MATCH(J81,NPSU,0),MATCH(K81,SchU,0))),""))) | AT81: =IF(ISNUMBER(AI81),AI81,IFERROR(INDEX(IF(CC_JobType="Decontamination",CC_TypeFillDC,CC_TypeFillCC),MATCH(E81,CC_TypeL,0)),1)) -> 1 | AU81: 3
A82: 7 | AD82: =IF(E82="Exchanger",IF(AND(ISNUMBER(S82),ISNUMBER(U82),ISNUMBER(V82)),S82*PI()/4*(U82*INDEX(LenF,MATCH($U$7,LenU,0)))^2*V82*INDEX(LenF,MATCH($V$7,LenU,0)),0)+IF(ISNUMBER(Y82),PI()/4*(Y82*INDEX(LenF,MATCH($Y$7,LenU,0)))^2*N(Z82)*INDEX(LenF,MATCH($Z$7,LenU,0))+IF(AA82="",0,IF(AA82="Conical",PI()/12*(Y82*INDEX(LenF,MATCH($Y$7,LenU,0)))^2*(0),INDEX(HeadK,MATCH(AA82,HeadU,0))*(Y82*INDEX(LenF,MATCH($Y$7,LenU,0)))^3)),0)+IF(ISNUMBER(Y82),PI()/4*(Y82*INDEX(LenF,MATCH($Y$7,LenU,0)))^2*N(AB82)*INDEX(LenF,MATCH($AB$7,LenU,0))+IF(AC82="",0,IF(AC82="Conical",PI()/12*(Y82*INDEX(LenF,MATCH($Y$7,LenU,0)))^2*(0),INDEX(HeadK,MATCH(AC82,HeadU,0))*(Y82*INDEX(LenF,MATCH($Y$7,LenU,0)))^3)),0),"") | AE82: =IF(OR(E82="",E82="Piping"),"",IF(E82="Exchanger",AQ82*AR82+IF(P82="",0,IF(P82="Conical",PI()/12*(SQRT(4*AQ82/PI()))^2*(0),INDEX(HeadK,MATCH(P82,HeadU,0))*(SQRT(4*AQ82/PI()))^3))-IF(AND(ISNUMBER(S82),ISNUMBER(V82)),S82*PI()/4*AP82^2*V82*INDEX(LenF,MATCH($V$7,LenU,0)),0),IF(ISNUMBER(N82),PI()/4*(N82*INDEX(LenF,MATCH($N$7,LenU,0)))^2*N(O82)*INDEX(LenF,MATCH($O$7,LenU,0))+IF(P82="",0,IF(P82="Conical",PI()/12*(N82*INDEX(LenF,MATCH($N$7,LenU,0)))^2*(N(R82)*INDEX(LenF,MATCH($R$7,LenU,0))),INDEX(HeadK,MATCH(P82,HeadU,0))*(N82*INDEX(LenF,MATCH($N$7,LenU,0)))^3))+IF(Q82="",0,IF(Q82="Conical",PI()/12*(N82*INDEX(LenF,MATCH($N$7,LenU,0)))^2*(N(R82)*INDEX(LenF,MATCH($R$7,LenU,0))),INDEX(HeadK,MATCH(Q82,HeadU,0))*(N82*INDEX(LenF,MATCH($N$7,LenU,0)))^3)),0))) | AF82: =IF(E82<>"Piping","",IF(AND(ISNUMBER(AS82),ISNUMBER(M82)),PI()/4*(AS82/1000)^2*M82*INDEX(LenF,MATCH($M$7,LenU,0)),0)) | AG82: =IF(E82="","",N(AD82)+N(AE82)+N(AF82)) | AH82: =IF(ISNUMBER(I82),I82*INDEX(WtF,MATCH($I$7,WtU,0))/CC_WaterRho,"") | AM82: =IF(AO82="","",AO82*IF(ISNUMBER(AK82),AK82,CC_DefFills)*(1+IF(ISNUMBER(AL82),AL82,CC_DefAllow))) | AN82: =IF(G82="Given volume",IF(ISNUMBER(H82),H82*INDEX(VolF,MATCH($H$7,VolU,0)),""),IF(G82="Water weight",AH82,IF(N(AG82)=0,"",AG82))) | AO82: =IF(N(AN82)=0,"",AN82*AT82*IF(ISNUMBER(AJ82),AJ82,CC_DefCirc)) | AP82: =IF(ISNUMBER(T82),T82*INDEX(LenF,MATCH($T$7,LenU,0)),IF(ISNUMBER(W82),W82*INDEX(LenF,MATCH($W$7,LenU,0))/CC_PitchRatio,0)) -> 0 | AQ82: =IF(ISNUMBER(N82),PI()/4*(N82*INDEX(LenF,MATCH($N$7,LenU,0)))^2,IF(AND(ISNUMBER(S82),ISNUMBER(W82),X82<>""),S82*(W82*INDEX(LenF,MATCH($W$7,LenU,0)))^2*INDEX(LayoutF,MATCH(X82,LayoutU,0)),0)) -> 0 | AR82: =IF(ISNUMBER(O82),O82*INDEX(LenF,MATCH($O$7,LenU,0)),IF(ISNUMBER(V82),V82*INDEX(LenF,MATCH($V$7,LenU,0)),0)) -> 0 | AS82: =IF(ISNUMBER(L82),L82*INDEX(LenF,MATCH($L$7,LenU,0))*1000,IF(OR(J82="",K82=""),"",IFERROR(IF(INDEX(PipeWT,MATCH(J82,NPSU,0),MATCH(K82,SchU,0))="","Sch n/a",INDEX(PipeOD,MATCH(J82,NPSU,0))-2*INDEX(PipeWT,MATCH(J82,NPSU,0),MATCH(K82,SchU,0))),""))) | AT82: =IF(ISNUMBER(AI82),AI82,IFERROR(INDEX(IF(CC_JobType="Decontamination",CC_TypeFillDC,CC_TypeFillCC),MATCH(E82,CC_TypeL,0)),1)) -> 1 | AU82: 3
A83: 8 | AD83: =IF(E83="Exchanger",IF(AND(ISNUMBER(S83),ISNUMBER(U83),ISNUMBER(V83)),S83*PI()/4*(U83*INDEX(LenF,MATCH($U$7,LenU,0)))^2*V83*INDEX(LenF,MATCH($V$7,LenU,0)),0)+IF(ISNUMBER(Y83),PI()/4*(Y83*INDEX(LenF,MATCH($Y$7,LenU,0)))^2*N(Z83)*INDEX(LenF,MATCH($Z$7,LenU,0))+IF(AA83="",0,IF(AA83="Conical",PI()/12*(Y83*INDEX(LenF,MATCH($Y$7,LenU,0)))^2*(0),INDEX(HeadK,MATCH(AA83,HeadU,0))*(Y83*INDEX(LenF,MATCH($Y$7,LenU,0)))^3)),0)+IF(ISNUMBER(Y83),PI()/4*(Y83*INDEX(LenF,MATCH($Y$7,LenU,0)))^2*N(AB83)*INDEX(LenF,MATCH($AB$7,LenU,0))+IF(AC83="",0,IF(AC83="Conical",PI()/12*(Y83*INDEX(LenF,MATCH($Y$7,LenU,0)))^2*(0),INDEX(HeadK,MATCH(AC83,HeadU,0))*(Y83*INDEX(LenF,MATCH($Y$7,LenU,0)))^3)),0),"") | AE83: =IF(OR(E83="",E83="Piping"),"",IF(E83="Exchanger",AQ83*AR83+IF(P83="",0,IF(P83="Conical",PI()/12*(SQRT(4*AQ83/PI()))^2*(0),INDEX(HeadK,MATCH(P83,HeadU,0))*(SQRT(4*AQ83/PI()))^3))-IF(AND(ISNUMBER(S83),ISNUMBER(V83)),S83*PI()/4*AP83^2*V83*INDEX(LenF,MATCH($V$7,LenU,0)),0),IF(ISNUMBER(N83),PI()/4*(N83*INDEX(LenF,MATCH($N$7,LenU,0)))^2*N(O83)*INDEX(LenF,MATCH($O$7,LenU,0))+IF(P83="",0,IF(P83="Conical",PI()/12*(N83*INDEX(LenF,MATCH($N$7,LenU,0)))^2*(N(R83)*INDEX(LenF,MATCH($R$7,LenU,0))),INDEX(HeadK,MATCH(P83,HeadU,0))*(N83*INDEX(LenF,MATCH($N$7,LenU,0)))^3))+IF(Q83="",0,IF(Q83="Conical",PI()/12*(N83*INDEX(LenF,MATCH($N$7,LenU,0)))^2*(N(R83)*INDEX(LenF,MATCH($R$7,LenU,0))),INDEX(HeadK,MATCH(Q83,HeadU,0))*(N83*INDEX(LenF,MATCH($N$7,LenU,0)))^3)),0))) | AF83: =IF(E83<>"Piping","",IF(AND(ISNUMBER(AS83),ISNUMBER(M83)),PI()/4*(AS83/1000)^2*M83*INDEX(LenF,MATCH($M$7,LenU,0)),0)) | AG83: =IF(E83="","",N(AD83)+N(AE83)+N(AF83)) | AH83: =IF(ISNUMBER(I83),I83*INDEX(WtF,MATCH($I$7,WtU,0))/CC_WaterRho,"") | AM83: =IF(AO83="","",AO83*IF(ISNUMBER(AK83),AK83,CC_DefFills)*(1+IF(ISNUMBER(AL83),AL83,CC_DefAllow))) | AN83: =IF(G83="Given volume",IF(ISNUMBER(H83),H83*INDEX(VolF,MATCH($H$7,VolU,0)),""),IF(G83="Water weight",AH83,IF(N(AG83)=0,"",AG83))) | AO83: =IF(N(AN83)=0,"",AN83*AT83*IF(ISNUMBER(AJ83),AJ83,CC_DefCirc)) | AP83: =IF(ISNUMBER(T83),T83*INDEX(LenF,MATCH($T$7,LenU,0)),IF(ISNUMBER(W83),W83*INDEX(LenF,MATCH($W$7,LenU,0))/CC_PitchRatio,0)) -> 0 | AQ83: =IF(ISNUMBER(N83),PI()/4*(N83*INDEX(LenF,MATCH($N$7,LenU,0)))^2,IF(AND(ISNUMBER(S83),ISNUMBER(W83),X83<>""),S83*(W83*INDEX(LenF,MATCH($W$7,LenU,0)))^2*INDEX(LayoutF,MATCH(X83,LayoutU,0)),0)) -> 0 | AR83: =IF(ISNUMBER(O83),O83*INDEX(LenF,MATCH($O$7,LenU,0)),IF(ISNUMBER(V83),V83*INDEX(LenF,MATCH($V$7,LenU,0)),0)) -> 0 | AS83: =IF(ISNUMBER(L83),L83*INDEX(LenF,MATCH($L$7,LenU,0))*1000,IF(OR(J83="",K83=""),"",IFERROR(IF(INDEX(PipeWT,MATCH(J83,NPSU,0),MATCH(K83,SchU,0))="","Sch n/a",INDEX(PipeOD,MATCH(J83,NPSU,0))-2*INDEX(PipeWT,MATCH(J83,NPSU,0),MATCH(K83,SchU,0))),""))) | AT83: =IF(ISNUMBER(AI83),AI83,IFERROR(INDEX(IF(CC_JobType="Decontamination",CC_TypeFillDC,CC_TypeFillCC),MATCH(E83,CC_TypeL,0)),1)) -> 1 | AU83: 3
A84: 9 | AD84: =IF(E84="Exchanger",IF(AND(ISNUMBER(S84),ISNUMBER(U84),ISNUMBER(V84)),S84*PI()/4*(U84*INDEX(LenF,MATCH($U$7,LenU,0)))^2*V84*INDEX(LenF,MATCH($V$7,LenU,0)),0)+IF(ISNUMBER(Y84),PI()/4*(Y84*INDEX(LenF,MATCH($Y$7,LenU,0)))^2*N(Z84)*INDEX(LenF,MATCH($Z$7,LenU,0))+IF(AA84="",0,IF(AA84="Conical",PI()/12*(Y84*INDEX(LenF,MATCH($Y$7,LenU,0)))^2*(0),INDEX(HeadK,MATCH(AA84,HeadU,0))*(Y84*INDEX(LenF,MATCH($Y$7,LenU,0)))^3)),0)+IF(ISNUMBER(Y84),PI()/4*(Y84*INDEX(LenF,MATCH($Y$7,LenU,0)))^2*N(AB84)*INDEX(LenF,MATCH($AB$7,LenU,0))+IF(AC84="",0,IF(AC84="Conical",PI()/12*(Y84*INDEX(LenF,MATCH($Y$7,LenU,0)))^2*(0),INDEX(HeadK,MATCH(AC84,HeadU,0))*(Y84*INDEX(LenF,MATCH($Y$7,LenU,0)))^3)),0),"") | AE84: =IF(OR(E84="",E84="Piping"),"",IF(E84="Exchanger",AQ84*AR84+IF(P84="",0,IF(P84="Conical",PI()/12*(SQRT(4*AQ84/PI()))^2*(0),INDEX(HeadK,MATCH(P84,HeadU,0))*(SQRT(4*AQ84/PI()))^3))-IF(AND(ISNUMBER(S84),ISNUMBER(V84)),S84*PI()/4*AP84^2*V84*INDEX(LenF,MATCH($V$7,LenU,0)),0),IF(ISNUMBER(N84),PI()/4*(N84*INDEX(LenF,MATCH($N$7,LenU,0)))^2*N(O84)*INDEX(LenF,MATCH($O$7,LenU,0))+IF(P84="",0,IF(P84="Conical",PI()/12*(N84*INDEX(LenF,MATCH($N$7,LenU,0)))^2*(N(R84)*INDEX(LenF,MATCH($R$7,LenU,0))),INDEX(HeadK,MATCH(P84,HeadU,0))*(N84*INDEX(LenF,MATCH($N$7,LenU,0)))^3))+IF(Q84="",0,IF(Q84="Conical",PI()/12*(N84*INDEX(LenF,MATCH($N$7,LenU,0)))^2*(N(R84)*INDEX(LenF,MATCH($R$7,LenU,0))),INDEX(HeadK,MATCH(Q84,HeadU,0))*(N84*INDEX(LenF,MATCH($N$7,LenU,0)))^3)),0))) | AF84: =IF(E84<>"Piping","",IF(AND(ISNUMBER(AS84),ISNUMBER(M84)),PI()/4*(AS84/1000)^2*M84*INDEX(LenF,MATCH($M$7,LenU,0)),0)) | AG84: =IF(E84="","",N(AD84)+N(AE84)+N(AF84)) | AH84: =IF(ISNUMBER(I84),I84*INDEX(WtF,MATCH($I$7,WtU,0))/CC_WaterRho,"") | AM84: =IF(AO84="","",AO84*IF(ISNUMBER(AK84),AK84,CC_DefFills)*(1+IF(ISNUMBER(AL84),AL84,CC_DefAllow))) | AN84: =IF(G84="Given volume",IF(ISNUMBER(H84),H84*INDEX(VolF,MATCH($H$7,VolU,0)),""),IF(G84="Water weight",AH84,IF(N(AG84)=0,"",AG84))) | AO84: =IF(N(AN84)=0,"",AN84*AT84*IF(ISNUMBER(AJ84),AJ84,CC_DefCirc)) | AP84: =IF(ISNUMBER(T84),T84*INDEX(LenF,MATCH($T$7,LenU,0)),IF(ISNUMBER(W84),W84*INDEX(LenF,MATCH($W$7,LenU,0))/CC_PitchRatio,0)) -> 0 | AQ84: =IF(ISNUMBER(N84),PI()/4*(N84*INDEX(LenF,MATCH($N$7,LenU,0)))^2,IF(AND(ISNUMBER(S84),ISNUMBER(W84),X84<>""),S84*(W84*INDEX(LenF,MATCH($W$7,LenU,0)))^2*INDEX(LayoutF,MATCH(X84,LayoutU,0)),0)) -> 0 | AR84: =IF(ISNUMBER(O84),O84*INDEX(LenF,MATCH($O$7,LenU,0)),IF(ISNUMBER(V84),V84*INDEX(LenF,MATCH($V$7,LenU,0)),0)) -> 0 | AS84: =IF(ISNUMBER(L84),L84*INDEX(LenF,MATCH($L$7,LenU,0))*1000,IF(OR(J84="",K84=""),"",IFERROR(IF(INDEX(PipeWT,MATCH(J84,NPSU,0),MATCH(K84,SchU,0))="","Sch n/a",INDEX(PipeOD,MATCH(J84,NPSU,0))-2*INDEX(PipeWT,MATCH(J84,NPSU,0),MATCH(K84,SchU,0))),""))) | AT84: =IF(ISNUMBER(AI84),AI84,IFERROR(INDEX(IF(CC_JobType="Decontamination",CC_TypeFillDC,CC_TypeFillCC),MATCH(E84,CC_TypeL,0)),1)) -> 1 | AU84: 3
A85: 10 | AD85: =IF(E85="Exchanger",IF(AND(ISNUMBER(S85),ISNUMBER(U85),ISNUMBER(V85)),S85*PI()/4*(U85*INDEX(LenF,MATCH($U$7,LenU,0)))^2*V85*INDEX(LenF,MATCH($V$7,LenU,0)),0)+IF(ISNUMBER(Y85),PI()/4*(Y85*INDEX(LenF,MATCH($Y$7,LenU,0)))^2*N(Z85)*INDEX(LenF,MATCH($Z$7,LenU,0))+IF(AA85="",0,IF(AA85="Conical",PI()/12*(Y85*INDEX(LenF,MATCH($Y$7,LenU,0)))^2*(0),INDEX(HeadK,MATCH(AA85,HeadU,0))*(Y85*INDEX(LenF,MATCH($Y$7,LenU,0)))^3)),0)+IF(ISNUMBER(Y85),PI()/4*(Y85*INDEX(LenF,MATCH($Y$7,LenU,0)))^2*N(AB85)*INDEX(LenF,MATCH($AB$7,LenU,0))+IF(AC85="",0,IF(AC85="Conical",PI()/12*(Y85*INDEX(LenF,MATCH($Y$7,LenU,0)))^2*(0),INDEX(HeadK,MATCH(AC85,HeadU,0))*(Y85*INDEX(LenF,MATCH($Y$7,LenU,0)))^3)),0),"") | AE85: =IF(OR(E85="",E85="Piping"),"",IF(E85="Exchanger",AQ85*AR85+IF(P85="",0,IF(P85="Conical",PI()/12*(SQRT(4*AQ85/PI()))^2*(0),INDEX(HeadK,MATCH(P85,HeadU,0))*(SQRT(4*AQ85/PI()))^3))-IF(AND(ISNUMBER(S85),ISNUMBER(V85)),S85*PI()/4*AP85^2*V85*INDEX(LenF,MATCH($V$7,LenU,0)),0),IF(ISNUMBER(N85),PI()/4*(N85*INDEX(LenF,MATCH($N$7,LenU,0)))^2*N(O85)*INDEX(LenF,MATCH($O$7,LenU,0))+IF(P85="",0,IF(P85="Conical",PI()/12*(N85*INDEX(LenF,MATCH($N$7,LenU,0)))^2*(N(R85)*INDEX(LenF,MATCH($R$7,LenU,0))),INDEX(HeadK,MATCH(P85,HeadU,0))*(N85*INDEX(LenF,MATCH($N$7,LenU,0)))^3))+IF(Q85="",0,IF(Q85="Conical",PI()/12*(N85*INDEX(LenF,MATCH($N$7,LenU,0)))^2*(N(R85)*INDEX(LenF,MATCH($R$7,LenU,0))),INDEX(HeadK,MATCH(Q85,HeadU,0))*(N85*INDEX(LenF,MATCH($N$7,LenU,0)))^3)),0))) | AF85: =IF(E85<>"Piping","",IF(AND(ISNUMBER(AS85),ISNUMBER(M85)),PI()/4*(AS85/1000)^2*M85*INDEX(LenF,MATCH($M$7,LenU,0)),0)) | AG85: =IF(E85="","",N(AD85)+N(AE85)+N(AF85)) | AH85: =IF(ISNUMBER(I85),I85*INDEX(WtF,MATCH($I$7,WtU,0))/CC_WaterRho,"") | AM85: =IF(AO85="","",AO85*IF(ISNUMBER(AK85),AK85,CC_DefFills)*(1+IF(ISNUMBER(AL85),AL85,CC_DefAllow))) | AN85: =IF(G85="Given volume",IF(ISNUMBER(H85),H85*INDEX(VolF,MATCH($H$7,VolU,0)),""),IF(G85="Water weight",AH85,IF(N(AG85)=0,"",AG85))) | AO85: =IF(N(AN85)=0,"",AN85*AT85*IF(ISNUMBER(AJ85),AJ85,CC_DefCirc)) | AP85: =IF(ISNUMBER(T85),T85*INDEX(LenF,MATCH($T$7,LenU,0)),IF(ISNUMBER(W85),W85*INDEX(LenF,MATCH($W$7,LenU,0))/CC_PitchRatio,0)) -> 0 | AQ85: =IF(ISNUMBER(N85),PI()/4*(N85*INDEX(LenF,MATCH($N$7,LenU,0)))^2,IF(AND(ISNUMBER(S85),ISNUMBER(W85),X85<>""),S85*(W85*INDEX(LenF,MATCH($W$7,LenU,0)))^2*INDEX(LayoutF,MATCH(X85,LayoutU,0)),0)) -> 0 | AR85: =IF(ISNUMBER(O85),O85*INDEX(LenF,MATCH($O$7,LenU,0)),IF(ISNUMBER(V85),V85*INDEX(LenF,MATCH($V$7,LenU,0)),0)) -> 0 | AS85: =IF(ISNUMBER(L85),L85*INDEX(LenF,MATCH($L$7,LenU,0))*1000,IF(OR(J85="",K85=""),"",IFERROR(IF(INDEX(PipeWT,MATCH(J85,NPSU,0),MATCH(K85,SchU,0))="","Sch n/a",INDEX(PipeOD,MATCH(J85,NPSU,0))-2*INDEX(PipeWT,MATCH(J85,NPSU,0),MATCH(K85,SchU,0))),""))) | AT85: =IF(ISNUMBER(AI85),AI85,IFERROR(INDEX(IF(CC_JobType="Decontamination",CC_TypeFillDC,CC_TypeFillCC),MATCH(E85,CC_TypeL,0)),1)) -> 1 | AU85: 3
A86: 11 | AD86: =IF(E86="Exchanger",IF(AND(ISNUMBER(S86),ISNUMBER(U86),ISNUMBER(V86)),S86*PI()/4*(U86*INDEX(LenF,MATCH($U$7,LenU,0)))^2*V86*INDEX(LenF,MATCH($V$7,LenU,0)),0)+IF(ISNUMBER(Y86),PI()/4*(Y86*INDEX(LenF,MATCH($Y$7,LenU,0)))^2*N(Z86)*INDEX(LenF,MATCH($Z$7,LenU,0))+IF(AA86="",0,IF(AA86="Conical",PI()/12*(Y86*INDEX(LenF,MATCH($Y$7,LenU,0)))^2*(0),INDEX(HeadK,MATCH(AA86,HeadU,0))*(Y86*INDEX(LenF,MATCH($Y$7,LenU,0)))^3)),0)+IF(ISNUMBER(Y86),PI()/4*(Y86*INDEX(LenF,MATCH($Y$7,LenU,0)))^2*N(AB86)*INDEX(LenF,MATCH($AB$7,LenU,0))+IF(AC86="",0,IF(AC86="Conical",PI()/12*(Y86*INDEX(LenF,MATCH($Y$7,LenU,0)))^2*(0),INDEX(HeadK,MATCH(AC86,HeadU,0))*(Y86*INDEX(LenF,MATCH($Y$7,LenU,0)))^3)),0),"") | AE86: =IF(OR(E86="",E86="Piping"),"",IF(E86="Exchanger",AQ86*AR86+IF(P86="",0,IF(P86="Conical",PI()/12*(SQRT(4*AQ86/PI()))^2*(0),INDEX(HeadK,MATCH(P86,HeadU,0))*(SQRT(4*AQ86/PI()))^3))-IF(AND(ISNUMBER(S86),ISNUMBER(V86)),S86*PI()/4*AP86^2*V86*INDEX(LenF,MATCH($V$7,LenU,0)),0),IF(ISNUMBER(N86),PI()/4*(N86*INDEX(LenF,MATCH($N$7,LenU,0)))^2*N(O86)*INDEX(LenF,MATCH($O$7,LenU,0))+IF(P86="",0,IF(P86="Conical",PI()/12*(N86*INDEX(LenF,MATCH($N$7,LenU,0)))^2*(N(R86)*INDEX(LenF,MATCH($R$7,LenU,0))),INDEX(HeadK,MATCH(P86,HeadU,0))*(N86*INDEX(LenF,MATCH($N$7,LenU,0)))^3))+IF(Q86="",0,IF(Q86="Conical",PI()/12*(N86*INDEX(LenF,MATCH($N$7,LenU,0)))^2*(N(R86)*INDEX(LenF,MATCH($R$7,LenU,0))),INDEX(HeadK,MATCH(Q86,HeadU,0))*(N86*INDEX(LenF,MATCH($N$7,LenU,0)))^3)),0))) | AF86: =IF(E86<>"Piping","",IF(AND(ISNUMBER(AS86),ISNUMBER(M86)),PI()/4*(AS86/1000)^2*M86*INDEX(LenF,MATCH($M$7,LenU,0)),0)) | AG86: =IF(E86="","",N(AD86)+N(AE86)+N(AF86)) | AH86: =IF(ISNUMBER(I86),I86*INDEX(WtF,MATCH($I$7,WtU,0))/CC_WaterRho,"") | AM86: =IF(AO86="","",AO86*IF(ISNUMBER(AK86),AK86,CC_DefFills)*(1+IF(ISNUMBER(AL86),AL86,CC_DefAllow))) | AN86: =IF(G86="Given volume",IF(ISNUMBER(H86),H86*INDEX(VolF,MATCH($H$7,VolU,0)),""),IF(G86="Water weight",AH86,IF(N(AG86)=0,"",AG86))) | AO86: =IF(N(AN86)=0,"",AN86*AT86*IF(ISNUMBER(AJ86),AJ86,CC_DefCirc)) | AP86: =IF(ISNUMBER(T86),T86*INDEX(LenF,MATCH($T$7,LenU,0)),IF(ISNUMBER(W86),W86*INDEX(LenF,MATCH($W$7,LenU,0))/CC_PitchRatio,0)) -> 0 | AQ86: =IF(ISNUMBER(N86),PI()/4*(N86*INDEX(LenF,MATCH($N$7,LenU,0)))^2,IF(AND(ISNUMBER(S86),ISNUMBER(W86),X86<>""),S86*(W86*INDEX(LenF,MATCH($W$7,LenU,0)))^2*INDEX(LayoutF,MATCH(X86,LayoutU,0)),0)) -> 0 | AR86: =IF(ISNUMBER(O86),O86*INDEX(LenF,MATCH($O$7,LenU,0)),IF(ISNUMBER(V86),V86*INDEX(LenF,MATCH($V$7,LenU,0)),0)) -> 0 | AS86: =IF(ISNUMBER(L86),L86*INDEX(LenF,MATCH($L$7,LenU,0))*1000,IF(OR(J86="",K86=""),"",IFERROR(IF(INDEX(PipeWT,MATCH(J86,NPSU,0),MATCH(K86,SchU,0))="","Sch n/a",INDEX(PipeOD,MATCH(J86,NPSU,0))-2*INDEX(PipeWT,MATCH(J86,NPSU,0),MATCH(K86,SchU,0))),""))) | AT86: =IF(ISNUMBER(AI86),AI86,IFERROR(INDEX(IF(CC_JobType="Decontamination",CC_TypeFillDC,CC_TypeFillCC),MATCH(E86,CC_TypeL,0)),1)) -> 1 | AU86: 3
A87: 12 | AD87: =IF(E87="Exchanger",IF(AND(ISNUMBER(S87),ISNUMBER(U87),ISNUMBER(V87)),S87*PI()/4*(U87*INDEX(LenF,MATCH($U$7,LenU,0)))^2*V87*INDEX(LenF,MATCH($V$7,LenU,0)),0)+IF(ISNUMBER(Y87),PI()/4*(Y87*INDEX(LenF,MATCH($Y$7,LenU,0)))^2*N(Z87)*INDEX(LenF,MATCH($Z$7,LenU,0))+IF(AA87="",0,IF(AA87="Conical",PI()/12*(Y87*INDEX(LenF,MATCH($Y$7,LenU,0)))^2*(0),INDEX(HeadK,MATCH(AA87,HeadU,0))*(Y87*INDEX(LenF,MATCH($Y$7,LenU,0)))^3)),0)+IF(ISNUMBER(Y87),PI()/4*(Y87*INDEX(LenF,MATCH($Y$7,LenU,0)))^2*N(AB87)*INDEX(LenF,MATCH($AB$7,LenU,0))+IF(AC87="",0,IF(AC87="Conical",PI()/12*(Y87*INDEX(LenF,MATCH($Y$7,LenU,0)))^2*(0),INDEX(HeadK,MATCH(AC87,HeadU,0))*(Y87*INDEX(LenF,MATCH($Y$7,LenU,0)))^3)),0),"") | AE87: =IF(OR(E87="",E87="Piping"),"",IF(E87="Exchanger",AQ87*AR87+IF(P87="",0,IF(P87="Conical",PI()/12*(SQRT(4*AQ87/PI()))^2*(0),INDEX(HeadK,MATCH(P87,HeadU,0))*(SQRT(4*AQ87/PI()))^3))-IF(AND(ISNUMBER(S87),ISNUMBER(V87)),S87*PI()/4*AP87^2*V87*INDEX(LenF,MATCH($V$7,LenU,0)),0),IF(ISNUMBER(N87),PI()/4*(N87*INDEX(LenF,MATCH($N$7,LenU,0)))^2*N(O87)*INDEX(LenF,MATCH($O$7,LenU,0))+IF(P87="",0,IF(P87="Conical",PI()/12*(N87*INDEX(LenF,MATCH($N$7,LenU,0)))^2*(N(R87)*INDEX(LenF,MATCH($R$7,LenU,0))),INDEX(HeadK,MATCH(P87,HeadU,0))*(N87*INDEX(LenF,MATCH($N$7,LenU,0)))^3))+IF(Q87="",0,IF(Q87="Conical",PI()/12*(N87*INDEX(LenF,MATCH($N$7,LenU,0)))^2*(N(R87)*INDEX(LenF,MATCH($R$7,LenU,0))),INDEX(HeadK,MATCH(Q87,HeadU,0))*(N87*INDEX(LenF,MATCH($N$7,LenU,0)))^3)),0))) | AF87: =IF(E87<>"Piping","",IF(AND(ISNUMBER(AS87),ISNUMBER(M87)),PI()/4*(AS87/1000)^2*M87*INDEX(LenF,MATCH($M$7,LenU,0)),0)) | AG87: =IF(E87="","",N(AD87)+N(AE87)+N(AF87)) | AH87: =IF(ISNUMBER(I87),I87*INDEX(WtF,MATCH($I$7,WtU,0))/CC_WaterRho,"") | AM87: =IF(AO87="","",AO87*IF(ISNUMBER(AK87),AK87,CC_DefFills)*(1+IF(ISNUMBER(AL87),AL87,CC_DefAllow))) | AN87: =IF(G87="Given volume",IF(ISNUMBER(H87),H87*INDEX(VolF,MATCH($H$7,VolU,0)),""),IF(G87="Water weight",AH87,IF(N(AG87)=0,"",AG87))) | AO87: =IF(N(AN87)=0,"",AN87*AT87*IF(ISNUMBER(AJ87),AJ87,CC_DefCirc)) | AP87: =IF(ISNUMBER(T87),T87*INDEX(LenF,MATCH($T$7,LenU,0)),IF(ISNUMBER(W87),W87*INDEX(LenF,MATCH($W$7,LenU,0))/CC_PitchRatio,0)) -> 0 | AQ87: =IF(ISNUMBER(N87),PI()/4*(N87*INDEX(LenF,MATCH($N$7,LenU,0)))^2,IF(AND(ISNUMBER(S87),ISNUMBER(W87),X87<>""),S87*(W87*INDEX(LenF,MATCH($W$7,LenU,0)))^2*INDEX(LayoutF,MATCH(X87,LayoutU,0)),0)) -> 0 | AR87: =IF(ISNUMBER(O87),O87*INDEX(LenF,MATCH($O$7,LenU,0)),IF(ISNUMBER(V87),V87*INDEX(LenF,MATCH($V$7,LenU,0)),0)) -> 0 | AS87: =IF(ISNUMBER(L87),L87*INDEX(LenF,MATCH($L$7,LenU,0))*1000,IF(OR(J87="",K87=""),"",IFERROR(IF(INDEX(PipeWT,MATCH(J87,NPSU,0),MATCH(K87,SchU,0))="","Sch n/a",INDEX(PipeOD,MATCH(J87,NPSU,0))-2*INDEX(PipeWT,MATCH(J87,NPSU,0),MATCH(K87,SchU,0))),""))) | AT87: =IF(ISNUMBER(AI87),AI87,IFERROR(INDEX(IF(CC_JobType="Decontamination",CC_TypeFillDC,CC_TypeFillCC),MATCH(E87,CC_TypeL,0)),1)) -> 1 | AU87: 3
... A105: 30 | AD105: =IF(E105="Exchanger",IF(AND(ISNUMBER(S105),ISNUMBER(U105),ISNUMBER(V105)),S105*PI()/4*(U105*INDEX(LenF,MATCH($U$7,LenU,0)))^2*V105*INDEX(LenF,MATCH($V$7,LenU,0)),0)+IF(ISNUMBER(Y105),PI()/4*(Y105*INDEX(LenF,MATCH($Y$7,LenU,0)))^2*N(Z105)*INDEX(LenF,MATCH($Z$7,LenU,0))+IF(AA105="",0,IF(AA105="Conical",PI()/12*(Y105*INDEX(LenF,MATCH($Y$7,LenU,0)))^2*(0),INDEX(HeadK,MATCH(AA105,HeadU,0))*(Y105*INDEX(LenF,MATCH($Y$7,LenU,0)))^3)),0)+IF(ISNUMBER(Y105),PI()/4*(Y105*INDEX(LenF,MATCH($Y$7,LenU,0)))^2*N(AB105)*INDEX(LenF,MATCH($AB$7,LenU,0))+IF(AC105="",0,IF(AC105="Conical",PI()/12*(Y105*INDEX(LenF,MATCH($Y$7,LenU,0)))^2*(0),INDEX(HeadK,MATCH(AC105,HeadU,0))*(Y105*INDEX(LenF,MATCH($Y$7,LenU,0)))^3)),0),"") | AE105: =IF(OR(E105="",E105="Piping"),"",IF(E105="Exchanger",AQ105*AR105+IF(P105="",0,IF(P105="Conical",PI()/12*(SQRT(4*AQ105/PI()))^2*(0),INDEX(HeadK,MATCH(P105,HeadU,0))*(SQRT(4*AQ105/PI()))^3))-IF(AND(ISNUMBER(S105),ISNUMBER(V105)),S105*PI()/4*AP105^2*V105*INDEX(LenF,MATCH($V$7,LenU,0)),0),IF(ISNUMBER(N105),PI()/4*(N105*INDEX(LenF,MATCH($N$7,LenU,0)))^2*N(O105)*INDEX(LenF,MATCH($O$7,LenU,0))+IF(P105="",0,IF(P105="Conical",PI()/12*(N105*INDEX(LenF,MATCH($N$7,LenU,0)))^2*(N(R105)*INDEX(LenF,MATCH($R$7,LenU,0))),INDEX(HeadK,MATCH(P105,HeadU,0))*(N105*INDEX(LenF,MATCH($N$7,LenU,0)))^3))+IF(Q105="",0,IF(Q105="Conical",PI()/12*(N105*INDEX(LenF,MATCH($N$7,LenU,0)))^2*(N(R105)*INDEX(LenF,MATCH($R$7,LenU,0))),INDEX(HeadK,MATCH(Q105,HeadU,0))*(N105*INDEX(LenF,MATCH($N$7,LenU,0)))^3)),0))) | AF105: =IF(E105<>"Piping","",IF(AND(ISNUMBER(AS105),ISNUMBER(M105)),PI()/4*(AS105/1000)^2*M105*INDEX(LenF,MATCH($M$7,LenU,0)),0)) | AG105: =IF(E105="","",N(AD105)+N(AE105)+N(AF105)) | AH105: =IF(ISNUMBER(I105),I105*INDEX(WtF,MATCH($I$7,WtU,0))/CC_WaterRho,"") | AM105: =IF(AO105="","",AO105*IF(ISNUMBER(AK105),AK105,CC_DefFills)*(1+IF(ISNUMBER(AL105),AL105,CC_DefAllow))) | AN105: =IF(G105="Given volume",IF(ISNUMBER(H105),H105*INDEX(VolF,MATCH($H$7,VolU,0)),""),IF(G105="Water weight",AH105,IF(N(AG105)=0,"",AG105))) | AO105: =IF(N(AN105)=0,"",AN105*AT105*IF(ISNUMBER(AJ105),AJ105,CC_DefCirc)) | AP105: =IF(ISNUMBER(T105),T105*INDEX(LenF,MATCH($T$7,LenU,0)),IF(ISNUMBER(W105),W105*INDEX(LenF,MATCH($W$7,LenU,0))/CC_PitchRatio,0)) -> 0 | AQ105: =IF(ISNUMBER(N105),PI()/4*(N105*INDEX(LenF,MATCH($N$7,LenU,0)))^2,IF(AND(ISNUMBER(S105),ISNUMBER(W105),X105<>""),S105*(W105*INDEX(LenF,MATCH($W$7,LenU,0)))^2*INDEX(LayoutF,MATCH(X105,LayoutU,0)),0)) -> 0 | AR105: =IF(ISNUMBER(O105),O105*INDEX(LenF,MATCH($O$7,LenU,0)),IF(ISNUMBER(V105),V105*INDEX(LenF,MATCH($V$7,LenU,0)),0)) -> 0 | AS105: =IF(ISNUMBER(L105),L105*INDEX(LenF,MATCH($L$7,LenU,0))*1000,IF(OR(J105="",K105=""),"",IFERROR(IF(INDEX(PipeWT,MATCH(J105,NPSU,0),MATCH(K105,SchU,0))="","Sch n/a",INDEX(PipeOD,MATCH(J105,NPSU,0))-2*INDEX(PipeWT,MATCH(J105,NPSU,0),MATCH(K105,SchU,0))),""))) | AT105: =IF(ISNUMBER(AI105),AI105,IFERROR(INDEX(IF(CC_JobType="Decontamination",CC_TypeFillDC,CC_TypeFillCC),MATCH(E105,CC_TypeL,0)),1)) -> 1 | AU105: 3
A106: ="TOTAL – "&INDEX(CC_UnitNames,3) -> TOTAL – Unit 3 | S106: =COUNT(AN76:AN105)&" items" -> 0 items | AD106: =SUM(AD76:AD105) -> 0 | AE106: =SUM(AE76:AE105) -> 0 | AF106: =SUM(AF76:AF105) -> 0 | AG106: =SUM(AG76:AG105) -> 0 | AH106: =SUM(AH76:AH105) -> 0 | AM106: =SUM(AM76:AM105) -> 0 | AN106: =SUM(AN76:AN105) -> 0 | AO106: =SUM(AO76:AO105) -> 0
A108: ="UNIT 4: "&INDEX(CC_UnitNames,4) -> UNIT 4: Unit 4
A109: 1 | AD109: =IF(E109="Exchanger",IF(AND(ISNUMBER(S109),ISNUMBER(U109),ISNUMBER(V109)),S109*PI()/4*(U109*INDEX(LenF,MATCH($U$7,LenU,0)))^2*V109*INDEX(LenF,MATCH($V$7,LenU,0)),0)+IF(ISNUMBER(Y109),PI()/4*(Y109*INDEX(LenF,MATCH($Y$7,LenU,0)))^2*N(Z109)*INDEX(LenF,MATCH($Z$7,LenU,0))+IF(AA109="",0,IF(AA109="Conical",PI()/12*(Y109*INDEX(LenF,MATCH($Y$7,LenU,0)))^2*(0),INDEX(HeadK,MATCH(AA109,HeadU,0))*(Y109*INDEX(LenF,MATCH($Y$7,LenU,0)))^3)),0)+IF(ISNUMBER(Y109),PI()/4*(Y109*INDEX(LenF,MATCH($Y$7,LenU,0)))^2*N(AB109)*INDEX(LenF,MATCH($AB$7,LenU,0))+IF(AC109="",0,IF(AC109="Conical",PI()/12*(Y109*INDEX(LenF,MATCH($Y$7,LenU,0)))^2*(0),INDEX(HeadK,MATCH(AC109,HeadU,0))*(Y109*INDEX(LenF,MATCH($Y$7,LenU,0)))^3)),0),"") | AE109: =IF(OR(E109="",E109="Piping"),"",IF(E109="Exchanger",AQ109*AR109+IF(P109="",0,IF(P109="Conical",PI()/12*(SQRT(4*AQ109/PI()))^2*(0),INDEX(HeadK,MATCH(P109,HeadU,0))*(SQRT(4*AQ109/PI()))^3))-IF(AND(ISNUMBER(S109),ISNUMBER(V109)),S109*PI()/4*AP109^2*V109*INDEX(LenF,MATCH($V$7,LenU,0)),0),IF(ISNUMBER(N109),PI()/4*(N109*INDEX(LenF,MATCH($N$7,LenU,0)))^2*N(O109)*INDEX(LenF,MATCH($O$7,LenU,0))+IF(P109="",0,IF(P109="Conical",PI()/12*(N109*INDEX(LenF,MATCH($N$7,LenU,0)))^2*(N(R109)*INDEX(LenF,MATCH($R$7,LenU,0))),INDEX(HeadK,MATCH(P109,HeadU,0))*(N109*INDEX(LenF,MATCH($N$7,LenU,0)))^3))+IF(Q109="",0,IF(Q109="Conical",PI()/12*(N109*INDEX(LenF,MATCH($N$7,LenU,0)))^2*(N(R109)*INDEX(LenF,MATCH($R$7,LenU,0))),INDEX(HeadK,MATCH(Q109,HeadU,0))*(N109*INDEX(LenF,MATCH($N$7,LenU,0)))^3)),0))) | AF109: =IF(E109<>"Piping","",IF(AND(ISNUMBER(AS109),ISNUMBER(M109)),PI()/4*(AS109/1000)^2*M109*INDEX(LenF,MATCH($M$7,LenU,0)),0)) | AG109: =IF(E109="","",N(AD109)+N(AE109)+N(AF109)) | AH109: =IF(ISNUMBER(I109),I109*INDEX(WtF,MATCH($I$7,WtU,0))/CC_WaterRho,"") | AM109: =IF(AO109="","",AO109*IF(ISNUMBER(AK109),AK109,CC_DefFills)*(1+IF(ISNUMBER(AL109),AL109,CC_DefAllow))) | AN109: =IF(G109="Given volume",IF(ISNUMBER(H109),H109*INDEX(VolF,MATCH($H$7,VolU,0)),""),IF(G109="Water weight",AH109,IF(N(AG109)=0,"",AG109))) | AO109: =IF(N(AN109)=0,"",AN109*AT109*IF(ISNUMBER(AJ109),AJ109,CC_DefCirc)) | AP109: =IF(ISNUMBER(T109),T109*INDEX(LenF,MATCH($T$7,LenU,0)),IF(ISNUMBER(W109),W109*INDEX(LenF,MATCH($W$7,LenU,0))/CC_PitchRatio,0)) -> 0 | AQ109: =IF(ISNUMBER(N109),PI()/4*(N109*INDEX(LenF,MATCH($N$7,LenU,0)))^2,IF(AND(ISNUMBER(S109),ISNUMBER(W109),X109<>""),S109*(W109*INDEX(LenF,MATCH($W$7,LenU,0)))^2*INDEX(LayoutF,MATCH(X109,LayoutU,0)),0)) -> 0 | AR109: =IF(ISNUMBER(O109),O109*INDEX(LenF,MATCH($O$7,LenU,0)),IF(ISNUMBER(V109),V109*INDEX(LenF,MATCH($V$7,LenU,0)),0)) -> 0 | AS109: =IF(ISNUMBER(L109),L109*INDEX(LenF,MATCH($L$7,LenU,0))*1000,IF(OR(J109="",K109=""),"",IFERROR(IF(INDEX(PipeWT,MATCH(J109,NPSU,0),MATCH(K109,SchU,0))="","Sch n/a",INDEX(PipeOD,MATCH(J109,NPSU,0))-2*INDEX(PipeWT,MATCH(J109,NPSU,0),MATCH(K109,SchU,0))),""))) | AT109: =IF(ISNUMBER(AI109),AI109,IFERROR(INDEX(IF(CC_JobType="Decontamination",CC_TypeFillDC,CC_TypeFillCC),MATCH(E109,CC_TypeL,0)),1)) -> 1 | AU109: 4
A110: 2 | AD110: =IF(E110="Exchanger",IF(AND(ISNUMBER(S110),ISNUMBER(U110),ISNUMBER(V110)),S110*PI()/4*(U110*INDEX(LenF,MATCH($U$7,LenU,0)))^2*V110*INDEX(LenF,MATCH($V$7,LenU,0)),0)+IF(ISNUMBER(Y110),PI()/4*(Y110*INDEX(LenF,MATCH($Y$7,LenU,0)))^2*N(Z110)*INDEX(LenF,MATCH($Z$7,LenU,0))+IF(AA110="",0,IF(AA110="Conical",PI()/12*(Y110*INDEX(LenF,MATCH($Y$7,LenU,0)))^2*(0),INDEX(HeadK,MATCH(AA110,HeadU,0))*(Y110*INDEX(LenF,MATCH($Y$7,LenU,0)))^3)),0)+IF(ISNUMBER(Y110),PI()/4*(Y110*INDEX(LenF,MATCH($Y$7,LenU,0)))^2*N(AB110)*INDEX(LenF,MATCH($AB$7,LenU,0))+IF(AC110="",0,IF(AC110="Conical",PI()/12*(Y110*INDEX(LenF,MATCH($Y$7,LenU,0)))^2*(0),INDEX(HeadK,MATCH(AC110,HeadU,0))*(Y110*INDEX(LenF,MATCH($Y$7,LenU,0)))^3)),0),"") | AE110: =IF(OR(E110="",E110="Piping"),"",IF(E110="Exchanger",AQ110*AR110+IF(P110="",0,IF(P110="Conical",PI()/12*(SQRT(4*AQ110/PI()))^2*(0),INDEX(HeadK,MATCH(P110,HeadU,0))*(SQRT(4*AQ110/PI()))^3))-IF(AND(ISNUMBER(S110),ISNUMBER(V110)),S110*PI()/4*AP110^2*V110*INDEX(LenF,MATCH($V$7,LenU,0)),0),IF(ISNUMBER(N110),PI()/4*(N110*INDEX(LenF,MATCH($N$7,LenU,0)))^2*N(O110)*INDEX(LenF,MATCH($O$7,LenU,0))+IF(P110="",0,IF(P110="Conical",PI()/12*(N110*INDEX(LenF,MATCH($N$7,LenU,0)))^2*(N(R110)*INDEX(LenF,MATCH($R$7,LenU,0))),INDEX(HeadK,MATCH(P110,HeadU,0))*(N110*INDEX(LenF,MATCH($N$7,LenU,0)))^3))+IF(Q110="",0,IF(Q110="Conical",PI()/12*(N110*INDEX(LenF,MATCH($N$7,LenU,0)))^2*(N(R110)*INDEX(LenF,MATCH($R$7,LenU,0))),INDEX(HeadK,MATCH(Q110,HeadU,0))*(N110*INDEX(LenF,MATCH($N$7,LenU,0)))^3)),0))) | AF110: =IF(E110<>"Piping","",IF(AND(ISNUMBER(AS110),ISNUMBER(M110)),PI()/4*(AS110/1000)^2*M110*INDEX(LenF,MATCH($M$7,LenU,0)),0)) | AG110: =IF(E110="","",N(AD110)+N(AE110)+N(AF110)) | AH110: =IF(ISNUMBER(I110),I110*INDEX(WtF,MATCH($I$7,WtU,0))/CC_WaterRho,"") | AM110: =IF(AO110="","",AO110*IF(ISNUMBER(AK110),AK110,CC_DefFills)*(1+IF(ISNUMBER(AL110),AL110,CC_DefAllow))) | AN110: =IF(G110="Given volume",IF(ISNUMBER(H110),H110*INDEX(VolF,MATCH($H$7,VolU,0)),""),IF(G110="Water weight",AH110,IF(N(AG110)=0,"",AG110))) | AO110: =IF(N(AN110)=0,"",AN110*AT110*IF(ISNUMBER(AJ110),AJ110,CC_DefCirc)) | AP110: =IF(ISNUMBER(T110),T110*INDEX(LenF,MATCH($T$7,LenU,0)),IF(ISNUMBER(W110),W110*INDEX(LenF,MATCH($W$7,LenU,0))/CC_PitchRatio,0)) -> 0 | AQ110: =IF(ISNUMBER(N110),PI()/4*(N110*INDEX(LenF,MATCH($N$7,LenU,0)))^2,IF(AND(ISNUMBER(S110),ISNUMBER(W110),X110<>""),S110*(W110*INDEX(LenF,MATCH($W$7,LenU,0)))^2*INDEX(LayoutF,MATCH(X110,LayoutU,0)),0)) -> 0 | AR110: =IF(ISNUMBER(O110),O110*INDEX(LenF,MATCH($O$7,LenU,0)),IF(ISNUMBER(V110),V110*INDEX(LenF,MATCH($V$7,LenU,0)),0)) -> 0 | AS110: =IF(ISNUMBER(L110),L110*INDEX(LenF,MATCH($L$7,LenU,0))*1000,IF(OR(J110="",K110=""),"",IFERROR(IF(INDEX(PipeWT,MATCH(J110,NPSU,0),MATCH(K110,SchU,0))="","Sch n/a",INDEX(PipeOD,MATCH(J110,NPSU,0))-2*INDEX(PipeWT,MATCH(J110,NPSU,0),MATCH(K110,SchU,0))),""))) | AT110: =IF(ISNUMBER(AI110),AI110,IFERROR(INDEX(IF(CC_JobType="Decontamination",CC_TypeFillDC,CC_TypeFillCC),MATCH(E110,CC_TypeL,0)),1)) -> 1 | AU110: 4
A111: 3 | AD111: =IF(E111="Exchanger",IF(AND(ISNUMBER(S111),ISNUMBER(U111),ISNUMBER(V111)),S111*PI()/4*(U111*INDEX(LenF,MATCH($U$7,LenU,0)))^2*V111*INDEX(LenF,MATCH($V$7,LenU,0)),0)+IF(ISNUMBER(Y111),PI()/4*(Y111*INDEX(LenF,MATCH($Y$7,LenU,0)))^2*N(Z111)*INDEX(LenF,MATCH($Z$7,LenU,0))+IF(AA111="",0,IF(AA111="Conical",PI()/12*(Y111*INDEX(LenF,MATCH($Y$7,LenU,0)))^2*(0),INDEX(HeadK,MATCH(AA111,HeadU,0))*(Y111*INDEX(LenF,MATCH($Y$7,LenU,0)))^3)),0)+IF(ISNUMBER(Y111),PI()/4*(Y111*INDEX(LenF,MATCH($Y$7,LenU,0)))^2*N(AB111)*INDEX(LenF,MATCH($AB$7,LenU,0))+IF(AC111="",0,IF(AC111="Conical",PI()/12*(Y111*INDEX(LenF,MATCH($Y$7,LenU,0)))^2*(0),INDEX(HeadK,MATCH(AC111,HeadU,0))*(Y111*INDEX(LenF,MATCH($Y$7,LenU,0)))^3)),0),"") | AE111: =IF(OR(E111="",E111="Piping"),"",IF(E111="Exchanger",AQ111*AR111+IF(P111="",0,IF(P111="Conical",PI()/12*(SQRT(4*AQ111/PI()))^2*(0),INDEX(HeadK,MATCH(P111,HeadU,0))*(SQRT(4*AQ111/PI()))^3))-IF(AND(ISNUMBER(S111),ISNUMBER(V111)),S111*PI()/4*AP111^2*V111*INDEX(LenF,MATCH($V$7,LenU,0)),0),IF(ISNUMBER(N111),PI()/4*(N111*INDEX(LenF,MATCH($N$7,LenU,0)))^2*N(O111)*INDEX(LenF,MATCH($O$7,LenU,0))+IF(P111="",0,IF(P111="Conical",PI()/12*(N111*INDEX(LenF,MATCH($N$7,LenU,0)))^2*(N(R111)*INDEX(LenF,MATCH($R$7,LenU,0))),INDEX(HeadK,MATCH(P111,HeadU,0))*(N111*INDEX(LenF,MATCH($N$7,LenU,0)))^3))+IF(Q111="",0,IF(Q111="Conical",PI()/12*(N111*INDEX(LenF,MATCH($N$7,LenU,0)))^2*(N(R111)*INDEX(LenF,MATCH($R$7,LenU,0))),INDEX(HeadK,MATCH(Q111,HeadU,0))*(N111*INDEX(LenF,MATCH($N$7,LenU,0)))^3)),0))) | AF111: =IF(E111<>"Piping","",IF(AND(ISNUMBER(AS111),ISNUMBER(M111)),PI()/4*(AS111/1000)^2*M111*INDEX(LenF,MATCH($M$7,LenU,0)),0)) | AG111: =IF(E111="","",N(AD111)+N(AE111)+N(AF111)) | AH111: =IF(ISNUMBER(I111),I111*INDEX(WtF,MATCH($I$7,WtU,0))/CC_WaterRho,"") | AM111: =IF(AO111="","",AO111*IF(ISNUMBER(AK111),AK111,CC_DefFills)*(1+IF(ISNUMBER(AL111),AL111,CC_DefAllow))) | AN111: =IF(G111="Given volume",IF(ISNUMBER(H111),H111*INDEX(VolF,MATCH($H$7,VolU,0)),""),IF(G111="Water weight",AH111,IF(N(AG111)=0,"",AG111))) | AO111: =IF(N(AN111)=0,"",AN111*AT111*IF(ISNUMBER(AJ111),AJ111,CC_DefCirc)) | AP111: =IF(ISNUMBER(T111),T111*INDEX(LenF,MATCH($T$7,LenU,0)),IF(ISNUMBER(W111),W111*INDEX(LenF,MATCH($W$7,LenU,0))/CC_PitchRatio,0)) -> 0 | AQ111: =IF(ISNUMBER(N111),PI()/4*(N111*INDEX(LenF,MATCH($N$7,LenU,0)))^2,IF(AND(ISNUMBER(S111),ISNUMBER(W111),X111<>""),S111*(W111*INDEX(LenF,MATCH($W$7,LenU,0)))^2*INDEX(LayoutF,MATCH(X111,LayoutU,0)),0)) -> 0 | AR111: =IF(ISNUMBER(O111),O111*INDEX(LenF,MATCH($O$7,LenU,0)),IF(ISNUMBER(V111),V111*INDEX(LenF,MATCH($V$7,LenU,0)),0)) -> 0 | AS111: =IF(ISNUMBER(L111),L111*INDEX(LenF,MATCH($L$7,LenU,0))*1000,IF(OR(J111="",K111=""),"",IFERROR(IF(INDEX(PipeWT,MATCH(J111,NPSU,0),MATCH(K111,SchU,0))="","Sch n/a",INDEX(PipeOD,MATCH(J111,NPSU,0))-2*INDEX(PipeWT,MATCH(J111,NPSU,0),MATCH(K111,SchU,0))),""))) | AT111: =IF(ISNUMBER(AI111),AI111,IFERROR(INDEX(IF(CC_JobType="Decontamination",CC_TypeFillDC,CC_TypeFillCC),MATCH(E111,CC_TypeL,0)),1)) -> 1 | AU111: 4
A112: 4 | AD112: =IF(E112="Exchanger",IF(AND(ISNUMBER(S112),ISNUMBER(U112),ISNUMBER(V112)),S112*PI()/4*(U112*INDEX(LenF,MATCH($U$7,LenU,0)))^2*V112*INDEX(LenF,MATCH($V$7,LenU,0)),0)+IF(ISNUMBER(Y112),PI()/4*(Y112*INDEX(LenF,MATCH($Y$7,LenU,0)))^2*N(Z112)*INDEX(LenF,MATCH($Z$7,LenU,0))+IF(AA112="",0,IF(AA112="Conical",PI()/12*(Y112*INDEX(LenF,MATCH($Y$7,LenU,0)))^2*(0),INDEX(HeadK,MATCH(AA112,HeadU,0))*(Y112*INDEX(LenF,MATCH($Y$7,LenU,0)))^3)),0)+IF(ISNUMBER(Y112),PI()/4*(Y112*INDEX(LenF,MATCH($Y$7,LenU,0)))^2*N(AB112)*INDEX(LenF,MATCH($AB$7,LenU,0))+IF(AC112="",0,IF(AC112="Conical",PI()/12*(Y112*INDEX(LenF,MATCH($Y$7,LenU,0)))^2*(0),INDEX(HeadK,MATCH(AC112,HeadU,0))*(Y112*INDEX(LenF,MATCH($Y$7,LenU,0)))^3)),0),"") | AE112: =IF(OR(E112="",E112="Piping"),"",IF(E112="Exchanger",AQ112*AR112+IF(P112="",0,IF(P112="Conical",PI()/12*(SQRT(4*AQ112/PI()))^2*(0),INDEX(HeadK,MATCH(P112,HeadU,0))*(SQRT(4*AQ112/PI()))^3))-IF(AND(ISNUMBER(S112),ISNUMBER(V112)),S112*PI()/4*AP112^2*V112*INDEX(LenF,MATCH($V$7,LenU,0)),0),IF(ISNUMBER(N112),PI()/4*(N112*INDEX(LenF,MATCH($N$7,LenU,0)))^2*N(O112)*INDEX(LenF,MATCH($O$7,LenU,0))+IF(P112="",0,IF(P112="Conical",PI()/12*(N112*INDEX(LenF,MATCH($N$7,LenU,0)))^2*(N(R112)*INDEX(LenF,MATCH($R$7,LenU,0))),INDEX(HeadK,MATCH(P112,HeadU,0))*(N112*INDEX(LenF,MATCH($N$7,LenU,0)))^3))+IF(Q112="",0,IF(Q112="Conical",PI()/12*(N112*INDEX(LenF,MATCH($N$7,LenU,0)))^2*(N(R112)*INDEX(LenF,MATCH($R$7,LenU,0))),INDEX(HeadK,MATCH(Q112,HeadU,0))*(N112*INDEX(LenF,MATCH($N$7,LenU,0)))^3)),0))) | AF112: =IF(E112<>"Piping","",IF(AND(ISNUMBER(AS112),ISNUMBER(M112)),PI()/4*(AS112/1000)^2*M112*INDEX(LenF,MATCH($M$7,LenU,0)),0)) | AG112: =IF(E112="","",N(AD112)+N(AE112)+N(AF112)) | AH112: =IF(ISNUMBER(I112),I112*INDEX(WtF,MATCH($I$7,WtU,0))/CC_WaterRho,"") | AM112: =IF(AO112="","",AO112*IF(ISNUMBER(AK112),AK112,CC_DefFills)*(1+IF(ISNUMBER(AL112),AL112,CC_DefAllow))) | AN112: =IF(G112="Given volume",IF(ISNUMBER(H112),H112*INDEX(VolF,MATCH($H$7,VolU,0)),""),IF(G112="Water weight",AH112,IF(N(AG112)=0,"",AG112))) | AO112: =IF(N(AN112)=0,"",AN112*AT112*IF(ISNUMBER(AJ112),AJ112,CC_DefCirc)) | AP112: =IF(ISNUMBER(T112),T112*INDEX(LenF,MATCH($T$7,LenU,0)),IF(ISNUMBER(W112),W112*INDEX(LenF,MATCH($W$7,LenU,0))/CC_PitchRatio,0)) -> 0 | AQ112: =IF(ISNUMBER(N112),PI()/4*(N112*INDEX(LenF,MATCH($N$7,LenU,0)))^2,IF(AND(ISNUMBER(S112),ISNUMBER(W112),X112<>""),S112*(W112*INDEX(LenF,MATCH($W$7,LenU,0)))^2*INDEX(LayoutF,MATCH(X112,LayoutU,0)),0)) -> 0 | AR112: =IF(ISNUMBER(O112),O112*INDEX(LenF,MATCH($O$7,LenU,0)),IF(ISNUMBER(V112),V112*INDEX(LenF,MATCH($V$7,LenU,0)),0)) -> 0 | AS112: =IF(ISNUMBER(L112),L112*INDEX(LenF,MATCH($L$7,LenU,0))*1000,IF(OR(J112="",K112=""),"",IFERROR(IF(INDEX(PipeWT,MATCH(J112,NPSU,0),MATCH(K112,SchU,0))="","Sch n/a",INDEX(PipeOD,MATCH(J112,NPSU,0))-2*INDEX(PipeWT,MATCH(J112,NPSU,0),MATCH(K112,SchU,0))),""))) | AT112: =IF(ISNUMBER(AI112),AI112,IFERROR(INDEX(IF(CC_JobType="Decontamination",CC_TypeFillDC,CC_TypeFillCC),MATCH(E112,CC_TypeL,0)),1)) -> 1 | AU112: 4
A113: 5 | AD113: =IF(E113="Exchanger",IF(AND(ISNUMBER(S113),ISNUMBER(U113),ISNUMBER(V113)),S113*PI()/4*(U113*INDEX(LenF,MATCH($U$7,LenU,0)))^2*V113*INDEX(LenF,MATCH($V$7,LenU,0)),0)+IF(ISNUMBER(Y113),PI()/4*(Y113*INDEX(LenF,MATCH($Y$7,LenU,0)))^2*N(Z113)*INDEX(LenF,MATCH($Z$7,LenU,0))+IF(AA113="",0,IF(AA113="Conical",PI()/12*(Y113*INDEX(LenF,MATCH($Y$7,LenU,0)))^2*(0),INDEX(HeadK,MATCH(AA113,HeadU,0))*(Y113*INDEX(LenF,MATCH($Y$7,LenU,0)))^3)),0)+IF(ISNUMBER(Y113),PI()/4*(Y113*INDEX(LenF,MATCH($Y$7,LenU,0)))^2*N(AB113)*INDEX(LenF,MATCH($AB$7,LenU,0))+IF(AC113="",0,IF(AC113="Conical",PI()/12*(Y113*INDEX(LenF,MATCH($Y$7,LenU,0)))^2*(0),INDEX(HeadK,MATCH(AC113,HeadU,0))*(Y113*INDEX(LenF,MATCH($Y$7,LenU,0)))^3)),0),"") | AE113: =IF(OR(E113="",E113="Piping"),"",IF(E113="Exchanger",AQ113*AR113+IF(P113="",0,IF(P113="Conical",PI()/12*(SQRT(4*AQ113/PI()))^2*(0),INDEX(HeadK,MATCH(P113,HeadU,0))*(SQRT(4*AQ113/PI()))^3))-IF(AND(ISNUMBER(S113),ISNUMBER(V113)),S113*PI()/4*AP113^2*V113*INDEX(LenF,MATCH($V$7,LenU,0)),0),IF(ISNUMBER(N113),PI()/4*(N113*INDEX(LenF,MATCH($N$7,LenU,0)))^2*N(O113)*INDEX(LenF,MATCH($O$7,LenU,0))+IF(P113="",0,IF(P113="Conical",PI()/12*(N113*INDEX(LenF,MATCH($N$7,LenU,0)))^2*(N(R113)*INDEX(LenF,MATCH($R$7,LenU,0))),INDEX(HeadK,MATCH(P113,HeadU,0))*(N113*INDEX(LenF,MATCH($N$7,LenU,0)))^3))+IF(Q113="",0,IF(Q113="Conical",PI()/12*(N113*INDEX(LenF,MATCH($N$7,LenU,0)))^2*(N(R113)*INDEX(LenF,MATCH($R$7,LenU,0))),INDEX(HeadK,MATCH(Q113,HeadU,0))*(N113*INDEX(LenF,MATCH($N$7,LenU,0)))^3)),0))) | AF113: =IF(E113<>"Piping","",IF(AND(ISNUMBER(AS113),ISNUMBER(M113)),PI()/4*(AS113/1000)^2*M113*INDEX(LenF,MATCH($M$7,LenU,0)),0)) | AG113: =IF(E113="","",N(AD113)+N(AE113)+N(AF113)) | AH113: =IF(ISNUMBER(I113),I113*INDEX(WtF,MATCH($I$7,WtU,0))/CC_WaterRho,"") | AM113: =IF(AO113="","",AO113*IF(ISNUMBER(AK113),AK113,CC_DefFills)*(1+IF(ISNUMBER(AL113),AL113,CC_DefAllow))) | AN113: =IF(G113="Given volume",IF(ISNUMBER(H113),H113*INDEX(VolF,MATCH($H$7,VolU,0)),""),IF(G113="Water weight",AH113,IF(N(AG113)=0,"",AG113))) | AO113: =IF(N(AN113)=0,"",AN113*AT113*IF(ISNUMBER(AJ113),AJ113,CC_DefCirc)) | AP113: =IF(ISNUMBER(T113),T113*INDEX(LenF,MATCH($T$7,LenU,0)),IF(ISNUMBER(W113),W113*INDEX(LenF,MATCH($W$7,LenU,0))/CC_PitchRatio,0)) -> 0 | AQ113: =IF(ISNUMBER(N113),PI()/4*(N113*INDEX(LenF,MATCH($N$7,LenU,0)))^2,IF(AND(ISNUMBER(S113),ISNUMBER(W113),X113<>""),S113*(W113*INDEX(LenF,MATCH($W$7,LenU,0)))^2*INDEX(LayoutF,MATCH(X113,LayoutU,0)),0)) -> 0 | AR113: =IF(ISNUMBER(O113),O113*INDEX(LenF,MATCH($O$7,LenU,0)),IF(ISNUMBER(V113),V113*INDEX(LenF,MATCH($V$7,LenU,0)),0)) -> 0 | AS113: =IF(ISNUMBER(L113),L113*INDEX(LenF,MATCH($L$7,LenU,0))*1000,IF(OR(J113="",K113=""),"",IFERROR(IF(INDEX(PipeWT,MATCH(J113,NPSU,0),MATCH(K113,SchU,0))="","Sch n/a",INDEX(PipeOD,MATCH(J113,NPSU,0))-2*INDEX(PipeWT,MATCH(J113,NPSU,0),MATCH(K113,SchU,0))),""))) | AT113: =IF(ISNUMBER(AI113),AI113,IFERROR(INDEX(IF(CC_JobType="Decontamination",CC_TypeFillDC,CC_TypeFillCC),MATCH(E113,CC_TypeL,0)),1)) -> 1 | AU113: 4
A114: 6 | AD114: =IF(E114="Exchanger",IF(AND(ISNUMBER(S114),ISNUMBER(U114),ISNUMBER(V114)),S114*PI()/4*(U114*INDEX(LenF,MATCH($U$7,LenU,0)))^2*V114*INDEX(LenF,MATCH($V$7,LenU,0)),0)+IF(ISNUMBER(Y114),PI()/4*(Y114*INDEX(LenF,MATCH($Y$7,LenU,0)))^2*N(Z114)*INDEX(LenF,MATCH($Z$7,LenU,0))+IF(AA114="",0,IF(AA114="Conical",PI()/12*(Y114*INDEX(LenF,MATCH($Y$7,LenU,0)))^2*(0),INDEX(HeadK,MATCH(AA114,HeadU,0))*(Y114*INDEX(LenF,MATCH($Y$7,LenU,0)))^3)),0)+IF(ISNUMBER(Y114),PI()/4*(Y114*INDEX(LenF,MATCH($Y$7,LenU,0)))^2*N(AB114)*INDEX(LenF,MATCH($AB$7,LenU,0))+IF(AC114="",0,IF(AC114="Conical",PI()/12*(Y114*INDEX(LenF,MATCH($Y$7,LenU,0)))^2*(0),INDEX(HeadK,MATCH(AC114,HeadU,0))*(Y114*INDEX(LenF,MATCH($Y$7,LenU,0)))^3)),0),"") | AE114: =IF(OR(E114="",E114="Piping"),"",IF(E114="Exchanger",AQ114*AR114+IF(P114="",0,IF(P114="Conical",PI()/12*(SQRT(4*AQ114/PI()))^2*(0),INDEX(HeadK,MATCH(P114,HeadU,0))*(SQRT(4*AQ114/PI()))^3))-IF(AND(ISNUMBER(S114),ISNUMBER(V114)),S114*PI()/4*AP114^2*V114*INDEX(LenF,MATCH($V$7,LenU,0)),0),IF(ISNUMBER(N114),PI()/4*(N114*INDEX(LenF,MATCH($N$7,LenU,0)))^2*N(O114)*INDEX(LenF,MATCH($O$7,LenU,0))+IF(P114="",0,IF(P114="Conical",PI()/12*(N114*INDEX(LenF,MATCH($N$7,LenU,0)))^2*(N(R114)*INDEX(LenF,MATCH($R$7,LenU,0))),INDEX(HeadK,MATCH(P114,HeadU,0))*(N114*INDEX(LenF,MATCH($N$7,LenU,0)))^3))+IF(Q114="",0,IF(Q114="Conical",PI()/12*(N114*INDEX(LenF,MATCH($N$7,LenU,0)))^2*(N(R114)*INDEX(LenF,MATCH($R$7,LenU,0))),INDEX(HeadK,MATCH(Q114,HeadU,0))*(N114*INDEX(LenF,MATCH($N$7,LenU,0)))^3)),0))) | AF114: =IF(E114<>"Piping","",IF(AND(ISNUMBER(AS114),ISNUMBER(M114)),PI()/4*(AS114/1000)^2*M114*INDEX(LenF,MATCH($M$7,LenU,0)),0)) | AG114: =IF(E114="","",N(AD114)+N(AE114)+N(AF114)) | AH114: =IF(ISNUMBER(I114),I114*INDEX(WtF,MATCH($I$7,WtU,0))/CC_WaterRho,"") | AM114: =IF(AO114="","",AO114*IF(ISNUMBER(AK114),AK114,CC_DefFills)*(1+IF(ISNUMBER(AL114),AL114,CC_DefAllow))) | AN114: =IF(G114="Given volume",IF(ISNUMBER(H114),H114*INDEX(VolF,MATCH($H$7,VolU,0)),""),IF(G114="Water weight",AH114,IF(N(AG114)=0,"",AG114))) | AO114: =IF(N(AN114)=0,"",AN114*AT114*IF(ISNUMBER(AJ114),AJ114,CC_DefCirc)) | AP114: =IF(ISNUMBER(T114),T114*INDEX(LenF,MATCH($T$7,LenU,0)),IF(ISNUMBER(W114),W114*INDEX(LenF,MATCH($W$7,LenU,0))/CC_PitchRatio,0)) -> 0 | AQ114: =IF(ISNUMBER(N114),PI()/4*(N114*INDEX(LenF,MATCH($N$7,LenU,0)))^2,IF(AND(ISNUMBER(S114),ISNUMBER(W114),X114<>""),S114*(W114*INDEX(LenF,MATCH($W$7,LenU,0)))^2*INDEX(LayoutF,MATCH(X114,LayoutU,0)),0)) -> 0 | AR114: =IF(ISNUMBER(O114),O114*INDEX(LenF,MATCH($O$7,LenU,0)),IF(ISNUMBER(V114),V114*INDEX(LenF,MATCH($V$7,LenU,0)),0)) -> 0 | AS114: =IF(ISNUMBER(L114),L114*INDEX(LenF,MATCH($L$7,LenU,0))*1000,IF(OR(J114="",K114=""),"",IFERROR(IF(INDEX(PipeWT,MATCH(J114,NPSU,0),MATCH(K114,SchU,0))="","Sch n/a",INDEX(PipeOD,MATCH(J114,NPSU,0))-2*INDEX(PipeWT,MATCH(J114,NPSU,0),MATCH(K114,SchU,0))),""))) | AT114: =IF(ISNUMBER(AI114),AI114,IFERROR(INDEX(IF(CC_JobType="Decontamination",CC_TypeFillDC,CC_TypeFillCC),MATCH(E114,CC_TypeL,0)),1)) -> 1 | AU114: 4
A115: 7 | AD115: =IF(E115="Exchanger",IF(AND(ISNUMBER(S115),ISNUMBER(U115),ISNUMBER(V115)),S115*PI()/4*(U115*INDEX(LenF,MATCH($U$7,LenU,0)))^2*V115*INDEX(LenF,MATCH($V$7,LenU,0)),0)+IF(ISNUMBER(Y115),PI()/4*(Y115*INDEX(LenF,MATCH($Y$7,LenU,0)))^2*N(Z115)*INDEX(LenF,MATCH($Z$7,LenU,0))+IF(AA115="",0,IF(AA115="Conical",PI()/12*(Y115*INDEX(LenF,MATCH($Y$7,LenU,0)))^2*(0),INDEX(HeadK,MATCH(AA115,HeadU,0))*(Y115*INDEX(LenF,MATCH($Y$7,LenU,0)))^3)),0)+IF(ISNUMBER(Y115),PI()/4*(Y115*INDEX(LenF,MATCH($Y$7,LenU,0)))^2*N(AB115)*INDEX(LenF,MATCH($AB$7,LenU,0))+IF(AC115="",0,IF(AC115="Conical",PI()/12*(Y115*INDEX(LenF,MATCH($Y$7,LenU,0)))^2*(0),INDEX(HeadK,MATCH(AC115,HeadU,0))*(Y115*INDEX(LenF,MATCH($Y$7,LenU,0)))^3)),0),"") | AE115: =IF(OR(E115="",E115="Piping"),"",IF(E115="Exchanger",AQ115*AR115+IF(P115="",0,IF(P115="Conical",PI()/12*(SQRT(4*AQ115/PI()))^2*(0),INDEX(HeadK,MATCH(P115,HeadU,0))*(SQRT(4*AQ115/PI()))^3))-IF(AND(ISNUMBER(S115),ISNUMBER(V115)),S115*PI()/4*AP115^2*V115*INDEX(LenF,MATCH($V$7,LenU,0)),0),IF(ISNUMBER(N115),PI()/4*(N115*INDEX(LenF,MATCH($N$7,LenU,0)))^2*N(O115)*INDEX(LenF,MATCH($O$7,LenU,0))+IF(P115="",0,IF(P115="Conical",PI()/12*(N115*INDEX(LenF,MATCH($N$7,LenU,0)))^2*(N(R115)*INDEX(LenF,MATCH($R$7,LenU,0))),INDEX(HeadK,MATCH(P115,HeadU,0))*(N115*INDEX(LenF,MATCH($N$7,LenU,0)))^3))+IF(Q115="",0,IF(Q115="Conical",PI()/12*(N115*INDEX(LenF,MATCH($N$7,LenU,0)))^2*(N(R115)*INDEX(LenF,MATCH($R$7,LenU,0))),INDEX(HeadK,MATCH(Q115,HeadU,0))*(N115*INDEX(LenF,MATCH($N$7,LenU,0)))^3)),0))) | AF115: =IF(E115<>"Piping","",IF(AND(ISNUMBER(AS115),ISNUMBER(M115)),PI()/4*(AS115/1000)^2*M115*INDEX(LenF,MATCH($M$7,LenU,0)),0)) | AG115: =IF(E115="","",N(AD115)+N(AE115)+N(AF115)) | AH115: =IF(ISNUMBER(I115),I115*INDEX(WtF,MATCH($I$7,WtU,0))/CC_WaterRho,"") | AM115: =IF(AO115="","",AO115*IF(ISNUMBER(AK115),AK115,CC_DefFills)*(1+IF(ISNUMBER(AL115),AL115,CC_DefAllow))) | AN115: =IF(G115="Given volume",IF(ISNUMBER(H115),H115*INDEX(VolF,MATCH($H$7,VolU,0)),""),IF(G115="Water weight",AH115,IF(N(AG115)=0,"",AG115))) | AO115: =IF(N(AN115)=0,"",AN115*AT115*IF(ISNUMBER(AJ115),AJ115,CC_DefCirc)) | AP115: =IF(ISNUMBER(T115),T115*INDEX(LenF,MATCH($T$7,LenU,0)),IF(ISNUMBER(W115),W115*INDEX(LenF,MATCH($W$7,LenU,0))/CC_PitchRatio,0)) -> 0 | AQ115: =IF(ISNUMBER(N115),PI()/4*(N115*INDEX(LenF,MATCH($N$7,LenU,0)))^2,IF(AND(ISNUMBER(S115),ISNUMBER(W115),X115<>""),S115*(W115*INDEX(LenF,MATCH($W$7,LenU,0)))^2*INDEX(LayoutF,MATCH(X115,LayoutU,0)),0)) -> 0 | AR115: =IF(ISNUMBER(O115),O115*INDEX(LenF,MATCH($O$7,LenU,0)),IF(ISNUMBER(V115),V115*INDEX(LenF,MATCH($V$7,LenU,0)),0)) -> 0 | AS115: =IF(ISNUMBER(L115),L115*INDEX(LenF,MATCH($L$7,LenU,0))*1000,IF(OR(J115="",K115=""),"",IFERROR(IF(INDEX(PipeWT,MATCH(J115,NPSU,0),MATCH(K115,SchU,0))="","Sch n/a",INDEX(PipeOD,MATCH(J115,NPSU,0))-2*INDEX(PipeWT,MATCH(J115,NPSU,0),MATCH(K115,SchU,0))),""))) | AT115: =IF(ISNUMBER(AI115),AI115,IFERROR(INDEX(IF(CC_JobType="Decontamination",CC_TypeFillDC,CC_TypeFillCC),MATCH(E115,CC_TypeL,0)),1)) -> 1 | AU115: 4
A116: 8 | AD116: =IF(E116="Exchanger",IF(AND(ISNUMBER(S116),ISNUMBER(U116),ISNUMBER(V116)),S116*PI()/4*(U116*INDEX(LenF,MATCH($U$7,LenU,0)))^2*V116*INDEX(LenF,MATCH($V$7,LenU,0)),0)+IF(ISNUMBER(Y116),PI()/4*(Y116*INDEX(LenF,MATCH($Y$7,LenU,0)))^2*N(Z116)*INDEX(LenF,MATCH($Z$7,LenU,0))+IF(AA116="",0,IF(AA116="Conical",PI()/12*(Y116*INDEX(LenF,MATCH($Y$7,LenU,0)))^2*(0),INDEX(HeadK,MATCH(AA116,HeadU,0))*(Y116*INDEX(LenF,MATCH($Y$7,LenU,0)))^3)),0)+IF(ISNUMBER(Y116),PI()/4*(Y116*INDEX(LenF,MATCH($Y$7,LenU,0)))^2*N(AB116)*INDEX(LenF,MATCH($AB$7,LenU,0))+IF(AC116="",0,IF(AC116="Conical",PI()/12*(Y116*INDEX(LenF,MATCH($Y$7,LenU,0)))^2*(0),INDEX(HeadK,MATCH(AC116,HeadU,0))*(Y116*INDEX(LenF,MATCH($Y$7,LenU,0)))^3)),0),"") | AE116: =IF(OR(E116="",E116="Piping"),"",IF(E116="Exchanger",AQ116*AR116+IF(P116="",0,IF(P116="Conical",PI()/12*(SQRT(4*AQ116/PI()))^2*(0),INDEX(HeadK,MATCH(P116,HeadU,0))*(SQRT(4*AQ116/PI()))^3))-IF(AND(ISNUMBER(S116),ISNUMBER(V116)),S116*PI()/4*AP116^2*V116*INDEX(LenF,MATCH($V$7,LenU,0)),0),IF(ISNUMBER(N116),PI()/4*(N116*INDEX(LenF,MATCH($N$7,LenU,0)))^2*N(O116)*INDEX(LenF,MATCH($O$7,LenU,0))+IF(P116="",0,IF(P116="Conical",PI()/12*(N116*INDEX(LenF,MATCH($N$7,LenU,0)))^2*(N(R116)*INDEX(LenF,MATCH($R$7,LenU,0))),INDEX(HeadK,MATCH(P116,HeadU,0))*(N116*INDEX(LenF,MATCH($N$7,LenU,0)))^3))+IF(Q116="",0,IF(Q116="Conical",PI()/12*(N116*INDEX(LenF,MATCH($N$7,LenU,0)))^2*(N(R116)*INDEX(LenF,MATCH($R$7,LenU,0))),INDEX(HeadK,MATCH(Q116,HeadU,0))*(N116*INDEX(LenF,MATCH($N$7,LenU,0)))^3)),0))) | AF116: =IF(E116<>"Piping","",IF(AND(ISNUMBER(AS116),ISNUMBER(M116)),PI()/4*(AS116/1000)^2*M116*INDEX(LenF,MATCH($M$7,LenU,0)),0)) | AG116: =IF(E116="","",N(AD116)+N(AE116)+N(AF116)) | AH116: =IF(ISNUMBER(I116),I116*INDEX(WtF,MATCH($I$7,WtU,0))/CC_WaterRho,"") | AM116: =IF(AO116="","",AO116*IF(ISNUMBER(AK116),AK116,CC_DefFills)*(1+IF(ISNUMBER(AL116),AL116,CC_DefAllow))) | AN116: =IF(G116="Given volume",IF(ISNUMBER(H116),H116*INDEX(VolF,MATCH($H$7,VolU,0)),""),IF(G116="Water weight",AH116,IF(N(AG116)=0,"",AG116))) | AO116: =IF(N(AN116)=0,"",AN116*AT116*IF(ISNUMBER(AJ116),AJ116,CC_DefCirc)) | AP116: =IF(ISNUMBER(T116),T116*INDEX(LenF,MATCH($T$7,LenU,0)),IF(ISNUMBER(W116),W116*INDEX(LenF,MATCH($W$7,LenU,0))/CC_PitchRatio,0)) -> 0 | AQ116: =IF(ISNUMBER(N116),PI()/4*(N116*INDEX(LenF,MATCH($N$7,LenU,0)))^2,IF(AND(ISNUMBER(S116),ISNUMBER(W116),X116<>""),S116*(W116*INDEX(LenF,MATCH($W$7,LenU,0)))^2*INDEX(LayoutF,MATCH(X116,LayoutU,0)),0)) -> 0 | AR116: =IF(ISNUMBER(O116),O116*INDEX(LenF,MATCH($O$7,LenU,0)),IF(ISNUMBER(V116),V116*INDEX(LenF,MATCH($V$7,LenU,0)),0)) -> 0 | AS116: =IF(ISNUMBER(L116),L116*INDEX(LenF,MATCH($L$7,LenU,0))*1000,IF(OR(J116="",K116=""),"",IFERROR(IF(INDEX(PipeWT,MATCH(J116,NPSU,0),MATCH(K116,SchU,0))="","Sch n/a",INDEX(PipeOD,MATCH(J116,NPSU,0))-2*INDEX(PipeWT,MATCH(J116,NPSU,0),MATCH(K116,SchU,0))),""))) | AT116: =IF(ISNUMBER(AI116),AI116,IFERROR(INDEX(IF(CC_JobType="Decontamination",CC_TypeFillDC,CC_TypeFillCC),MATCH(E116,CC_TypeL,0)),1)) -> 1 | AU116: 4
A117: 9 | AD117: =IF(E117="Exchanger",IF(AND(ISNUMBER(S117),ISNUMBER(U117),ISNUMBER(V117)),S117*PI()/4*(U117*INDEX(LenF,MATCH($U$7,LenU,0)))^2*V117*INDEX(LenF,MATCH($V$7,LenU,0)),0)+IF(ISNUMBER(Y117),PI()/4*(Y117*INDEX(LenF,MATCH($Y$7,LenU,0)))^2*N(Z117)*INDEX(LenF,MATCH($Z$7,LenU,0))+IF(AA117="",0,IF(AA117="Conical",PI()/12*(Y117*INDEX(LenF,MATCH($Y$7,LenU,0)))^2*(0),INDEX(HeadK,MATCH(AA117,HeadU,0))*(Y117*INDEX(LenF,MATCH($Y$7,LenU,0)))^3)),0)+IF(ISNUMBER(Y117),PI()/4*(Y117*INDEX(LenF,MATCH($Y$7,LenU,0)))^2*N(AB117)*INDEX(LenF,MATCH($AB$7,LenU,0))+IF(AC117="",0,IF(AC117="Conical",PI()/12*(Y117*INDEX(LenF,MATCH($Y$7,LenU,0)))^2*(0),INDEX(HeadK,MATCH(AC117,HeadU,0))*(Y117*INDEX(LenF,MATCH($Y$7,LenU,0)))^3)),0),"") | AE117: =IF(OR(E117="",E117="Piping"),"",IF(E117="Exchanger",AQ117*AR117+IF(P117="",0,IF(P117="Conical",PI()/12*(SQRT(4*AQ117/PI()))^2*(0),INDEX(HeadK,MATCH(P117,HeadU,0))*(SQRT(4*AQ117/PI()))^3))-IF(AND(ISNUMBER(S117),ISNUMBER(V117)),S117*PI()/4*AP117^2*V117*INDEX(LenF,MATCH($V$7,LenU,0)),0),IF(ISNUMBER(N117),PI()/4*(N117*INDEX(LenF,MATCH($N$7,LenU,0)))^2*N(O117)*INDEX(LenF,MATCH($O$7,LenU,0))+IF(P117="",0,IF(P117="Conical",PI()/12*(N117*INDEX(LenF,MATCH($N$7,LenU,0)))^2*(N(R117)*INDEX(LenF,MATCH($R$7,LenU,0))),INDEX(HeadK,MATCH(P117,HeadU,0))*(N117*INDEX(LenF,MATCH($N$7,LenU,0)))^3))+IF(Q117="",0,IF(Q117="Conical",PI()/12*(N117*INDEX(LenF,MATCH($N$7,LenU,0)))^2*(N(R117)*INDEX(LenF,MATCH($R$7,LenU,0))),INDEX(HeadK,MATCH(Q117,HeadU,0))*(N117*INDEX(LenF,MATCH($N$7,LenU,0)))^3)),0))) | AF117: =IF(E117<>"Piping","",IF(AND(ISNUMBER(AS117),ISNUMBER(M117)),PI()/4*(AS117/1000)^2*M117*INDEX(LenF,MATCH($M$7,LenU,0)),0)) | AG117: =IF(E117="","",N(AD117)+N(AE117)+N(AF117)) | AH117: =IF(ISNUMBER(I117),I117*INDEX(WtF,MATCH($I$7,WtU,0))/CC_WaterRho,"") | AM117: =IF(AO117="","",AO117*IF(ISNUMBER(AK117),AK117,CC_DefFills)*(1+IF(ISNUMBER(AL117),AL117,CC_DefAllow))) | AN117: =IF(G117="Given volume",IF(ISNUMBER(H117),H117*INDEX(VolF,MATCH($H$7,VolU,0)),""),IF(G117="Water weight",AH117,IF(N(AG117)=0,"",AG117))) | AO117: =IF(N(AN117)=0,"",AN117*AT117*IF(ISNUMBER(AJ117),AJ117,CC_DefCirc)) | AP117: =IF(ISNUMBER(T117),T117*INDEX(LenF,MATCH($T$7,LenU,0)),IF(ISNUMBER(W117),W117*INDEX(LenF,MATCH($W$7,LenU,0))/CC_PitchRatio,0)) -> 0 | AQ117: =IF(ISNUMBER(N117),PI()/4*(N117*INDEX(LenF,MATCH($N$7,LenU,0)))^2,IF(AND(ISNUMBER(S117),ISNUMBER(W117),X117<>""),S117*(W117*INDEX(LenF,MATCH($W$7,LenU,0)))^2*INDEX(LayoutF,MATCH(X117,LayoutU,0)),0)) -> 0 | AR117: =IF(ISNUMBER(O117),O117*INDEX(LenF,MATCH($O$7,LenU,0)),IF(ISNUMBER(V117),V117*INDEX(LenF,MATCH($V$7,LenU,0)),0)) -> 0 | AS117: =IF(ISNUMBER(L117),L117*INDEX(LenF,MATCH($L$7,LenU,0))*1000,IF(OR(J117="",K117=""),"",IFERROR(IF(INDEX(PipeWT,MATCH(J117,NPSU,0),MATCH(K117,SchU,0))="","Sch n/a",INDEX(PipeOD,MATCH(J117,NPSU,0))-2*INDEX(PipeWT,MATCH(J117,NPSU,0),MATCH(K117,SchU,0))),""))) | AT117: =IF(ISNUMBER(AI117),AI117,IFERROR(INDEX(IF(CC_JobType="Decontamination",CC_TypeFillDC,CC_TypeFillCC),MATCH(E117,CC_TypeL,0)),1)) -> 1 | AU117: 4
A118: 10 | AD118: =IF(E118="Exchanger",IF(AND(ISNUMBER(S118),ISNUMBER(U118),ISNUMBER(V118)),S118*PI()/4*(U118*INDEX(LenF,MATCH($U$7,LenU,0)))^2*V118*INDEX(LenF,MATCH($V$7,LenU,0)),0)+IF(ISNUMBER(Y118),PI()/4*(Y118*INDEX(LenF,MATCH($Y$7,LenU,0)))^2*N(Z118)*INDEX(LenF,MATCH($Z$7,LenU,0))+IF(AA118="",0,IF(AA118="Conical",PI()/12*(Y118*INDEX(LenF,MATCH($Y$7,LenU,0)))^2*(0),INDEX(HeadK,MATCH(AA118,HeadU,0))*(Y118*INDEX(LenF,MATCH($Y$7,LenU,0)))^3)),0)+IF(ISNUMBER(Y118),PI()/4*(Y118*INDEX(LenF,MATCH($Y$7,LenU,0)))^2*N(AB118)*INDEX(LenF,MATCH($AB$7,LenU,0))+IF(AC118="",0,IF(AC118="Conical",PI()/12*(Y118*INDEX(LenF,MATCH($Y$7,LenU,0)))^2*(0),INDEX(HeadK,MATCH(AC118,HeadU,0))*(Y118*INDEX(LenF,MATCH($Y$7,LenU,0)))^3)),0),"") | AE118: =IF(OR(E118="",E118="Piping"),"",IF(E118="Exchanger",AQ118*AR118+IF(P118="",0,IF(P118="Conical",PI()/12*(SQRT(4*AQ118/PI()))^2*(0),INDEX(HeadK,MATCH(P118,HeadU,0))*(SQRT(4*AQ118/PI()))^3))-IF(AND(ISNUMBER(S118),ISNUMBER(V118)),S118*PI()/4*AP118^2*V118*INDEX(LenF,MATCH($V$7,LenU,0)),0),IF(ISNUMBER(N118),PI()/4*(N118*INDEX(LenF,MATCH($N$7,LenU,0)))^2*N(O118)*INDEX(LenF,MATCH($O$7,LenU,0))+IF(P118="",0,IF(P118="Conical",PI()/12*(N118*INDEX(LenF,MATCH($N$7,LenU,0)))^2*(N(R118)*INDEX(LenF,MATCH($R$7,LenU,0))),INDEX(HeadK,MATCH(P118,HeadU,0))*(N118*INDEX(LenF,MATCH($N$7,LenU,0)))^3))+IF(Q118="",0,IF(Q118="Conical",PI()/12*(N118*INDEX(LenF,MATCH($N$7,LenU,0)))^2*(N(R118)*INDEX(LenF,MATCH($R$7,LenU,0))),INDEX(HeadK,MATCH(Q118,HeadU,0))*(N118*INDEX(LenF,MATCH($N$7,LenU,0)))^3)),0))) | AF118: =IF(E118<>"Piping","",IF(AND(ISNUMBER(AS118),ISNUMBER(M118)),PI()/4*(AS118/1000)^2*M118*INDEX(LenF,MATCH($M$7,LenU,0)),0)) | AG118: =IF(E118="","",N(AD118)+N(AE118)+N(AF118)) | AH118: =IF(ISNUMBER(I118),I118*INDEX(WtF,MATCH($I$7,WtU,0))/CC_WaterRho,"") | AM118: =IF(AO118="","",AO118*IF(ISNUMBER(AK118),AK118,CC_DefFills)*(1+IF(ISNUMBER(AL118),AL118,CC_DefAllow))) | AN118: =IF(G118="Given volume",IF(ISNUMBER(H118),H118*INDEX(VolF,MATCH($H$7,VolU,0)),""),IF(G118="Water weight",AH118,IF(N(AG118)=0,"",AG118))) | AO118: =IF(N(AN118)=0,"",AN118*AT118*IF(ISNUMBER(AJ118),AJ118,CC_DefCirc)) | AP118: =IF(ISNUMBER(T118),T118*INDEX(LenF,MATCH($T$7,LenU,0)),IF(ISNUMBER(W118),W118*INDEX(LenF,MATCH($W$7,LenU,0))/CC_PitchRatio,0)) -> 0 | AQ118: =IF(ISNUMBER(N118),PI()/4*(N118*INDEX(LenF,MATCH($N$7,LenU,0)))^2,IF(AND(ISNUMBER(S118),ISNUMBER(W118),X118<>""),S118*(W118*INDEX(LenF,MATCH($W$7,LenU,0)))^2*INDEX(LayoutF,MATCH(X118,LayoutU,0)),0)) -> 0 | AR118: =IF(ISNUMBER(O118),O118*INDEX(LenF,MATCH($O$7,LenU,0)),IF(ISNUMBER(V118),V118*INDEX(LenF,MATCH($V$7,LenU,0)),0)) -> 0 | AS118: =IF(ISNUMBER(L118),L118*INDEX(LenF,MATCH($L$7,LenU,0))*1000,IF(OR(J118="",K118=""),"",IFERROR(IF(INDEX(PipeWT,MATCH(J118,NPSU,0),MATCH(K118,SchU,0))="","Sch n/a",INDEX(PipeOD,MATCH(J118,NPSU,0))-2*INDEX(PipeWT,MATCH(J118,NPSU,0),MATCH(K118,SchU,0))),""))) | AT118: =IF(ISNUMBER(AI118),AI118,IFERROR(INDEX(IF(CC_JobType="Decontamination",CC_TypeFillDC,CC_TypeFillCC),MATCH(E118,CC_TypeL,0)),1)) -> 1 | AU118: 4
A119: 11 | AD119: =IF(E119="Exchanger",IF(AND(ISNUMBER(S119),ISNUMBER(U119),ISNUMBER(V119)),S119*PI()/4*(U119*INDEX(LenF,MATCH($U$7,LenU,0)))^2*V119*INDEX(LenF,MATCH($V$7,LenU,0)),0)+IF(ISNUMBER(Y119),PI()/4*(Y119*INDEX(LenF,MATCH($Y$7,LenU,0)))^2*N(Z119)*INDEX(LenF,MATCH($Z$7,LenU,0))+IF(AA119="",0,IF(AA119="Conical",PI()/12*(Y119*INDEX(LenF,MATCH($Y$7,LenU,0)))^2*(0),INDEX(HeadK,MATCH(AA119,HeadU,0))*(Y119*INDEX(LenF,MATCH($Y$7,LenU,0)))^3)),0)+IF(ISNUMBER(Y119),PI()/4*(Y119*INDEX(LenF,MATCH($Y$7,LenU,0)))^2*N(AB119)*INDEX(LenF,MATCH($AB$7,LenU,0))+IF(AC119="",0,IF(AC119="Conical",PI()/12*(Y119*INDEX(LenF,MATCH($Y$7,LenU,0)))^2*(0),INDEX(HeadK,MATCH(AC119,HeadU,0))*(Y119*INDEX(LenF,MATCH($Y$7,LenU,0)))^3)),0),"") | AE119: =IF(OR(E119="",E119="Piping"),"",IF(E119="Exchanger",AQ119*AR119+IF(P119="",0,IF(P119="Conical",PI()/12*(SQRT(4*AQ119/PI()))^2*(0),INDEX(HeadK,MATCH(P119,HeadU,0))*(SQRT(4*AQ119/PI()))^3))-IF(AND(ISNUMBER(S119),ISNUMBER(V119)),S119*PI()/4*AP119^2*V119*INDEX(LenF,MATCH($V$7,LenU,0)),0),IF(ISNUMBER(N119),PI()/4*(N119*INDEX(LenF,MATCH($N$7,LenU,0)))^2*N(O119)*INDEX(LenF,MATCH($O$7,LenU,0))+IF(P119="",0,IF(P119="Conical",PI()/12*(N119*INDEX(LenF,MATCH($N$7,LenU,0)))^2*(N(R119)*INDEX(LenF,MATCH($R$7,LenU,0))),INDEX(HeadK,MATCH(P119,HeadU,0))*(N119*INDEX(LenF,MATCH($N$7,LenU,0)))^3))+IF(Q119="",0,IF(Q119="Conical",PI()/12*(N119*INDEX(LenF,MATCH($N$7,LenU,0)))^2*(N(R119)*INDEX(LenF,MATCH($R$7,LenU,0))),INDEX(HeadK,MATCH(Q119,HeadU,0))*(N119*INDEX(LenF,MATCH($N$7,LenU,0)))^3)),0))) | AF119: =IF(E119<>"Piping","",IF(AND(ISNUMBER(AS119),ISNUMBER(M119)),PI()/4*(AS119/1000)^2*M119*INDEX(LenF,MATCH($M$7,LenU,0)),0)) | AG119: =IF(E119="","",N(AD119)+N(AE119)+N(AF119)) | AH119: =IF(ISNUMBER(I119),I119*INDEX(WtF,MATCH($I$7,WtU,0))/CC_WaterRho,"") | AM119: =IF(AO119="","",AO119*IF(ISNUMBER(AK119),AK119,CC_DefFills)*(1+IF(ISNUMBER(AL119),AL119,CC_DefAllow))) | AN119: =IF(G119="Given volume",IF(ISNUMBER(H119),H119*INDEX(VolF,MATCH($H$7,VolU,0)),""),IF(G119="Water weight",AH119,IF(N(AG119)=0,"",AG119))) | AO119: =IF(N(AN119)=0,"",AN119*AT119*IF(ISNUMBER(AJ119),AJ119,CC_DefCirc)) | AP119: =IF(ISNUMBER(T119),T119*INDEX(LenF,MATCH($T$7,LenU,0)),IF(ISNUMBER(W119),W119*INDEX(LenF,MATCH($W$7,LenU,0))/CC_PitchRatio,0)) -> 0 | AQ119: =IF(ISNUMBER(N119),PI()/4*(N119*INDEX(LenF,MATCH($N$7,LenU,0)))^2,IF(AND(ISNUMBER(S119),ISNUMBER(W119),X119<>""),S119*(W119*INDEX(LenF,MATCH($W$7,LenU,0)))^2*INDEX(LayoutF,MATCH(X119,LayoutU,0)),0)) -> 0 | AR119: =IF(ISNUMBER(O119),O119*INDEX(LenF,MATCH($O$7,LenU,0)),IF(ISNUMBER(V119),V119*INDEX(LenF,MATCH($V$7,LenU,0)),0)) -> 0 | AS119: =IF(ISNUMBER(L119),L119*INDEX(LenF,MATCH($L$7,LenU,0))*1000,IF(OR(J119="",K119=""),"",IFERROR(IF(INDEX(PipeWT,MATCH(J119,NPSU,0),MATCH(K119,SchU,0))="","Sch n/a",INDEX(PipeOD,MATCH(J119,NPSU,0))-2*INDEX(PipeWT,MATCH(J119,NPSU,0),MATCH(K119,SchU,0))),""))) | AT119: =IF(ISNUMBER(AI119),AI119,IFERROR(INDEX(IF(CC_JobType="Decontamination",CC_TypeFillDC,CC_TypeFillCC),MATCH(E119,CC_TypeL,0)),1)) -> 1 | AU119: 4
A120: 12 | AD120: =IF(E120="Exchanger",IF(AND(ISNUMBER(S120),ISNUMBER(U120),ISNUMBER(V120)),S120*PI()/4*(U120*INDEX(LenF,MATCH($U$7,LenU,0)))^2*V120*INDEX(LenF,MATCH($V$7,LenU,0)),0)+IF(ISNUMBER(Y120),PI()/4*(Y120*INDEX(LenF,MATCH($Y$7,LenU,0)))^2*N(Z120)*INDEX(LenF,MATCH($Z$7,LenU,0))+IF(AA120="",0,IF(AA120="Conical",PI()/12*(Y120*INDEX(LenF,MATCH($Y$7,LenU,0)))^2*(0),INDEX(HeadK,MATCH(AA120,HeadU,0))*(Y120*INDEX(LenF,MATCH($Y$7,LenU,0)))^3)),0)+IF(ISNUMBER(Y120),PI()/4*(Y120*INDEX(LenF,MATCH($Y$7,LenU,0)))^2*N(AB120)*INDEX(LenF,MATCH($AB$7,LenU,0))+IF(AC120="",0,IF(AC120="Conical",PI()/12*(Y120*INDEX(LenF,MATCH($Y$7,LenU,0)))^2*(0),INDEX(HeadK,MATCH(AC120,HeadU,0))*(Y120*INDEX(LenF,MATCH($Y$7,LenU,0)))^3)),0),"") | AE120: =IF(OR(E120="",E120="Piping"),"",IF(E120="Exchanger",AQ120*AR120+IF(P120="",0,IF(P120="Conical",PI()/12*(SQRT(4*AQ120/PI()))^2*(0),INDEX(HeadK,MATCH(P120,HeadU,0))*(SQRT(4*AQ120/PI()))^3))-IF(AND(ISNUMBER(S120),ISNUMBER(V120)),S120*PI()/4*AP120^2*V120*INDEX(LenF,MATCH($V$7,LenU,0)),0),IF(ISNUMBER(N120),PI()/4*(N120*INDEX(LenF,MATCH($N$7,LenU,0)))^2*N(O120)*INDEX(LenF,MATCH($O$7,LenU,0))+IF(P120="",0,IF(P120="Conical",PI()/12*(N120*INDEX(LenF,MATCH($N$7,LenU,0)))^2*(N(R120)*INDEX(LenF,MATCH($R$7,LenU,0))),INDEX(HeadK,MATCH(P120,HeadU,0))*(N120*INDEX(LenF,MATCH($N$7,LenU,0)))^3))+IF(Q120="",0,IF(Q120="Conical",PI()/12*(N120*INDEX(LenF,MATCH($N$7,LenU,0)))^2*(N(R120)*INDEX(LenF,MATCH($R$7,LenU,0))),INDEX(HeadK,MATCH(Q120,HeadU,0))*(N120*INDEX(LenF,MATCH($N$7,LenU,0)))^3)),0))) | AF120: =IF(E120<>"Piping","",IF(AND(ISNUMBER(AS120),ISNUMBER(M120)),PI()/4*(AS120/1000)^2*M120*INDEX(LenF,MATCH($M$7,LenU,0)),0)) | AG120: =IF(E120="","",N(AD120)+N(AE120)+N(AF120)) | AH120: =IF(ISNUMBER(I120),I120*INDEX(WtF,MATCH($I$7,WtU,0))/CC_WaterRho,"") | AM120: =IF(AO120="","",AO120*IF(ISNUMBER(AK120),AK120,CC_DefFills)*(1+IF(ISNUMBER(AL120),AL120,CC_DefAllow))) | AN120: =IF(G120="Given volume",IF(ISNUMBER(H120),H120*INDEX(VolF,MATCH($H$7,VolU,0)),""),IF(G120="Water weight",AH120,IF(N(AG120)=0,"",AG120))) | AO120: =IF(N(AN120)=0,"",AN120*AT120*IF(ISNUMBER(AJ120),AJ120,CC_DefCirc)) | AP120: =IF(ISNUMBER(T120),T120*INDEX(LenF,MATCH($T$7,LenU,0)),IF(ISNUMBER(W120),W120*INDEX(LenF,MATCH($W$7,LenU,0))/CC_PitchRatio,0)) -> 0 | AQ120: =IF(ISNUMBER(N120),PI()/4*(N120*INDEX(LenF,MATCH($N$7,LenU,0)))^2,IF(AND(ISNUMBER(S120),ISNUMBER(W120),X120<>""),S120*(W120*INDEX(LenF,MATCH($W$7,LenU,0)))^2*INDEX(LayoutF,MATCH(X120,LayoutU,0)),0)) -> 0 | AR120: =IF(ISNUMBER(O120),O120*INDEX(LenF,MATCH($O$7,LenU,0)),IF(ISNUMBER(V120),V120*INDEX(LenF,MATCH($V$7,LenU,0)),0)) -> 0 | AS120: =IF(ISNUMBER(L120),L120*INDEX(LenF,MATCH($L$7,LenU,0))*1000,IF(OR(J120="",K120=""),"",IFERROR(IF(INDEX(PipeWT,MATCH(J120,NPSU,0),MATCH(K120,SchU,0))="","Sch n/a",INDEX(PipeOD,MATCH(J120,NPSU,0))-2*INDEX(PipeWT,MATCH(J120,NPSU,0),MATCH(K120,SchU,0))),""))) | AT120: =IF(ISNUMBER(AI120),AI120,IFERROR(INDEX(IF(CC_JobType="Decontamination",CC_TypeFillDC,CC_TypeFillCC),MATCH(E120,CC_TypeL,0)),1)) -> 1 | AU120: 4
... A138: 30 | AD138: =IF(E138="Exchanger",IF(AND(ISNUMBER(S138),ISNUMBER(U138),ISNUMBER(V138)),S138*PI()/4*(U138*INDEX(LenF,MATCH($U$7,LenU,0)))^2*V138*INDEX(LenF,MATCH($V$7,LenU,0)),0)+IF(ISNUMBER(Y138),PI()/4*(Y138*INDEX(LenF,MATCH($Y$7,LenU,0)))^2*N(Z138)*INDEX(LenF,MATCH($Z$7,LenU,0))+IF(AA138="",0,IF(AA138="Conical",PI()/12*(Y138*INDEX(LenF,MATCH($Y$7,LenU,0)))^2*(0),INDEX(HeadK,MATCH(AA138,HeadU,0))*(Y138*INDEX(LenF,MATCH($Y$7,LenU,0)))^3)),0)+IF(ISNUMBER(Y138),PI()/4*(Y138*INDEX(LenF,MATCH($Y$7,LenU,0)))^2*N(AB138)*INDEX(LenF,MATCH($AB$7,LenU,0))+IF(AC138="",0,IF(AC138="Conical",PI()/12*(Y138*INDEX(LenF,MATCH($Y$7,LenU,0)))^2*(0),INDEX(HeadK,MATCH(AC138,HeadU,0))*(Y138*INDEX(LenF,MATCH($Y$7,LenU,0)))^3)),0),"") | AE138: =IF(OR(E138="",E138="Piping"),"",IF(E138="Exchanger",AQ138*AR138+IF(P138="",0,IF(P138="Conical",PI()/12*(SQRT(4*AQ138/PI()))^2*(0),INDEX(HeadK,MATCH(P138,HeadU,0))*(SQRT(4*AQ138/PI()))^3))-IF(AND(ISNUMBER(S138),ISNUMBER(V138)),S138*PI()/4*AP138^2*V138*INDEX(LenF,MATCH($V$7,LenU,0)),0),IF(ISNUMBER(N138),PI()/4*(N138*INDEX(LenF,MATCH($N$7,LenU,0)))^2*N(O138)*INDEX(LenF,MATCH($O$7,LenU,0))+IF(P138="",0,IF(P138="Conical",PI()/12*(N138*INDEX(LenF,MATCH($N$7,LenU,0)))^2*(N(R138)*INDEX(LenF,MATCH($R$7,LenU,0))),INDEX(HeadK,MATCH(P138,HeadU,0))*(N138*INDEX(LenF,MATCH($N$7,LenU,0)))^3))+IF(Q138="",0,IF(Q138="Conical",PI()/12*(N138*INDEX(LenF,MATCH($N$7,LenU,0)))^2*(N(R138)*INDEX(LenF,MATCH($R$7,LenU,0))),INDEX(HeadK,MATCH(Q138,HeadU,0))*(N138*INDEX(LenF,MATCH($N$7,LenU,0)))^3)),0))) | AF138: =IF(E138<>"Piping","",IF(AND(ISNUMBER(AS138),ISNUMBER(M138)),PI()/4*(AS138/1000)^2*M138*INDEX(LenF,MATCH($M$7,LenU,0)),0)) | AG138: =IF(E138="","",N(AD138)+N(AE138)+N(AF138)) | AH138: =IF(ISNUMBER(I138),I138*INDEX(WtF,MATCH($I$7,WtU,0))/CC_WaterRho,"") | AM138: =IF(AO138="","",AO138*IF(ISNUMBER(AK138),AK138,CC_DefFills)*(1+IF(ISNUMBER(AL138),AL138,CC_DefAllow))) | AN138: =IF(G138="Given volume",IF(ISNUMBER(H138),H138*INDEX(VolF,MATCH($H$7,VolU,0)),""),IF(G138="Water weight",AH138,IF(N(AG138)=0,"",AG138))) | AO138: =IF(N(AN138)=0,"",AN138*AT138*IF(ISNUMBER(AJ138),AJ138,CC_DefCirc)) | AP138: =IF(ISNUMBER(T138),T138*INDEX(LenF,MATCH($T$7,LenU,0)),IF(ISNUMBER(W138),W138*INDEX(LenF,MATCH($W$7,LenU,0))/CC_PitchRatio,0)) -> 0 | AQ138: =IF(ISNUMBER(N138),PI()/4*(N138*INDEX(LenF,MATCH($N$7,LenU,0)))^2,IF(AND(ISNUMBER(S138),ISNUMBER(W138),X138<>""),S138*(W138*INDEX(LenF,MATCH($W$7,LenU,0)))^2*INDEX(LayoutF,MATCH(X138,LayoutU,0)),0)) -> 0 | AR138: =IF(ISNUMBER(O138),O138*INDEX(LenF,MATCH($O$7,LenU,0)),IF(ISNUMBER(V138),V138*INDEX(LenF,MATCH($V$7,LenU,0)),0)) -> 0 | AS138: =IF(ISNUMBER(L138),L138*INDEX(LenF,MATCH($L$7,LenU,0))*1000,IF(OR(J138="",K138=""),"",IFERROR(IF(INDEX(PipeWT,MATCH(J138,NPSU,0),MATCH(K138,SchU,0))="","Sch n/a",INDEX(PipeOD,MATCH(J138,NPSU,0))-2*INDEX(PipeWT,MATCH(J138,NPSU,0),MATCH(K138,SchU,0))),""))) | AT138: =IF(ISNUMBER(AI138),AI138,IFERROR(INDEX(IF(CC_JobType="Decontamination",CC_TypeFillDC,CC_TypeFillCC),MATCH(E138,CC_TypeL,0)),1)) -> 1 | AU138: 4
A139: ="TOTAL – "&INDEX(CC_UnitNames,4) -> TOTAL – Unit 4 | S139: =COUNT(AN109:AN138)&" items" -> 0 items | AD139: =SUM(AD109:AD138) -> 0 | AE139: =SUM(AE109:AE138) -> 0 | AF139: =SUM(AF109:AF138) -> 0 | AG139: =SUM(AG109:AG138) -> 0 | AH139: =SUM(AH109:AH138) -> 0 | AM139: =SUM(AM109:AM138) -> 0 | AN139: =SUM(AN109:AN138) -> 0 | AO139: =SUM(AO109:AO138) -> 0
A141: ="UNIT 5: "&INDEX(CC_UnitNames,5) -> UNIT 5: Unit 5
A142: 1 | AD142: =IF(E142="Exchanger",IF(AND(ISNUMBER(S142),ISNUMBER(U142),ISNUMBER(V142)),S142*PI()/4*(U142*INDEX(LenF,MATCH($U$7,LenU,0)))^2*V142*INDEX(LenF,MATCH($V$7,LenU,0)),0)+IF(ISNUMBER(Y142),PI()/4*(Y142*INDEX(LenF,MATCH($Y$7,LenU,0)))^2*N(Z142)*INDEX(LenF,MATCH($Z$7,LenU,0))+IF(AA142="",0,IF(AA142="Conical",PI()/12*(Y142*INDEX(LenF,MATCH($Y$7,LenU,0)))^2*(0),INDEX(HeadK,MATCH(AA142,HeadU,0))*(Y142*INDEX(LenF,MATCH($Y$7,LenU,0)))^3)),0)+IF(ISNUMBER(Y142),PI()/4*(Y142*INDEX(LenF,MATCH($Y$7,LenU,0)))^2*N(AB142)*INDEX(LenF,MATCH($AB$7,LenU,0))+IF(AC142="",0,IF(AC142="Conical",PI()/12*(Y142*INDEX(LenF,MATCH($Y$7,LenU,0)))^2*(0),INDEX(HeadK,MATCH(AC142,HeadU,0))*(Y142*INDEX(LenF,MATCH($Y$7,LenU,0)))^3)),0),"") | AE142: =IF(OR(E142="",E142="Piping"),"",IF(E142="Exchanger",AQ142*AR142+IF(P142="",0,IF(P142="Conical",PI()/12*(SQRT(4*AQ142/PI()))^2*(0),INDEX(HeadK,MATCH(P142,HeadU,0))*(SQRT(4*AQ142/PI()))^3))-IF(AND(ISNUMBER(S142),ISNUMBER(V142)),S142*PI()/4*AP142^2*V142*INDEX(LenF,MATCH($V$7,LenU,0)),0),IF(ISNUMBER(N142),PI()/4*(N142*INDEX(LenF,MATCH($N$7,LenU,0)))^2*N(O142)*INDEX(LenF,MATCH($O$7,LenU,0))+IF(P142="",0,IF(P142="Conical",PI()/12*(N142*INDEX(LenF,MATCH($N$7,LenU,0)))^2*(N(R142)*INDEX(LenF,MATCH($R$7,LenU,0))),INDEX(HeadK,MATCH(P142,HeadU,0))*(N142*INDEX(LenF,MATCH($N$7,LenU,0)))^3))+IF(Q142="",0,IF(Q142="Conical",PI()/12*(N142*INDEX(LenF,MATCH($N$7,LenU,0)))^2*(N(R142)*INDEX(LenF,MATCH($R$7,LenU,0))),INDEX(HeadK,MATCH(Q142,HeadU,0))*(N142*INDEX(LenF,MATCH($N$7,LenU,0)))^3)),0))) | AF142: =IF(E142<>"Piping","",IF(AND(ISNUMBER(AS142),ISNUMBER(M142)),PI()/4*(AS142/1000)^2*M142*INDEX(LenF,MATCH($M$7,LenU,0)),0)) | AG142: =IF(E142="","",N(AD142)+N(AE142)+N(AF142)) | AH142: =IF(ISNUMBER(I142),I142*INDEX(WtF,MATCH($I$7,WtU,0))/CC_WaterRho,"") | AM142: =IF(AO142="","",AO142*IF(ISNUMBER(AK142),AK142,CC_DefFills)*(1+IF(ISNUMBER(AL142),AL142,CC_DefAllow))) | AN142: =IF(G142="Given volume",IF(ISNUMBER(H142),H142*INDEX(VolF,MATCH($H$7,VolU,0)),""),IF(G142="Water weight",AH142,IF(N(AG142)=0,"",AG142))) | AO142: =IF(N(AN142)=0,"",AN142*AT142*IF(ISNUMBER(AJ142),AJ142,CC_DefCirc)) | AP142: =IF(ISNUMBER(T142),T142*INDEX(LenF,MATCH($T$7,LenU,0)),IF(ISNUMBER(W142),W142*INDEX(LenF,MATCH($W$7,LenU,0))/CC_PitchRatio,0)) -> 0 | AQ142: =IF(ISNUMBER(N142),PI()/4*(N142*INDEX(LenF,MATCH($N$7,LenU,0)))^2,IF(AND(ISNUMBER(S142),ISNUMBER(W142),X142<>""),S142*(W142*INDEX(LenF,MATCH($W$7,LenU,0)))^2*INDEX(LayoutF,MATCH(X142,LayoutU,0)),0)) -> 0 | AR142: =IF(ISNUMBER(O142),O142*INDEX(LenF,MATCH($O$7,LenU,0)),IF(ISNUMBER(V142),V142*INDEX(LenF,MATCH($V$7,LenU,0)),0)) -> 0 | AS142: =IF(ISNUMBER(L142),L142*INDEX(LenF,MATCH($L$7,LenU,0))*1000,IF(OR(J142="",K142=""),"",IFERROR(IF(INDEX(PipeWT,MATCH(J142,NPSU,0),MATCH(K142,SchU,0))="","Sch n/a",INDEX(PipeOD,MATCH(J142,NPSU,0))-2*INDEX(PipeWT,MATCH(J142,NPSU,0),MATCH(K142,SchU,0))),""))) | AT142: =IF(ISNUMBER(AI142),AI142,IFERROR(INDEX(IF(CC_JobType="Decontamination",CC_TypeFillDC,CC_TypeFillCC),MATCH(E142,CC_TypeL,0)),1)) -> 1 | AU142: 5
A143: 2 | AD143: =IF(E143="Exchanger",IF(AND(ISNUMBER(S143),ISNUMBER(U143),ISNUMBER(V143)),S143*PI()/4*(U143*INDEX(LenF,MATCH($U$7,LenU,0)))^2*V143*INDEX(LenF,MATCH($V$7,LenU,0)),0)+IF(ISNUMBER(Y143),PI()/4*(Y143*INDEX(LenF,MATCH($Y$7,LenU,0)))^2*N(Z143)*INDEX(LenF,MATCH($Z$7,LenU,0))+IF(AA143="",0,IF(AA143="Conical",PI()/12*(Y143*INDEX(LenF,MATCH($Y$7,LenU,0)))^2*(0),INDEX(HeadK,MATCH(AA143,HeadU,0))*(Y143*INDEX(LenF,MATCH($Y$7,LenU,0)))^3)),0)+IF(ISNUMBER(Y143),PI()/4*(Y143*INDEX(LenF,MATCH($Y$7,LenU,0)))^2*N(AB143)*INDEX(LenF,MATCH($AB$7,LenU,0))+IF(AC143="",0,IF(AC143="Conical",PI()/12*(Y143*INDEX(LenF,MATCH($Y$7,LenU,0)))^2*(0),INDEX(HeadK,MATCH(AC143,HeadU,0))*(Y143*INDEX(LenF,MATCH($Y$7,LenU,0)))^3)),0),"") | AE143: =IF(OR(E143="",E143="Piping"),"",IF(E143="Exchanger",AQ143*AR143+IF(P143="",0,IF(P143="Conical",PI()/12*(SQRT(4*AQ143/PI()))^2*(0),INDEX(HeadK,MATCH(P143,HeadU,0))*(SQRT(4*AQ143/PI()))^3))-IF(AND(ISNUMBER(S143),ISNUMBER(V143)),S143*PI()/4*AP143^2*V143*INDEX(LenF,MATCH($V$7,LenU,0)),0),IF(ISNUMBER(N143),PI()/4*(N143*INDEX(LenF,MATCH($N$7,LenU,0)))^2*N(O143)*INDEX(LenF,MATCH($O$7,LenU,0))+IF(P143="",0,IF(P143="Conical",PI()/12*(N143*INDEX(LenF,MATCH($N$7,LenU,0)))^2*(N(R143)*INDEX(LenF,MATCH($R$7,LenU,0))),INDEX(HeadK,MATCH(P143,HeadU,0))*(N143*INDEX(LenF,MATCH($N$7,LenU,0)))^3))+IF(Q143="",0,IF(Q143="Conical",PI()/12*(N143*INDEX(LenF,MATCH($N$7,LenU,0)))^2*(N(R143)*INDEX(LenF,MATCH($R$7,LenU,0))),INDEX(HeadK,MATCH(Q143,HeadU,0))*(N143*INDEX(LenF,MATCH($N$7,LenU,0)))^3)),0))) | AF143: =IF(E143<>"Piping","",IF(AND(ISNUMBER(AS143),ISNUMBER(M143)),PI()/4*(AS143/1000)^2*M143*INDEX(LenF,MATCH($M$7,LenU,0)),0)) | AG143: =IF(E143="","",N(AD143)+N(AE143)+N(AF143)) | AH143: =IF(ISNUMBER(I143),I143*INDEX(WtF,MATCH($I$7,WtU,0))/CC_WaterRho,"") | AM143: =IF(AO143="","",AO143*IF(ISNUMBER(AK143),AK143,CC_DefFills)*(1+IF(ISNUMBER(AL143),AL143,CC_DefAllow))) | AN143: =IF(G143="Given volume",IF(ISNUMBER(H143),H143*INDEX(VolF,MATCH($H$7,VolU,0)),""),IF(G143="Water weight",AH143,IF(N(AG143)=0,"",AG143))) | AO143: =IF(N(AN143)=0,"",AN143*AT143*IF(ISNUMBER(AJ143),AJ143,CC_DefCirc)) | AP143: =IF(ISNUMBER(T143),T143*INDEX(LenF,MATCH($T$7,LenU,0)),IF(ISNUMBER(W143),W143*INDEX(LenF,MATCH($W$7,LenU,0))/CC_PitchRatio,0)) -> 0 | AQ143: =IF(ISNUMBER(N143),PI()/4*(N143*INDEX(LenF,MATCH($N$7,LenU,0)))^2,IF(AND(ISNUMBER(S143),ISNUMBER(W143),X143<>""),S143*(W143*INDEX(LenF,MATCH($W$7,LenU,0)))^2*INDEX(LayoutF,MATCH(X143,LayoutU,0)),0)) -> 0 | AR143: =IF(ISNUMBER(O143),O143*INDEX(LenF,MATCH($O$7,LenU,0)),IF(ISNUMBER(V143),V143*INDEX(LenF,MATCH($V$7,LenU,0)),0)) -> 0 | AS143: =IF(ISNUMBER(L143),L143*INDEX(LenF,MATCH($L$7,LenU,0))*1000,IF(OR(J143="",K143=""),"",IFERROR(IF(INDEX(PipeWT,MATCH(J143,NPSU,0),MATCH(K143,SchU,0))="","Sch n/a",INDEX(PipeOD,MATCH(J143,NPSU,0))-2*INDEX(PipeWT,MATCH(J143,NPSU,0),MATCH(K143,SchU,0))),""))) | AT143: =IF(ISNUMBER(AI143),AI143,IFERROR(INDEX(IF(CC_JobType="Decontamination",CC_TypeFillDC,CC_TypeFillCC),MATCH(E143,CC_TypeL,0)),1)) -> 1 | AU143: 5
A144: 3 | AD144: =IF(E144="Exchanger",IF(AND(ISNUMBER(S144),ISNUMBER(U144),ISNUMBER(V144)),S144*PI()/4*(U144*INDEX(LenF,MATCH($U$7,LenU,0)))^2*V144*INDEX(LenF,MATCH($V$7,LenU,0)),0)+IF(ISNUMBER(Y144),PI()/4*(Y144*INDEX(LenF,MATCH($Y$7,LenU,0)))^2*N(Z144)*INDEX(LenF,MATCH($Z$7,LenU,0))+IF(AA144="",0,IF(AA144="Conical",PI()/12*(Y144*INDEX(LenF,MATCH($Y$7,LenU,0)))^2*(0),INDEX(HeadK,MATCH(AA144,HeadU,0))*(Y144*INDEX(LenF,MATCH($Y$7,LenU,0)))^3)),0)+IF(ISNUMBER(Y144),PI()/4*(Y144*INDEX(LenF,MATCH($Y$7,LenU,0)))^2*N(AB144)*INDEX(LenF,MATCH($AB$7,LenU,0))+IF(AC144="",0,IF(AC144="Conical",PI()/12*(Y144*INDEX(LenF,MATCH($Y$7,LenU,0)))^2*(0),INDEX(HeadK,MATCH(AC144,HeadU,0))*(Y144*INDEX(LenF,MATCH($Y$7,LenU,0)))^3)),0),"") | AE144: =IF(OR(E144="",E144="Piping"),"",IF(E144="Exchanger",AQ144*AR144+IF(P144="",0,IF(P144="Conical",PI()/12*(SQRT(4*AQ144/PI()))^2*(0),INDEX(HeadK,MATCH(P144,HeadU,0))*(SQRT(4*AQ144/PI()))^3))-IF(AND(ISNUMBER(S144),ISNUMBER(V144)),S144*PI()/4*AP144^2*V144*INDEX(LenF,MATCH($V$7,LenU,0)),0),IF(ISNUMBER(N144),PI()/4*(N144*INDEX(LenF,MATCH($N$7,LenU,0)))^2*N(O144)*INDEX(LenF,MATCH($O$7,LenU,0))+IF(P144="",0,IF(P144="Conical",PI()/12*(N144*INDEX(LenF,MATCH($N$7,LenU,0)))^2*(N(R144)*INDEX(LenF,MATCH($R$7,LenU,0))),INDEX(HeadK,MATCH(P144,HeadU,0))*(N144*INDEX(LenF,MATCH($N$7,LenU,0)))^3))+IF(Q144="",0,IF(Q144="Conical",PI()/12*(N144*INDEX(LenF,MATCH($N$7,LenU,0)))^2*(N(R144)*INDEX(LenF,MATCH($R$7,LenU,0))),INDEX(HeadK,MATCH(Q144,HeadU,0))*(N144*INDEX(LenF,MATCH($N$7,LenU,0)))^3)),0))) | AF144: =IF(E144<>"Piping","",IF(AND(ISNUMBER(AS144),ISNUMBER(M144)),PI()/4*(AS144/1000)^2*M144*INDEX(LenF,MATCH($M$7,LenU,0)),0)) | AG144: =IF(E144="","",N(AD144)+N(AE144)+N(AF144)) | AH144: =IF(ISNUMBER(I144),I144*INDEX(WtF,MATCH($I$7,WtU,0))/CC_WaterRho,"") | AM144: =IF(AO144="","",AO144*IF(ISNUMBER(AK144),AK144,CC_DefFills)*(1+IF(ISNUMBER(AL144),AL144,CC_DefAllow))) | AN144: =IF(G144="Given volume",IF(ISNUMBER(H144),H144*INDEX(VolF,MATCH($H$7,VolU,0)),""),IF(G144="Water weight",AH144,IF(N(AG144)=0,"",AG144))) | AO144: =IF(N(AN144)=0,"",AN144*AT144*IF(ISNUMBER(AJ144),AJ144,CC_DefCirc)) | AP144: =IF(ISNUMBER(T144),T144*INDEX(LenF,MATCH($T$7,LenU,0)),IF(ISNUMBER(W144),W144*INDEX(LenF,MATCH($W$7,LenU,0))/CC_PitchRatio,0)) -> 0 | AQ144: =IF(ISNUMBER(N144),PI()/4*(N144*INDEX(LenF,MATCH($N$7,LenU,0)))^2,IF(AND(ISNUMBER(S144),ISNUMBER(W144),X144<>""),S144*(W144*INDEX(LenF,MATCH($W$7,LenU,0)))^2*INDEX(LayoutF,MATCH(X144,LayoutU,0)),0)) -> 0 | AR144: =IF(ISNUMBER(O144),O144*INDEX(LenF,MATCH($O$7,LenU,0)),IF(ISNUMBER(V144),V144*INDEX(LenF,MATCH($V$7,LenU,0)),0)) -> 0 | AS144: =IF(ISNUMBER(L144),L144*INDEX(LenF,MATCH($L$7,LenU,0))*1000,IF(OR(J144="",K144=""),"",IFERROR(IF(INDEX(PipeWT,MATCH(J144,NPSU,0),MATCH(K144,SchU,0))="","Sch n/a",INDEX(PipeOD,MATCH(J144,NPSU,0))-2*INDEX(PipeWT,MATCH(J144,NPSU,0),MATCH(K144,SchU,0))),""))) | AT144: =IF(ISNUMBER(AI144),AI144,IFERROR(INDEX(IF(CC_JobType="Decontamination",CC_TypeFillDC,CC_TypeFillCC),MATCH(E144,CC_TypeL,0)),1)) -> 1 | AU144: 5
A145: 4 | AD145: =IF(E145="Exchanger",IF(AND(ISNUMBER(S145),ISNUMBER(U145),ISNUMBER(V145)),S145*PI()/4*(U145*INDEX(LenF,MATCH($U$7,LenU,0)))^2*V145*INDEX(LenF,MATCH($V$7,LenU,0)),0)+IF(ISNUMBER(Y145),PI()/4*(Y145*INDEX(LenF,MATCH($Y$7,LenU,0)))^2*N(Z145)*INDEX(LenF,MATCH($Z$7,LenU,0))+IF(AA145="",0,IF(AA145="Conical",PI()/12*(Y145*INDEX(LenF,MATCH($Y$7,LenU,0)))^2*(0),INDEX(HeadK,MATCH(AA145,HeadU,0))*(Y145*INDEX(LenF,MATCH($Y$7,LenU,0)))^3)),0)+IF(ISNUMBER(Y145),PI()/4*(Y145*INDEX(LenF,MATCH($Y$7,LenU,0)))^2*N(AB145)*INDEX(LenF,MATCH($AB$7,LenU,0))+IF(AC145="",0,IF(AC145="Conical",PI()/12*(Y145*INDEX(LenF,MATCH($Y$7,LenU,0)))^2*(0),INDEX(HeadK,MATCH(AC145,HeadU,0))*(Y145*INDEX(LenF,MATCH($Y$7,LenU,0)))^3)),0),"") | AE145: =IF(OR(E145="",E145="Piping"),"",IF(E145="Exchanger",AQ145*AR145+IF(P145="",0,IF(P145="Conical",PI()/12*(SQRT(4*AQ145/PI()))^2*(0),INDEX(HeadK,MATCH(P145,HeadU,0))*(SQRT(4*AQ145/PI()))^3))-IF(AND(ISNUMBER(S145),ISNUMBER(V145)),S145*PI()/4*AP145^2*V145*INDEX(LenF,MATCH($V$7,LenU,0)),0),IF(ISNUMBER(N145),PI()/4*(N145*INDEX(LenF,MATCH($N$7,LenU,0)))^2*N(O145)*INDEX(LenF,MATCH($O$7,LenU,0))+IF(P145="",0,IF(P145="Conical",PI()/12*(N145*INDEX(LenF,MATCH($N$7,LenU,0)))^2*(N(R145)*INDEX(LenF,MATCH($R$7,LenU,0))),INDEX(HeadK,MATCH(P145,HeadU,0))*(N145*INDEX(LenF,MATCH($N$7,LenU,0)))^3))+IF(Q145="",0,IF(Q145="Conical",PI()/12*(N145*INDEX(LenF,MATCH($N$7,LenU,0)))^2*(N(R145)*INDEX(LenF,MATCH($R$7,LenU,0))),INDEX(HeadK,MATCH(Q145,HeadU,0))*(N145*INDEX(LenF,MATCH($N$7,LenU,0)))^3)),0))) | AF145: =IF(E145<>"Piping","",IF(AND(ISNUMBER(AS145),ISNUMBER(M145)),PI()/4*(AS145/1000)^2*M145*INDEX(LenF,MATCH($M$7,LenU,0)),0)) | AG145: =IF(E145="","",N(AD145)+N(AE145)+N(AF145)) | AH145: =IF(ISNUMBER(I145),I145*INDEX(WtF,MATCH($I$7,WtU,0))/CC_WaterRho,"") | AM145: =IF(AO145="","",AO145*IF(ISNUMBER(AK145),AK145,CC_DefFills)*(1+IF(ISNUMBER(AL145),AL145,CC_DefAllow))) | AN145: =IF(G145="Given volume",IF(ISNUMBER(H145),H145*INDEX(VolF,MATCH($H$7,VolU,0)),""),IF(G145="Water weight",AH145,IF(N(AG145)=0,"",AG145))) | AO145: =IF(N(AN145)=0,"",AN145*AT145*IF(ISNUMBER(AJ145),AJ145,CC_DefCirc)) | AP145: =IF(ISNUMBER(T145),T145*INDEX(LenF,MATCH($T$7,LenU,0)),IF(ISNUMBER(W145),W145*INDEX(LenF,MATCH($W$7,LenU,0))/CC_PitchRatio,0)) -> 0 | AQ145: =IF(ISNUMBER(N145),PI()/4*(N145*INDEX(LenF,MATCH($N$7,LenU,0)))^2,IF(AND(ISNUMBER(S145),ISNUMBER(W145),X145<>""),S145*(W145*INDEX(LenF,MATCH($W$7,LenU,0)))^2*INDEX(LayoutF,MATCH(X145,LayoutU,0)),0)) -> 0 | AR145: =IF(ISNUMBER(O145),O145*INDEX(LenF,MATCH($O$7,LenU,0)),IF(ISNUMBER(V145),V145*INDEX(LenF,MATCH($V$7,LenU,0)),0)) -> 0 | AS145: =IF(ISNUMBER(L145),L145*INDEX(LenF,MATCH($L$7,LenU,0))*1000,IF(OR(J145="",K145=""),"",IFERROR(IF(INDEX(PipeWT,MATCH(J145,NPSU,0),MATCH(K145,SchU,0))="","Sch n/a",INDEX(PipeOD,MATCH(J145,NPSU,0))-2*INDEX(PipeWT,MATCH(J145,NPSU,0),MATCH(K145,SchU,0))),""))) | AT145: =IF(ISNUMBER(AI145),AI145,IFERROR(INDEX(IF(CC_JobType="Decontamination",CC_TypeFillDC,CC_TypeFillCC),MATCH(E145,CC_TypeL,0)),1)) -> 1 | AU145: 5
A146: 5 | AD146: =IF(E146="Exchanger",IF(AND(ISNUMBER(S146),ISNUMBER(U146),ISNUMBER(V146)),S146*PI()/4*(U146*INDEX(LenF,MATCH($U$7,LenU,0)))^2*V146*INDEX(LenF,MATCH($V$7,LenU,0)),0)+IF(ISNUMBER(Y146),PI()/4*(Y146*INDEX(LenF,MATCH($Y$7,LenU,0)))^2*N(Z146)*INDEX(LenF,MATCH($Z$7,LenU,0))+IF(AA146="",0,IF(AA146="Conical",PI()/12*(Y146*INDEX(LenF,MATCH($Y$7,LenU,0)))^2*(0),INDEX(HeadK,MATCH(AA146,HeadU,0))*(Y146*INDEX(LenF,MATCH($Y$7,LenU,0)))^3)),0)+IF(ISNUMBER(Y146),PI()/4*(Y146*INDEX(LenF,MATCH($Y$7,LenU,0)))^2*N(AB146)*INDEX(LenF,MATCH($AB$7,LenU,0))+IF(AC146="",0,IF(AC146="Conical",PI()/12*(Y146*INDEX(LenF,MATCH($Y$7,LenU,0)))^2*(0),INDEX(HeadK,MATCH(AC146,HeadU,0))*(Y146*INDEX(LenF,MATCH($Y$7,LenU,0)))^3)),0),"") | AE146: =IF(OR(E146="",E146="Piping"),"",IF(E146="Exchanger",AQ146*AR146+IF(P146="",0,IF(P146="Conical",PI()/12*(SQRT(4*AQ146/PI()))^2*(0),INDEX(HeadK,MATCH(P146,HeadU,0))*(SQRT(4*AQ146/PI()))^3))-IF(AND(ISNUMBER(S146),ISNUMBER(V146)),S146*PI()/4*AP146^2*V146*INDEX(LenF,MATCH($V$7,LenU,0)),0),IF(ISNUMBER(N146),PI()/4*(N146*INDEX(LenF,MATCH($N$7,LenU,0)))^2*N(O146)*INDEX(LenF,MATCH($O$7,LenU,0))+IF(P146="",0,IF(P146="Conical",PI()/12*(N146*INDEX(LenF,MATCH($N$7,LenU,0)))^2*(N(R146)*INDEX(LenF,MATCH($R$7,LenU,0))),INDEX(HeadK,MATCH(P146,HeadU,0))*(N146*INDEX(LenF,MATCH($N$7,LenU,0)))^3))+IF(Q146="",0,IF(Q146="Conical",PI()/12*(N146*INDEX(LenF,MATCH($N$7,LenU,0)))^2*(N(R146)*INDEX(LenF,MATCH($R$7,LenU,0))),INDEX(HeadK,MATCH(Q146,HeadU,0))*(N146*INDEX(LenF,MATCH($N$7,LenU,0)))^3)),0))) | AF146: =IF(E146<>"Piping","",IF(AND(ISNUMBER(AS146),ISNUMBER(M146)),PI()/4*(AS146/1000)^2*M146*INDEX(LenF,MATCH($M$7,LenU,0)),0)) | AG146: =IF(E146="","",N(AD146)+N(AE146)+N(AF146)) | AH146: =IF(ISNUMBER(I146),I146*INDEX(WtF,MATCH($I$7,WtU,0))/CC_WaterRho,"") | AM146: =IF(AO146="","",AO146*IF(ISNUMBER(AK146),AK146,CC_DefFills)*(1+IF(ISNUMBER(AL146),AL146,CC_DefAllow))) | AN146: =IF(G146="Given volume",IF(ISNUMBER(H146),H146*INDEX(VolF,MATCH($H$7,VolU,0)),""),IF(G146="Water weight",AH146,IF(N(AG146)=0,"",AG146))) | AO146: =IF(N(AN146)=0,"",AN146*AT146*IF(ISNUMBER(AJ146),AJ146,CC_DefCirc)) | AP146: =IF(ISNUMBER(T146),T146*INDEX(LenF,MATCH($T$7,LenU,0)),IF(ISNUMBER(W146),W146*INDEX(LenF,MATCH($W$7,LenU,0))/CC_PitchRatio,0)) -> 0 | AQ146: =IF(ISNUMBER(N146),PI()/4*(N146*INDEX(LenF,MATCH($N$7,LenU,0)))^2,IF(AND(ISNUMBER(S146),ISNUMBER(W146),X146<>""),S146*(W146*INDEX(LenF,MATCH($W$7,LenU,0)))^2*INDEX(LayoutF,MATCH(X146,LayoutU,0)),0)) -> 0 | AR146: =IF(ISNUMBER(O146),O146*INDEX(LenF,MATCH($O$7,LenU,0)),IF(ISNUMBER(V146),V146*INDEX(LenF,MATCH($V$7,LenU,0)),0)) -> 0 | AS146: =IF(ISNUMBER(L146),L146*INDEX(LenF,MATCH($L$7,LenU,0))*1000,IF(OR(J146="",K146=""),"",IFERROR(IF(INDEX(PipeWT,MATCH(J146,NPSU,0),MATCH(K146,SchU,0))="","Sch n/a",INDEX(PipeOD,MATCH(J146,NPSU,0))-2*INDEX(PipeWT,MATCH(J146,NPSU,0),MATCH(K146,SchU,0))),""))) | AT146: =IF(ISNUMBER(AI146),AI146,IFERROR(INDEX(IF(CC_JobType="Decontamination",CC_TypeFillDC,CC_TypeFillCC),MATCH(E146,CC_TypeL,0)),1)) -> 1 | AU146: 5
A147: 6 | AD147: =IF(E147="Exchanger",IF(AND(ISNUMBER(S147),ISNUMBER(U147),ISNUMBER(V147)),S147*PI()/4*(U147*INDEX(LenF,MATCH($U$7,LenU,0)))^2*V147*INDEX(LenF,MATCH($V$7,LenU,0)),0)+IF(ISNUMBER(Y147),PI()/4*(Y147*INDEX(LenF,MATCH($Y$7,LenU,0)))^2*N(Z147)*INDEX(LenF,MATCH($Z$7,LenU,0))+IF(AA147="",0,IF(AA147="Conical",PI()/12*(Y147*INDEX(LenF,MATCH($Y$7,LenU,0)))^2*(0),INDEX(HeadK,MATCH(AA147,HeadU,0))*(Y147*INDEX(LenF,MATCH($Y$7,LenU,0)))^3)),0)+IF(ISNUMBER(Y147),PI()/4*(Y147*INDEX(LenF,MATCH($Y$7,LenU,0)))^2*N(AB147)*INDEX(LenF,MATCH($AB$7,LenU,0))+IF(AC147="",0,IF(AC147="Conical",PI()/12*(Y147*INDEX(LenF,MATCH($Y$7,LenU,0)))^2*(0),INDEX(HeadK,MATCH(AC147,HeadU,0))*(Y147*INDEX(LenF,MATCH($Y$7,LenU,0)))^3)),0),"") | AE147: =IF(OR(E147="",E147="Piping"),"",IF(E147="Exchanger",AQ147*AR147+IF(P147="",0,IF(P147="Conical",PI()/12*(SQRT(4*AQ147/PI()))^2*(0),INDEX(HeadK,MATCH(P147,HeadU,0))*(SQRT(4*AQ147/PI()))^3))-IF(AND(ISNUMBER(S147),ISNUMBER(V147)),S147*PI()/4*AP147^2*V147*INDEX(LenF,MATCH($V$7,LenU,0)),0),IF(ISNUMBER(N147),PI()/4*(N147*INDEX(LenF,MATCH($N$7,LenU,0)))^2*N(O147)*INDEX(LenF,MATCH($O$7,LenU,0))+IF(P147="",0,IF(P147="Conical",PI()/12*(N147*INDEX(LenF,MATCH($N$7,LenU,0)))^2*(N(R147)*INDEX(LenF,MATCH($R$7,LenU,0))),INDEX(HeadK,MATCH(P147,HeadU,0))*(N147*INDEX(LenF,MATCH($N$7,LenU,0)))^3))+IF(Q147="",0,IF(Q147="Conical",PI()/12*(N147*INDEX(LenF,MATCH($N$7,LenU,0)))^2*(N(R147)*INDEX(LenF,MATCH($R$7,LenU,0))),INDEX(HeadK,MATCH(Q147,HeadU,0))*(N147*INDEX(LenF,MATCH($N$7,LenU,0)))^3)),0))) | AF147: =IF(E147<>"Piping","",IF(AND(ISNUMBER(AS147),ISNUMBER(M147)),PI()/4*(AS147/1000)^2*M147*INDEX(LenF,MATCH($M$7,LenU,0)),0)) | AG147: =IF(E147="","",N(AD147)+N(AE147)+N(AF147)) | AH147: =IF(ISNUMBER(I147),I147*INDEX(WtF,MATCH($I$7,WtU,0))/CC_WaterRho,"") | AM147: =IF(AO147="","",AO147*IF(ISNUMBER(AK147),AK147,CC_DefFills)*(1+IF(ISNUMBER(AL147),AL147,CC_DefAllow))) | AN147: =IF(G147="Given volume",IF(ISNUMBER(H147),H147*INDEX(VolF,MATCH($H$7,VolU,0)),""),IF(G147="Water weight",AH147,IF(N(AG147)=0,"",AG147))) | AO147: =IF(N(AN147)=0,"",AN147*AT147*IF(ISNUMBER(AJ147),AJ147,CC_DefCirc)) | AP147: =IF(ISNUMBER(T147),T147*INDEX(LenF,MATCH($T$7,LenU,0)),IF(ISNUMBER(W147),W147*INDEX(LenF,MATCH($W$7,LenU,0))/CC_PitchRatio,0)) -> 0 | AQ147: =IF(ISNUMBER(N147),PI()/4*(N147*INDEX(LenF,MATCH($N$7,LenU,0)))^2,IF(AND(ISNUMBER(S147),ISNUMBER(W147),X147<>""),S147*(W147*INDEX(LenF,MATCH($W$7,LenU,0)))^2*INDEX(LayoutF,MATCH(X147,LayoutU,0)),0)) -> 0 | AR147: =IF(ISNUMBER(O147),O147*INDEX(LenF,MATCH($O$7,LenU,0)),IF(ISNUMBER(V147),V147*INDEX(LenF,MATCH($V$7,LenU,0)),0)) -> 0 | AS147: =IF(ISNUMBER(L147),L147*INDEX(LenF,MATCH($L$7,LenU,0))*1000,IF(OR(J147="",K147=""),"",IFERROR(IF(INDEX(PipeWT,MATCH(J147,NPSU,0),MATCH(K147,SchU,0))="","Sch n/a",INDEX(PipeOD,MATCH(J147,NPSU,0))-2*INDEX(PipeWT,MATCH(J147,NPSU,0),MATCH(K147,SchU,0))),""))) | AT147: =IF(ISNUMBER(AI147),AI147,IFERROR(INDEX(IF(CC_JobType="Decontamination",CC_TypeFillDC,CC_TypeFillCC),MATCH(E147,CC_TypeL,0)),1)) -> 1 | AU147: 5
